{"31047":{"itemCode":"31047","brand":{"name":"Bahco","slug":"bahco"},"invoices":1595,"finalPrice":30.9,"hasStock":true,"title":"Lápiz De Carpintero P-HB Bahco","family":"Herramientas","category":"Manuales","subCategory":"Lapiz carpintero","discount":0,"currency":null,"price":0,"tax":22,"unitsPerItem":"PIEZA","unitMult":25,"relatedItems":[],"shops":[{"cardCode":"401005","cardName":"Guglialmelli Oscar S.A.","cardFName":"Armeria Jabali","address2":"Paraguay 1109 y Rodo"}],"listOrder":"01280-000040","id":31047,"slug":"31047","code":"31047","subcategory":"Lapiz carpintero","images":["https://goldfarb.blob.core.windows.net/goldfarb/imagenes/31047.jpg"],"documents":[],"description":"Grafo HB  Caja de 25 pzs (venta minima)"},"31063":{"itemCode":"31063","brand":{"name":"Bahco","slug":"bahco"},"invoices":9,"finalPrice":30105.696,"hasStock":true,"title":"Conj. De Hoja Y Contra Hoja Completo  p/Tijera De Podar 9320 Bahco 9320-101-030","family":"","category":"","subCategory":"","discount":0,"currency":null,"price":0,"tax":22,"unitsPerItem":"PIEZA","unitMult":1,"relatedItems":[],"shops":[{"cardCode":"401005","cardName":"Guglialmelli Oscar S.A.","cardFName":"Armeria Jabali","address2":"Paraguay 1109 y Rodo"}],"listOrder":"04480-000480","id":31063,"slug":"31063","code":"31063","subcategory":null,"images":["https://goldfarb.blob.core.windows.net/goldfarb/imagenes/31063.jpg"],"documents":[],"description":""},"31064":{"itemCode":"31064","brand":{"name":"Bahco","slug":"bahco"},"invoices":156,"finalPrice":6109,"hasStock":false,"title":"Juego De Bocallaves Sx y Accs. Art.S240  Bahco","family":"Herramientas","category":"Manuales","subCategory":"Bocallaves y accesorios","discount":0,"currency":null,"price":0,"tax":22,"unitsPerItem":"JUEGO","unitMult":1,"relatedItems":["16622","6670","6669","6667","28384"],"shops":[{"cardCode":"401005","cardName":"Guglialmelli Oscar S.A.","cardFName":"Armeria Jabali","address2":"Paraguay 1109 y Rodo"}],"listOrder":"04420-001930","id":31064,"slug":"31064","code":"31064","subcategory":"Bocallaves y accesorios","images":["https://goldfarb.blob.core.windows.net/goldfarb/imagenes/31064.jpg"],"documents":[],"description":"Juego de dados de 1/2\"\rAleación de acero de alto rendimiento\rAcabado mate\rISO 1174\rDIN 3120\rCaja: Polietileno de alta densidad (HDPE)\rContiene 24 pzs:\r18 pzs bocallaves hexagonales 1/2\": 10, 11, 12, 13, 14, 15, 16, 17, 18, 19, 2,0 21, 22, 23, 24, 27, 30, 32 mm\r1 pz Crique 1/2\" con botón de extracción rápida, 60 dientes/ Ángulo de acción de 6º\r2 pzs Alargues de 1/2\" de 5\" y 10\"\r1 pz Junta universal 1/2\"\r1 pz Barra \"T\" deslizable de 1/2\"\r1 pz Mango articulado con mango bi-componente de 1/2\", 10\"\r1 pz Caja de plástico dividida en 3 secciones"},"31068":{"itemCode":"31068","brand":{"name":"Bahco","slug":"bahco"},"invoices":1,"finalPrice":15381.872,"hasStock":true,"title":"Carcasa Completa  P/Tijera De Podar 9320 Bahco 9320-110-220","family":"","category":"","subCategory":"","discount":0,"currency":null,"price":0,"tax":22,"unitsPerItem":"PIEZA","unitMult":1,"relatedItems":[],"shops":[{"cardCode":"401005","cardName":"Guglialmelli Oscar S.A.","cardFName":"Armeria Jabali","address2":"Paraguay 1109 y Rodo"}],"listOrder":"04480-000470","id":31068,"slug":"31068","code":"31068","subcategory":null,"images":["https://goldfarb.blob.core.windows.net/goldfarb/imagenes/31068.jpg"],"documents":[],"description":""},"31069":{"itemCode":"31069","brand":{"name":"Bahco","slug":"bahco"},"invoices":2,"finalPrice":912,"hasStock":true,"title":"Hoja Repuesto R211P/PX/PXR P/Diestro Bahco","family":"","category":"","subCategory":"","discount":0,"currency":null,"price":0,"tax":22,"unitsPerItem":"PIEZA","unitMult":1,"relatedItems":["31071"],"shops":[{"cardCode":"401005","cardName":"Guglialmelli Oscar S.A.","cardFName":"Armeria Jabali","address2":"Paraguay 1109 y Rodo"}],"listOrder":"04480-000280","id":31069,"slug":"31069","code":"31069","subcategory":null,"images":["https://goldfarb.blob.core.windows.net/goldfarb/imagenes/31069.jpg"],"documents":[],"description":"Hoja de repuesto para tijeras: Px/ PxR N° 2, P1-20, P2-20"},"31070":{"itemCode":"31070","brand":{"name":"Bahco","slug":"bahco"},"invoices":1,"finalPrice":931,"hasStock":true,"title":"Contra Hoja R403P  Bahco PX o PXR P/Diestro","family":"","category":"","subCategory":"","discount":0,"currency":null,"price":0,"tax":22,"unitsPerItem":"PIEZA","unitMult":1,"relatedItems":[],"shops":[{"cardCode":"401005","cardName":"Guglialmelli Oscar S.A.","cardFName":"Armeria Jabali","address2":"Paraguay 1109 y Rodo"}],"listOrder":"04480-000340","id":31070,"slug":"31070","code":"31070","subcategory":null,"images":["https://goldfarb.blob.core.windows.net/goldfarb/imagenes/31070.jpg"],"documents":[],"description":""},"31071":{"itemCode":"31071","brand":{"name":"Bahco","slug":"bahco"},"invoices":1,"finalPrice":0,"hasStock":false,"title":"Hoja Repuesto R600P PX/PXR P/Zurdo Bahco","family":"","category":"","subCategory":"","discount":0,"currency":null,"price":0,"tax":22,"unitsPerItem":"PIEZA","unitMult":1,"relatedItems":["5626","5645","5652"],"shops":[{"cardCode":"401005","cardName":"Guglialmelli Oscar S.A.","cardFName":"Armeria Jabali","address2":"Paraguay 1109 y Rodo"}],"listOrder":"04480-000270","id":31071,"slug":"31071","code":"31071","subcategory":null,"images":["https://goldfarb.blob.core.windows.net/goldfarb/imagenes/31071.jpg"],"documents":[],"description":""},"31073":{"itemCode":"31073","brand":{"name":"Bahco","slug":"bahco"},"invoices":4,"finalPrice":378,"hasStock":true,"title":"Resorte R905P PX o PXR Bahco","family":"","category":"","subCategory":"","discount":0,"currency":null,"price":0,"tax":22,"unitsPerItem":"PIEZA","unitMult":1,"relatedItems":[],"shops":[{"cardCode":"401005","cardName":"Guglialmelli Oscar S.A.","cardFName":"Armeria Jabali","address2":"Paraguay 1109 y Rodo"}],"listOrder":"04480-000420","id":31073,"slug":"31073","code":"31073","subcategory":null,"images":["https://goldfarb.blob.core.windows.net/goldfarb/imagenes/31073.jpg"],"documents":[],"description":""},"31077":{"itemCode":"31077","brand":{"name":"Bahco","slug":"bahco"},"invoices":71,"finalPrice":505,"hasStock":false,"title":"Galga Profesional P/Ajustar Medidas (Incluye 26 Hojas) 1544 Bahco","family":"Herramientas","category":"Medicion","subCategory":"Galgas","discount":0,"currency":null,"price":0,"tax":22,"unitsPerItem":"PIEZA","unitMult":1,"relatedItems":["31078"],"shops":[{"cardCode":"401005","cardName":"Guglialmelli Oscar S.A.","cardFName":"Armeria Jabali","address2":"Paraguay 1109 y Rodo"}],"listOrder":"04485-000170","id":31077,"slug":"31077","code":"31077","subcategory":"Galgas","images":["https://goldfarb.blob.core.windows.net/goldfarb/imagenes/31077.jpg"],"documents":[],"description":"Galga profesional, para ajustar medidas.\r\rIncluye 26 hojas: 0.03 mm a 0.1 mm en incrementos de 0.01 y 0.10 mm a 1.0 mm en incrementos de 0.05 mm.\r\rLargo 76 mm."},"31078":{"itemCode":"31078","brand":{"name":"Bahco","slug":"bahco"},"invoices":58,"finalPrice":450,"hasStock":false,"title":"Galga Profesional P/Ajustar Medidas (Incluye 20 Hojas) 1547 Bahco","family":"Herramientas","category":"Medicion","subCategory":"Galgas","discount":0,"currency":null,"price":0,"tax":22,"unitsPerItem":"PIEZA","unitMult":1,"relatedItems":["31077"],"shops":[{"cardCode":"401005","cardName":"Guglialmelli Oscar S.A.","cardFName":"Armeria Jabali","address2":"Paraguay 1109 y Rodo"}],"listOrder":"04485-000160","id":31078,"slug":"31078","code":"31078","subcategory":"Galgas","images":["https://goldfarb.blob.core.windows.net/goldfarb/imagenes/31078.jpg"],"documents":[],"description":"Galgas profesionales para ajustar medidas.\r\rIncluye 20 hojas en tamaños de 0.05 mm a 1.00 mm.\r\rLargo 100 mm."},"31079":{"itemCode":"31079","brand":{"name":"Bahco","slug":"bahco"},"invoices":4,"finalPrice":3342,"hasStock":true,"title":"Extractores De Tres Garras 4528M1 Bahco","family":"Herramientas","category":"Manuales","subCategory":"Extractores","discount":0,"currency":null,"price":0,"tax":22,"unitsPerItem":"PIEZA","unitMult":1,"relatedItems":[],"shops":[{"cardCode":"401005","cardName":"Guglialmelli Oscar S.A.","cardFName":"Armeria Jabali","address2":"Paraguay 1109 y Rodo"}],"listOrder":"04485-000150","id":31079,"slug":"31079","code":"31079","subcategory":"Extractores","images":["https://goldfarb.blob.core.windows.net/goldfarb/imagenes/31079.jpg"],"documents":[],"description":"Extractor: 3 garras - Industria Pesada\r\rAcabado: Galvanizado\r\rMaterial: Acero especial\r\rEspecialmente diseñado para extraer rodamientos, poleas, engranajes, etc."},"31080":{"itemCode":"31080","brand":{"name":"Bahco","slug":"bahco"},"invoices":86,"finalPrice":347,"hasStock":true,"title":"Arco De Sierra 306 Bahco","family":"Herramientas","category":"Manuales","subCategory":"Arcos de sierra","discount":0,"currency":null,"price":0,"tax":22,"unitsPerItem":"PIEZA","unitMult":1,"relatedItems":[],"shops":[{"cardCode":"401005","cardName":"Guglialmelli Oscar S.A.","cardFName":"Armeria Jabali","address2":"Paraguay 1109 y Rodo"}],"listOrder":"04405-000100","id":31080,"slug":"31080","code":"31080","subcategory":"Arcos de sierra","images":["https://goldfarb.blob.core.windows.net/goldfarb/imagenes/31080.jpg"],"documents":[],"description":"Sierra para metales ligera, cómoda y fácil de usar.\r\rPasadores de montaje de la hoja de 90° alternativos para corte a ras.\r\rSe suministra con una hoja Sandflex® bi-metal de 12\" (300 mm), 24 TPI, irrompible e inastillable, con excelente capacidad de corte.\r\rLargo 47 cm.\rPeso 325 gr."},"31081":{"itemCode":"31081","brand":{"name":"Bahco","slug":"bahco"},"invoices":62,"finalPrice":1188,"hasStock":false,"title":"Juego De Destornilladores 6pzas. 606-6 Bahco","family":"Herramientas","category":"Manuales","subCategory":"Destornilladores","discount":0,"currency":null,"price":0,"tax":22,"unitsPerItem":"PIEZA","unitMult":1,"relatedItems":["31082","28381","28382","28457","28475"],"shops":[{"cardCode":"401005","cardName":"Guglialmelli Oscar S.A.","cardFName":"Armeria Jabali","address2":"Paraguay 1109 y Rodo"}],"listOrder":"04425-001040","id":31081,"slug":"31081","code":"31081","subcategory":"Destornilladores","images":["https://goldfarb.blob.core.windows.net/goldfarb/imagenes/31081.jpg"],"documents":[],"description":"Mango de 2 componentes cómodo que ofrece una transmisión de par de torsión efectiva.\r\rIdentificación sencilla gracias a las marcas del mango.\r\rAcero de aleación de vanadio de molibdeno niquelado muy duradero en el vástago y la punta.\r\rOrificio para colgar integrado.\r\rIncluye:\r\r1 Plano 5 x 100 mm\r1 Plano 6.5 x 125 mm\r1 Plano paralelo 3 x 75 mm\r1 Plano paralelo 4 x 100 mm\r1 Phillips N1 x 100 mm\r1 Phillips N2 x 125 mm"},"31082":{"itemCode":"31082","brand":{"name":"Bahco","slug":"bahco"},"invoices":31,"finalPrice":730,"hasStock":true,"title":"Juego De Destornilladores 4pzas. 602-4 Bahco","family":"","category":"","subCategory":"","discount":0,"currency":null,"price":0,"tax":22,"unitsPerItem":"PIEZA","unitMult":1,"relatedItems":["31081","28381","28382","28457","28475"],"shops":[{"cardCode":"401005","cardName":"Guglialmelli Oscar S.A.","cardFName":"Armeria Jabali","address2":"Paraguay 1109 y Rodo"}],"listOrder":"04425-001038","id":31082,"slug":"31082","code":"31082","subcategory":null,"images":["https://goldfarb.blob.core.windows.net/goldfarb/imagenes/31082.jpg"],"documents":[],"description":"Mango de 2 componentes cómodo que ofrece una transmisión de par de torsión efectiva.\r\rIdentificación sencilla gracias a las marcas del mango.\r\rAcero de aleación de vanadio de molibdeno niquelado muy duradero en el vástago y la punta.\r\rOrificio para colgar integrado.\r\rIncluye:\r\r1 Plano 5.5 x 125 mm\r1 Plano paralelo 6.5 x 150 mm\r1 Plano paralelo 3 x 100 mm\r1 Phillips N1 x 100 mm"},"31083":{"itemCode":"31083","brand":{"name":"Bahco","slug":"bahco"},"invoices":22,"finalPrice":12831.936,"hasStock":true,"title":"Juego De Llave De Impacto Neumática 1/2'' Con Accs BP815KI Bahco","family":"","category":"","subCategory":"","discount":0,"currency":null,"price":0,"tax":22,"unitsPerItem":"PIEZA","unitMult":1,"relatedItems":[],"shops":[{"cardCode":"401005","cardName":"Guglialmelli Oscar S.A.","cardFName":"Armeria Jabali","address2":"Paraguay 1109 y Rodo"}],"listOrder":"04485-000190","id":31083,"slug":"31083","code":"31083","subcategory":null,"images":["https://goldfarb.blob.core.windows.net/goldfarb/imagenes/31083.jpg"],"documents":[],"description":"Juego de llave de impacto de 1/2\".\r\rSuministrado en una caja de plástico robusta.\r\rLa bandeja de espuma encaja en el T-Module System T12 de Bahco.\r\rEncastre 1/2\rPresión de trabajo 6.3 BAR\rCaudal necesario 130 litros/minuto\rRegulación de torque nominal 320 - 620 Nm.\rTorque máximo 825 Nm.\rVelocidad en vacío 7000 rpm.\r\rContiene:\r1 pz BP815 llave de impacto de 1/2\"\rVasos impacto: 10, 11, 12, 13, 14, 15, 17, 19, 21, 22 y 24 mm\rConector macho 1/4\""},"31095":{"itemCode":"31095","brand":{"name":"Bahco","slug":"bahco"},"invoices":76,"finalPrice":46942,"hasStock":false,"title":"Exhibidor De Mechas (Incluye 25 Medidas HSS En mm.) Bahco","family":"","category":"","subCategory":"","discount":0,"currency":null,"price":0,"tax":22,"unitsPerItem":"PIEZA","unitMult":1,"relatedItems":[],"shops":[{"cardCode":"401005","cardName":"Guglialmelli Oscar S.A.","cardFName":"Armeria Jabali","address2":"Paraguay 1109 y Rodo"}],"listOrder":"04470-000100","id":31095,"slug":"31095","code":"31095","subcategory":null,"images":["https://goldfarb.blob.core.windows.net/goldfarb/imagenes/31095.jpg"],"documents":[],"description":"Exhibidor de mechas para mostrador \r\rIncluye medidas :\r\r1  -  1.5  -  2  -  2.5  -  3  -  3.5  -  4  -  4.5  -  5  -5.5  -  6  -  6.5  \r7  -  7.5  -  8  -  8.5  -  9  -  9.5  -  10  -  10.5  -  11  -  11.5  -  12\r-  12.5  -  13 mm.\r\rDimensiones 38 x 40 x 24 cm."},"31096":{"itemCode":"31096","brand":{"name":"Bahco","slug":"bahco"},"invoices":2,"finalPrice":96912,"hasStock":true,"title":"Panel Supremo 85 Pzas. Bahco","family":"Herramientas","category":"Manuales","subCategory":"Bocallaves y accesorios","discount":0,"currency":null,"price":0,"tax":22,"unitsPerItem":"PIEZA","unitMult":1,"relatedItems":[],"shops":[{"cardCode":"401005","cardName":"Guglialmelli Oscar S.A.","cardFName":"Armeria Jabali","address2":"Paraguay 1109 y Rodo"}],"listOrder":"04465-000120","id":31096,"slug":"31096","code":"31096","subcategory":"Bocallaves y accesorios","images":[],"documents":[],"description":"Panel para accesorios y bocallaves de encastre 3/4\"\r\rIncluye:\r\rDados 19 a 40 mm.\rDados 3/4\" a 2.3/8\"\rAdaptadores   727   M 1/2  H 3/4\r                      726   M 3/4  H 1/2\rMango fuerza articulado 706 18\"\rBarra fuerza 787\rCabeza crique 797\rJunta universal 776\rProlongadores   746   5\"\r                         756   10\"\r                         766   15\"\r\rDimensiones tablero 121 x 80 cm."},"31107":{"itemCode":"31107","brand":{"name":"Rongpeng","slug":"rongpeng"},"invoices":2,"finalPrice":164.512,"hasStock":true,"title":"Filtro (Por RP8619) Ref.1 Rongpeng","family":"","category":"","subCategory":"","discount":0,"currency":null,"price":0,"tax":22,"unitsPerItem":"PIEZA","unitMult":1,"relatedItems":[],"shops":[{"cardCode":"401005","cardName":"Guglialmelli Oscar S.A.","cardFName":"Armeria Jabali","address2":"Paraguay 1109 y Rodo"}],"listOrder":"00780-000120","id":31107,"slug":"31107","code":"31107","subcategory":null,"images":["https://goldfarb.blob.core.windows.net/goldfarb/imagenes/31107.jpg"],"documents":[],"description":""},"31167":{"itemCode":"31167","brand":{"name":"Gardentec","slug":"gardentec"},"invoices":814,"finalPrice":4071.672,"hasStock":true,"title":"Motosierra A Nafta 16\" 0Km. 45cc. Gardentec GTS4501-16","family":"Agro y Jardin","category":"Motosierras","subCategory":"A nafta","discount":0,"currency":null,"price":0,"tax":0,"unitsPerItem":"PIEZA","unitMult":1,"relatedItems":["31168","32035","35799"],"shops":[{"cardCode":"401005","cardName":"Guglialmelli Oscar S.A.","cardFName":"Armeria Jabali","address2":"Paraguay 1109 y Rodo"}],"listOrder":"05200-000200","id":31167,"slug":"31167","code":"31167","subcategory":"A nafta","images":["https://goldfarb.blob.core.windows.net/goldfarb/imagenes/31167.jpg"],"documents":[],"description":"Motor 2 tiempos de 45cc.\rLargo de espada 16\" ( 40 cm. ).\rLubricación automática de cadena.\rCapacidad de tanque de nafta 550 cc.\rCapacidad de tanque de aceite para cadena 260 cc.\rSistema convencional de tensión de cadena.\rPase de cadena 3/8\".\rRelación de mezcla nafta/aceite 25:1\r1 año de garantía\rEl modelo es compatible con las espadas y cadenas trilink,\rcódigos 22528 y 22523 respectivamente."},"31168":{"itemCode":"31168","brand":{"name":"Gardentec","slug":"gardentec"},"invoices":1019,"finalPrice":4277.312,"hasStock":true,"title":"Motosierra A Nafta 18\" 0Km. 45cc. Gardentec GTS4501-18","family":"Agro y Jardin","category":"Motosierras","subCategory":"A nafta","discount":0,"currency":null,"price":0,"tax":0,"unitsPerItem":"PIEZA","unitMult":1,"relatedItems":["31167","32035","35799"],"shops":[{"cardCode":"401005","cardName":"Guglialmelli Oscar S.A.","cardFName":"Armeria Jabali","address2":"Paraguay 1109 y Rodo"}],"listOrder":"05200-000210","id":31168,"slug":"31168","code":"31168","subcategory":"A nafta","images":["https://goldfarb.blob.core.windows.net/goldfarb/imagenes/31168.jpg"],"documents":[],"description":"Motor 2 tiempos de 45cc.\rLargo de espada 18\" ( 45 cm. ).\rLubricación automática de cadena.\rCapacidad de tanque de nafta 550 cc.\rCapacidad de tanque de aceite para cadena 260 cc.\rSistema convencional de tensión de cadena.\rPase de cadena 0.325\".\rRelación de mezcla nafta/aceite 25:1\r1 año de garantía\rEl modelo es compatible con las espadas y cadenas trilink,\rcódigos 22529 y 22524 respectivamente."},"31169":{"itemCode":"31169","brand":{"name":"Gardentec","slug":"gardentec"},"invoices":322,"finalPrice":3907.16,"hasStock":true,"title":"Bordeadora A Nafta 25.4cc. 0Km. Gardentec GTB2601R","family":"Agro y Jardin","category":"Bordeadoras","subCategory":"A nafta","discount":0,"currency":null,"price":0,"tax":22,"unitsPerItem":"PIEZA","unitMult":1,"relatedItems":["31174","43134","35795","31170","31172"],"shops":[{"cardCode":"401005","cardName":"Guglialmelli Oscar S.A.","cardFName":"Armeria Jabali","address2":"Paraguay 1109 y Rodo"}],"listOrder":"05200-000100","id":31169,"slug":"31169","code":"31169","subcategory":"A nafta","images":["https://goldfarb.blob.core.windows.net/goldfarb/imagenes/31169.jpg"],"documents":[],"description":"Motor de 26cc de 2 tiempos.\rVelocidad en vacío 9000 rpm.\rPeso neto 6.4 kg.\rCapacidad de tanque de nafta 0.5 litros.\rRelación de mezcla nafta/aceite 25:1\rIncluye carrete y arnés.\r1 año de garantía"},"31170":{"itemCode":"31170","brand":{"name":"Gardentec","slug":"gardentec"},"invoices":904,"finalPrice":4236.184,"hasStock":false,"title":"Desmalezadora A Nafta GTB3302U 33cc. 0Km. Gardentec","family":"Agro y Jardin","category":"Desmalezadoras","subCategory":"A nafta","discount":0,"currency":null,"price":0,"tax":0,"unitsPerItem":"PIEZA","unitMult":1,"relatedItems":["31172","35797","43134","43135"],"shops":[{"cardCode":"401005","cardName":"Guglialmelli Oscar S.A.","cardFName":"Armeria Jabali","address2":"Paraguay 1109 y Rodo"}],"listOrder":"05200-000150","id":31170,"slug":"31170","code":"31170","subcategory":"A nafta","images":["https://goldfarb.blob.core.windows.net/goldfarb/imagenes/31170.jpg"],"documents":[],"description":"Motor de 33cc de 2 tiempos.\rEmbrague automático centrifugo.\rPeso neto 8.9 kg.\rCapacidad de tanque de nafta 0.75 litros.\rRelación de mezcla nafta/aceite 25:1\rEmpuñadura tipo bicicleta.\rIncluye carrete(doble hilo), cuchilla y arnés.\r1 año de garantía"},"31172":{"itemCode":"31172","brand":{"name":"Gardentec","slug":"gardentec"},"invoices":676,"finalPrice":5182.128,"hasStock":true,"title":"Desmalezadora A Nafta GTB5222U 52cc. 0Km. Gardentec","family":"Agro y Jardin","category":"Desmalezadoras","subCategory":"A nafta","discount":0,"currency":null,"price":0,"tax":0,"unitsPerItem":"PIEZA","unitMult":1,"relatedItems":["31170","35797","43134","43135"],"shops":[{"cardCode":"401005","cardName":"Guglialmelli Oscar S.A.","cardFName":"Armeria Jabali","address2":"Paraguay 1109 y Rodo"}],"listOrder":"05200-000170","id":31172,"slug":"31172","code":"31172","subcategory":"A nafta","images":["https://goldfarb.blob.core.windows.net/goldfarb/imagenes/31172.jpg"],"documents":[],"description":"Motor de 52cc de 2 tiempos.\rEmbrague automático centrifugo.\rPeso neto 9.6 kg.\rCapacidad de tanque de nafta 1.2 litros.\rRelación de mezcla nafta/aceite 25:1\rEmpuñadura tipo bicicleta.\rRegulador de altura de arnés.\rIncluye carrete, cuchilla y arnés.\r1 año de garantía"},"31173":{"itemCode":"31173","brand":{"name":"Gardentec","slug":"gardentec"},"invoices":370,"finalPrice":4770.848,"hasStock":true,"title":"Corta Cerco A Nafta GTH2302 25.4cc. 0Km. Gardentec","family":"Agro y Jardin","category":"Corta cercos","subCategory":"A nafta","discount":0,"currency":null,"price":0,"tax":22,"unitsPerItem":"PIEZA","unitMult":1,"relatedItems":[],"shops":[{"cardCode":"401005","cardName":"Guglialmelli Oscar S.A.","cardFName":"Armeria Jabali","address2":"Paraguay 1109 y Rodo"}],"listOrder":"05200-000110","id":31173,"slug":"31173","code":"31173","subcategory":"A nafta","images":["https://goldfarb.blob.core.windows.net/goldfarb/imagenes/31173.jpg"],"documents":[],"description":"Motor 2 tiempos de 25.4 cc.\rTransmisión con embrague centrifugo.\rLargo de cuchilla 62 cm.\rDiámetro de corte máximo 20 mm.\rVelocidad en vacío 7500 rpm.\rRelación mezcla nafta/aceite 25:1\rPeso neto 8.0 kg.\r1 año de garantía."},"31174":{"itemCode":"31174","brand":{"name":"Gardentec","slug":"gardentec"},"invoices":291,"finalPrice":5428.896,"hasStock":false,"title":"Soplador-Aspirador A Nafta 31cc. 0Km. Gardentec GTV3101","family":"Agro y Jardin","category":"Sopladores","subCategory":"A nafta","discount":0,"currency":null,"price":0,"tax":22,"unitsPerItem":"PIEZA","unitMult":1,"relatedItems":[],"shops":[{"cardCode":"401005","cardName":"Guglialmelli Oscar S.A.","cardFName":"Armeria Jabali","address2":"Paraguay 1109 y Rodo"}],"listOrder":"05200-000190","id":31174,"slug":"31174","code":"31174","subcategory":"A nafta","images":["https://goldfarb.blob.core.windows.net/goldfarb/imagenes/31174.jpg"],"documents":[],"description":"Motor 2 tiempos de 30 cc.\rPotencia según ISO 8893: 1 KW\rVelocidad en vacío 7500 rpm.\rCapacidad de tanque de nafta 0.5 litros.\rRelación mezcla nafta/aceite 25:1\rVelocidad de soplador hasta 200 km/h.\rCapacidad de bolsa 40 litros.\rPeso neto 6.1 kg.\rNivel de vibración 13.78 m/s2.\rPresión sonora 84 dBA.\r2 modalidades: soplador y aspirador.\r1 año de garantía."},"31175":{"itemCode":"31175","brand":{"name":"Rongpeng","slug":"rongpeng"},"invoices":118,"finalPrice":20564,"hasStock":false,"title":"Equipo De Pintar Airless  R470N 1.1Hp. Rongpeng","family":"Pinturas","category":"Equipos de pintar","subCategory":"Airless","discount":0,"currency":null,"price":0,"tax":22,"unitsPerItem":"PIEZA","unitMult":1,"relatedItems":["31176","1548","1547","30520","1478"],"shops":[{"cardCode":"401005","cardName":"Guglialmelli Oscar S.A.","cardFName":"Armeria Jabali","address2":"Paraguay 1109 y Rodo"}],"listOrder":"00780-000030","id":31175,"slug":"31175","code":"31175","subcategory":"Airless","images":["https://goldfarb.blob.core.windows.net/goldfarb/imagenes/31175.jpg"],"documents":[],"description":"Uso profesional.\rPara todo tipo de pinturas, incluso epoxi.\rPotencia 840 W ( 1.12 HP )\rPresión máxima de trabajo 3300 PSI\rRegulador de presión \rCaudal máximo de entrega 2.1 litros por minuto\rTemperatura ambiente de trabajo 5ºC - 40ºC\rHumedad ambiente de trabajo 30% - 95%\rPresión sonora 74 dB\rPeso 14.5 Kg.\rManguera de 15 mt.\r6 meses de garantía"},"31176":{"itemCode":"31176","brand":{"name":"Rongpeng","slug":"rongpeng"},"invoices":328,"finalPrice":12955.32,"hasStock":false,"title":"Equipo De Pintar Airless  R450 1.2Hp. Rongpeng","family":"Pinturas","category":"Equipos de pintar","subCategory":"Airless","discount":0,"currency":null,"price":0,"tax":22,"unitsPerItem":"PIEZA","unitMult":1,"relatedItems":["31175","1548","1547","30520","1478"],"shops":[{"cardCode":"401005","cardName":"Guglialmelli Oscar S.A.","cardFName":"Armeria Jabali","address2":"Paraguay 1109 y Rodo"}],"listOrder":"00780-000020","id":31176,"slug":"31176","code":"31176","subcategory":"Airless","images":["https://goldfarb.blob.core.windows.net/goldfarb/imagenes/31176.jpg"],"documents":[],"description":"Uso profesional.\rCarcaza robusta metálica.\rPara todo tipo de pinturas, incluso epoxi.\rPotencia 900 W ( 1.2 HP )\rPresión máxima de trabajo 3000 PSI\rRegulador de presión \rCaudal máximo de entrega 2.2 litros por minuto\rTemperatura ambiente de trabajo 5ºC - 40ºC\rHumedad ambiente de trabajo 30% - 95%\rPresión sonora 74 dB\rPeso 14.5 Kg.\rManguera de 15 mt.\r6 meses de garantía"},"31210":{"itemCode":"31210","brand":{"name":"Hunter","slug":"hunter"},"invoices":42,"finalPrice":35.7,"hasStock":true,"title":"Mini Rodillo S/Funda Nro.10 Hunter","family":"","category":"","subCategory":"","discount":0,"currency":null,"price":0,"tax":22,"unitsPerItem":"PIEZA","unitMult":1,"relatedItems":[],"shops":[{"cardCode":"401005","cardName":"Guglialmelli Oscar S.A.","cardFName":"Armeria Jabali","address2":"Paraguay 1109 y Rodo"}],"listOrder":"01950-000370","id":31210,"slug":"31210","code":"31210","subcategory":null,"images":["https://goldfarb.blob.core.windows.net/goldfarb/imagenes/31210.jpg"],"documents":[],"description":"Rodillo de 4 cm de diametro x 10 cm de largo\rLargo total 18.5 cm"},"31214":{"itemCode":"31214","brand":{"name":"Hunter","slug":"hunter"},"invoices":29,"finalPrice":78.8,"hasStock":true,"title":"Rodillo Poliester Especial Nro.10 Hunter","family":"","category":"","subCategory":"","discount":0,"currency":null,"price":0,"tax":22,"unitsPerItem":"PIEZA","unitMult":1,"relatedItems":["31218","31219"],"shops":[{"cardCode":"401005","cardName":"Guglialmelli Oscar S.A.","cardFName":"Armeria Jabali","address2":"Paraguay 1109 y Rodo"}],"listOrder":"01950-000380","id":31214,"slug":"31214","code":"31214","subcategory":null,"images":["https://goldfarb.blob.core.windows.net/goldfarb/imagenes/31214.jpg"],"documents":[],"description":""},"31218":{"itemCode":"31218","brand":{"name":"Hunter","slug":"hunter"},"invoices":6,"finalPrice":65.1,"hasStock":true,"title":"Repuesto Rodillo Poliester Especial Nro.17 Hunter","family":"","category":"","subCategory":"","discount":0,"currency":null,"price":0,"tax":22,"unitsPerItem":"PIEZA","unitMult":1,"relatedItems":["31219","31214"],"shops":[{"cardCode":"401005","cardName":"Guglialmelli Oscar S.A.","cardFName":"Armeria Jabali","address2":"Paraguay 1109 y Rodo"}],"listOrder":"01950-000410","id":31218,"slug":"31218","code":"31218","subcategory":null,"images":["https://goldfarb.blob.core.windows.net/goldfarb/imagenes/31218.jpg"],"documents":[],"description":"Para usar con todo tipo de pinturas y superficies.\rRodillo de 6 cm de diametro x 17 cm de largo."},"31219":{"itemCode":"31219","brand":{"name":"Hunter","slug":"hunter"},"invoices":10,"finalPrice":81.9,"hasStock":true,"title":"Repuesto Rodillo Poliester Especial Nro.22 Hunter","family":"","category":"","subCategory":"","discount":0,"currency":null,"price":0,"tax":22,"unitsPerItem":"PIEZA","unitMult":1,"relatedItems":["31218","31214"],"shops":[{"cardCode":"401005","cardName":"Guglialmelli Oscar S.A.","cardFName":"Armeria Jabali","address2":"Paraguay 1109 y Rodo"}],"listOrder":"01950-000420","id":31219,"slug":"31219","code":"31219","subcategory":null,"images":["https://goldfarb.blob.core.windows.net/goldfarb/imagenes/31219.jpg"],"documents":[],"description":""},"31221":{"itemCode":"31221","brand":{"name":"Hunter","slug":"hunter"},"invoices":67,"finalPrice":110,"hasStock":true,"title":"Rodillo Simil Lana Nro.22 Hunter","family":"","category":"","subCategory":"","discount":0,"currency":null,"price":0,"tax":22,"unitsPerItem":"PIEZA","unitMult":1,"relatedItems":[],"shops":[{"cardCode":"401005","cardName":"Guglialmelli Oscar S.A.","cardFName":"Armeria Jabali","address2":"Paraguay 1109 y Rodo"}],"listOrder":"01950-000440","id":31221,"slug":"31221","code":"31221","subcategory":null,"images":["https://goldfarb.blob.core.windows.net/goldfarb/imagenes/31221.jpg"],"documents":[],"description":"Para todo tipo de pinturas y superficies\rRodillo de 6 cm de diametro x 17 cm de largo"},"31223":{"itemCode":"31223","brand":{"name":"Hunter","slug":"hunter"},"invoices":35,"finalPrice":90.3,"hasStock":true,"title":"Rodillos Pelo Corto Epoxi Nro.17 Hunter","family":"","category":"","subCategory":"","discount":0,"currency":null,"price":0,"tax":22,"unitsPerItem":"PIEZA","unitMult":1,"relatedItems":["31224"],"shops":[{"cardCode":"401005","cardName":"Guglialmelli Oscar S.A.","cardFName":"Armeria Jabali","address2":"Paraguay 1109 y Rodo"}],"listOrder":"01950-000470","id":31223,"slug":"31223","code":"31223","subcategory":null,"images":["https://goldfarb.blob.core.windows.net/goldfarb/imagenes/31223.jpg"],"documents":[],"description":"Para uso con pintura latex en paredes lisas y cielo rasos.\rRapido recubrimiento.\rAntigota.\rRodillo de 5 cm de diametro x 17 cm de largo."},"31224":{"itemCode":"31224","brand":{"name":"Hunter","slug":"hunter"},"invoices":43,"finalPrice":99.8,"hasStock":true,"title":"Rodillos Pelo Corto Epoxi Nro.22 Hunter","family":"","category":"","subCategory":"","discount":0,"currency":null,"price":0,"tax":22,"unitsPerItem":"PIEZA","unitMult":1,"relatedItems":["31223"],"shops":[{"cardCode":"401005","cardName":"Guglialmelli Oscar S.A.","cardFName":"Armeria Jabali","address2":"Paraguay 1109 y Rodo"}],"listOrder":"01950-000480","id":31224,"slug":"31224","code":"31224","subcategory":null,"images":["https://goldfarb.blob.core.windows.net/goldfarb/imagenes/31224.jpg"],"documents":[],"description":"Para uso con pintura latex en paredes lisas y cielo rasos.\rRapido recubrimiento.\rAntigota.\rRodillo de 5 cm de diametro x 22 cm de largo."},"31231":{"itemCode":"31231","brand":{"name":"Hunter","slug":"hunter"},"invoices":26,"finalPrice":228,"hasStock":true,"title":"Rodillo Super Lana Nro.22 Hunter","family":"","category":"","subCategory":"","discount":0,"currency":null,"price":0,"tax":22,"unitsPerItem":"PIEZA","unitMult":1,"relatedItems":["31232","31221"],"shops":[{"cardCode":"401005","cardName":"Guglialmelli Oscar S.A.","cardFName":"Armeria Jabali","address2":"Paraguay 1109 y Rodo"}],"listOrder":"01950-000450","id":31231,"slug":"31231","code":"31231","subcategory":null,"images":["https://goldfarb.blob.core.windows.net/goldfarb/imagenes/31231.jpg"],"documents":[],"description":"Acabado perfecto\rNo deja marcas\rMaximo rendimiento"},"31232":{"itemCode":"31232","brand":{"name":"Hunter","slug":"hunter"},"invoices":20,"finalPrice":282,"hasStock":true,"title":"Rodillo Super Lana Dorada Premium Nro.22 Hunter","family":"","category":"","subCategory":"","discount":0,"currency":null,"price":0,"tax":22,"unitsPerItem":"PIEZA","unitMult":1,"relatedItems":["31231","31221"],"shops":[{"cardCode":"401005","cardName":"Guglialmelli Oscar S.A.","cardFName":"Armeria Jabali","address2":"Paraguay 1109 y Rodo"}],"listOrder":"01950-000460","id":31232,"slug":"31232","code":"31232","subcategory":null,"images":["https://goldfarb.blob.core.windows.net/goldfarb/imagenes/31232.jpg"],"documents":[],"description":"Acabado perfecto\rNo deja marcas\rMaximo rendimiento\rColor beige"},"31246":{"itemCode":"31246","brand":{"name":"Hunter","slug":"hunter"},"invoices":19,"finalPrice":461,"hasStock":true,"title":"Taco Lijador De Goma Hunter","family":"Ferreteria","category":"Accesorios","subCategory":"Accesorios","discount":0,"currency":null,"price":0,"tax":22,"unitsPerItem":"PIEZA","unitMult":1,"relatedItems":["31282"],"shops":[{"cardCode":"401005","cardName":"Guglialmelli Oscar S.A.","cardFName":"Armeria Jabali","address2":"Paraguay 1109 y Rodo"}],"listOrder":"01310-001420","id":31246,"slug":"31246","code":"31246","subcategory":"Accesorios","images":["https://goldfarb.blob.core.windows.net/goldfarb/imagenes/31246.jpg"],"documents":[],"description":"Base de 7 x 13 cm"},"31247":{"itemCode":"31247","brand":{"name":"Hunter","slug":"hunter"},"invoices":35,"finalPrice":142,"hasStock":true,"title":"Llanas Plasticas 12X30 Hunter","family":"","category":"","subCategory":"","discount":0,"currency":null,"price":0,"tax":22,"unitsPerItem":"PIEZA","unitMult":1,"relatedItems":["31248","31249"],"shops":[{"cardCode":"401005","cardName":"Guglialmelli Oscar S.A.","cardFName":"Armeria Jabali","address2":"Paraguay 1109 y Rodo"}],"listOrder":"01340-000110","id":31247,"slug":"31247","code":"31247","subcategory":null,"images":["https://goldfarb.blob.core.windows.net/goldfarb/imagenes/31247.jpg"],"documents":[],"description":""},"31248":{"itemCode":"31248","brand":{"name":"Hunter","slug":"hunter"},"invoices":35,"finalPrice":149,"hasStock":true,"title":"Llanas Plasticas 14X30 Hunter","family":"","category":"","subCategory":"","discount":0,"currency":null,"price":0,"tax":22,"unitsPerItem":"PIEZA","unitMult":1,"relatedItems":["31247","31249"],"shops":[{"cardCode":"401005","cardName":"Guglialmelli Oscar S.A.","cardFName":"Armeria Jabali","address2":"Paraguay 1109 y Rodo"}],"listOrder":"01340-000120","id":31248,"slug":"31248","code":"31248","subcategory":null,"images":["https://goldfarb.blob.core.windows.net/goldfarb/imagenes/31248.jpg"],"documents":[],"description":"Base plastica lisa de 14 x 30 cm\rAgarradera ergonomica plastica"},"31249":{"itemCode":"31249","brand":{"name":"Hunter","slug":"hunter"},"invoices":18,"finalPrice":208,"hasStock":true,"title":"Llanas Plasticas 20X30 Hunter","family":"","category":"","subCategory":"","discount":0,"currency":null,"price":0,"tax":22,"unitsPerItem":"PIEZA","unitMult":1,"relatedItems":["31247","31248"],"shops":[{"cardCode":"401005","cardName":"Guglialmelli Oscar S.A.","cardFName":"Armeria Jabali","address2":"Paraguay 1109 y Rodo"}],"listOrder":"01340-000130","id":31249,"slug":"31249","code":"31249","subcategory":null,"images":["https://goldfarb.blob.core.windows.net/goldfarb/imagenes/31249.jpg"],"documents":[],"description":"Base plastica lisa de 20 x 30 cm\rAgarradera ergonomica plastica"},"31282":{"itemCode":"31282","brand":{"name":"Hunter","slug":"hunter"},"invoices":25,"finalPrice":139,"hasStock":true,"title":"Kit Taco Lijador + 25 Repuestos De Lija Hunter","family":"","category":"","subCategory":"","discount":0,"currency":null,"price":0,"tax":22,"unitsPerItem":"PIEZA","unitMult":1,"relatedItems":[],"shops":[{"cardCode":"401005","cardName":"Guglialmelli Oscar S.A.","cardFName":"Armeria Jabali","address2":"Paraguay 1109 y Rodo"}],"listOrder":"01310-001430","id":31282,"slug":"31282","code":"31282","subcategory":null,"images":["https://goldfarb.blob.core.windows.net/goldfarb/imagenes/31282.jpg"],"documents":[],"description":"Incluye:\r\rTaco de lijar\r17 hojas de lija gr. 120/150\r7 hojas de lijar gr. 50/60\r1 hoja de lijar gr. 80/100"},"31284":{"itemCode":"31284","brand":{"name":"Hunter","slug":"hunter"},"invoices":18,"finalPrice":50.4,"hasStock":true,"title":"R.Lija P/Pared Y Maderas De 10cm. x 3m. # Medio Hunter","family":"","category":"","subCategory":"","discount":0,"currency":null,"price":0,"tax":22,"unitsPerItem":"PIEZA","unitMult":1,"relatedItems":[],"shops":[{"cardCode":"401005","cardName":"Guglialmelli Oscar S.A.","cardFName":"Armeria Jabali","address2":"Paraguay 1109 y Rodo"}],"listOrder":"01310-000670","id":31284,"slug":"31284","code":"31284","subcategory":null,"images":["https://goldfarb.blob.core.windows.net/goldfarb/imagenes/31284.jpg"],"documents":[],"description":"Ideal para maderas y pared.\rPara uso manual o con lijadoras orbitales.\rGrano medio ( 80/100 )\rDimensiones 10 cm x 300 cm"},"31286":{"itemCode":"31286","brand":{"name":"Hunter","slug":"hunter"},"invoices":10,"finalPrice":122,"hasStock":true,"title":"Lija Al Agua En Rollo De 23cm. x  3m. Gr.80 Hunter","family":"","category":"","subCategory":"","discount":0,"currency":null,"price":0,"tax":22,"unitsPerItem":"PIEZA","unitMult":1,"relatedItems":["31287","31288"],"shops":[{"cardCode":"401005","cardName":"Guglialmelli Oscar S.A.","cardFName":"Armeria Jabali","address2":"Paraguay 1109 y Rodo"}],"listOrder":"01310-000520","id":31286,"slug":"31286","code":"31286","subcategory":null,"images":["https://goldfarb.blob.core.windows.net/goldfarb/imagenes/31286.jpg"],"documents":[],"description":""},"31287":{"itemCode":"31287","brand":{"name":"Hunter","slug":"hunter"},"invoices":13,"finalPrice":122,"hasStock":true,"title":"Lija Al Agua En Rollo De 23cm. x  3m. Gr.120 Hunter","family":"","category":"","subCategory":"","discount":0,"currency":null,"price":0,"tax":22,"unitsPerItem":"PIEZA","unitMult":1,"relatedItems":["31286","31288"],"shops":[{"cardCode":"401005","cardName":"Guglialmelli Oscar S.A.","cardFName":"Armeria Jabali","address2":"Paraguay 1109 y Rodo"}],"listOrder":"01310-000530","id":31287,"slug":"31287","code":"31287","subcategory":null,"images":["https://goldfarb.blob.core.windows.net/goldfarb/imagenes/31287.jpg"],"documents":[],"description":""},"31288":{"itemCode":"31288","brand":{"name":"Hunter","slug":"hunter"},"invoices":12,"finalPrice":125,"hasStock":true,"title":"Lija Al Agua En Rollo De 23cm. x  3m. Gr.150 Hunter","family":"","category":"","subCategory":"","discount":0,"currency":null,"price":0,"tax":22,"unitsPerItem":"PIEZA","unitMult":1,"relatedItems":["31286","31287"],"shops":[{"cardCode":"401005","cardName":"Guglialmelli Oscar S.A.","cardFName":"Armeria Jabali","address2":"Paraguay 1109 y Rodo"}],"listOrder":"01310-000540","id":31288,"slug":"31288","code":"31288","subcategory":null,"images":["https://goldfarb.blob.core.windows.net/goldfarb/imagenes/31288.jpg"],"documents":[],"description":""},"31289":{"itemCode":"31289","brand":{"name":"Hunter","slug":"hunter"},"invoices":25,"finalPrice":109,"hasStock":true,"title":"R.Tela Esmeril De 10cm. x 3m. # Mediano Hunter","family":"","category":"","subCategory":"","discount":0,"currency":null,"price":0,"tax":22,"unitsPerItem":"PIEZA","unitMult":1,"relatedItems":[],"shops":[{"cardCode":"401005","cardName":"Guglialmelli Oscar S.A.","cardFName":"Armeria Jabali","address2":"Paraguay 1109 y Rodo"}],"listOrder":"01310-000500","id":31289,"slug":"31289","code":"31289","subcategory":null,"images":["https://goldfarb.blob.core.windows.net/goldfarb/imagenes/31289.jpg"],"documents":[],"description":""},"31290":{"itemCode":"31290","brand":{"name":"Hunter","slug":"hunter"},"invoices":33,"finalPrice":76.7,"hasStock":true,"title":"Venda P/Pared No Tej 5X25 Hunter","family":"Pinturas","category":"Accesorios","subCategory":"Venda p/pared","discount":0,"currency":null,"price":0,"tax":22,"unitsPerItem":"PIEZA","unitMult":1,"relatedItems":["31291","31292","31293","31294"],"shops":[{"cardCode":"401005","cardName":"Guglialmelli Oscar S.A.","cardFName":"Armeria Jabali","address2":"Paraguay 1109 y Rodo"}],"listOrder":"06475-000100","id":31290,"slug":"31290","code":"31290","subcategory":"Venda p/pared","images":[],"documents":[],"description":"Venda de 5 cm de ancho x 25 metros de largo\rRepara grietas y fisuras\rSe aplica con impermeabilizante para obtener una membrana armada"},"31291":{"itemCode":"31291","brand":{"name":"Hunter","slug":"hunter"},"invoices":77,"finalPrice":146,"hasStock":true,"title":"Venda P/Pared No Tej 10X25 Hunter","family":"Pinturas","category":"Accesorios","subCategory":"Venda p/pared","discount":0,"currency":null,"price":0,"tax":22,"unitsPerItem":"PIEZA","unitMult":1,"relatedItems":["31290","31292","31293","31294"],"shops":[{"cardCode":"401005","cardName":"Guglialmelli Oscar S.A.","cardFName":"Armeria Jabali","address2":"Paraguay 1109 y Rodo"}],"listOrder":"06475-000110","id":31291,"slug":"31291","code":"31291","subcategory":"Venda p/pared","images":["https://goldfarb.blob.core.windows.net/goldfarb/imagenes/31291.jpg"],"documents":[],"description":"Venda de 10 cm de ancho x 25 metros de largo\rRepara grietas y fisuras\rSe aplica con impermeabilizante para obtener una membrana armada"},"31292":{"itemCode":"31292","brand":{"name":"Hunter","slug":"hunter"},"invoices":88,"finalPrice":294,"hasStock":true,"title":"Venda P/Pared No Tej 20X25 Hunter","family":"Pinturas","category":"Accesorios","subCategory":"Venda p/pared","discount":0,"currency":null,"price":0,"tax":22,"unitsPerItem":"PIEZA","unitMult":1,"relatedItems":["31290","31291","31293","31294"],"shops":[{"cardCode":"401005","cardName":"Guglialmelli Oscar S.A.","cardFName":"Armeria Jabali","address2":"Paraguay 1109 y Rodo"}],"listOrder":"06475-000120","id":31292,"slug":"31292","code":"31292","subcategory":"Venda p/pared","images":["https://goldfarb.blob.core.windows.net/goldfarb/imagenes/31292.jpg"],"documents":[],"description":"Venda de 20 cm de ancho x 25 metros de largo\rRepara grietas y fisuras\rSe aplica con impermeabilizante para obtener una membrana armada"},"31293":{"itemCode":"31293","brand":{"name":"Hunter","slug":"hunter"},"invoices":67,"finalPrice":1241,"hasStock":true,"title":"Venda P/Pared No Tej 1.00 X 25 Hunter","family":"Pinturas","category":"Accesorios","subCategory":"Venda p/pared","discount":0,"currency":null,"price":0,"tax":22,"unitsPerItem":"PIEZA","unitMult":1,"relatedItems":["31290","31291","31292","31294"],"shops":[{"cardCode":"401005","cardName":"Guglialmelli Oscar S.A.","cardFName":"Armeria Jabali","address2":"Paraguay 1109 y Rodo"}],"listOrder":"01310-000130","id":31293,"slug":"31293","code":"31293","subcategory":"Venda p/pared","images":["https://goldfarb.blob.core.windows.net/goldfarb/imagenes/31293.jpg"],"documents":[],"description":"Venda de 1 mt de ancho x 25 metros de largo\rRepara grietas y fisuras\rSe aplica con impermeabilizante para obtener una membrana armada"},"31294":{"itemCode":"31294","brand":{"name":"Hunter","slug":"hunter"},"invoices":53,"finalPrice":2477,"hasStock":true,"title":"Venda P/Pared No Tej 1.00 X 50 Hunter","family":"Pinturas","category":"Accesorios","subCategory":"Venda p/pared","discount":0,"currency":null,"price":0,"tax":22,"unitsPerItem":"PIEZA","unitMult":1,"relatedItems":["31290","31291","31292","31293"],"shops":[{"cardCode":"401005","cardName":"Guglialmelli Oscar S.A.","cardFName":"Armeria Jabali","address2":"Paraguay 1109 y Rodo"}],"listOrder":"06475-000130","id":31294,"slug":"31294","code":"31294","subcategory":"Venda p/pared","images":["https://goldfarb.blob.core.windows.net/goldfarb/imagenes/31294.jpg"],"documents":[],"description":"Venda de 1 mt de ancho x 50 metros de largo\rRepara grietas y fisuras\rSe aplica con impermeabilizante para obtener una membrana armada"},"31296":{"itemCode":"31296","brand":{"name":"Hunter","slug":"hunter"},"invoices":34,"finalPrice":53.6,"hasStock":true,"title":"Sobre 5 Hojas Lija Agua #150 Hunter","family":"","category":"","subCategory":"","discount":0,"currency":null,"price":0,"tax":22,"unitsPerItem":"PIEZA","unitMult":1,"relatedItems":["31299"],"shops":[{"cardCode":"401005","cardName":"Guglialmelli Oscar S.A.","cardFName":"Armeria Jabali","address2":"Paraguay 1109 y Rodo"}],"listOrder":"01310-000270","id":31296,"slug":"31296","code":"31296","subcategory":null,"images":["https://goldfarb.blob.core.windows.net/goldfarb/imagenes/31296.jpg"],"documents":[],"description":"Ideal para lijar pinturas, chapas, metales, plasticos y masillas\rDimensiones 280 x 230 mm.\rGrano 150"},"31298":{"itemCode":"31298","brand":{"name":"Hunter","slug":"hunter"},"invoices":13,"finalPrice":77.7,"hasStock":true,"title":"Sobre 5 Tela Esm Surtido Hunter","family":"","category":"","subCategory":"","discount":0,"currency":null,"price":0,"tax":22,"unitsPerItem":"PIEZA","unitMult":1,"relatedItems":["31296"],"shops":[{"cardCode":"401005","cardName":"Guglialmelli Oscar S.A.","cardFName":"Armeria Jabali","address2":"Paraguay 1109 y Rodo"}],"listOrder":"01310-000510","id":31298,"slug":"31298","code":"31298","subcategory":null,"images":["https://goldfarb.blob.core.windows.net/goldfarb/imagenes/31298.jpg"],"documents":[],"description":"Ideal para lijar metales y rejas\rDimensiones 260 x 210 mm\rGrano surtido ( 50/60 - 80/100 - 120/150 - 180/220 )"},"31299":{"itemCode":"31299","brand":{"name":"Hunter","slug":"hunter"},"invoices":73,"finalPrice":122,"hasStock":true,"title":"Sobre 6 Hojas Lija Madera Surtido Hunter","family":"Ferreteria","category":"Abrasivos","subCategory":"Lijas p/madera","discount":0,"currency":null,"price":0,"tax":22,"unitsPerItem":"PIEZA","unitMult":1,"relatedItems":["31296"],"shops":[{"cardCode":"401005","cardName":"Guglialmelli Oscar S.A.","cardFName":"Armeria Jabali","address2":"Paraguay 1109 y Rodo"}],"listOrder":"01310-000330","id":31299,"slug":"31299","code":"31299","subcategory":"Lijas p/madera","images":["https://goldfarb.blob.core.windows.net/goldfarb/imagenes/31299.jpg"],"documents":[],"description":"Ideal para lijar maderas y paredes\rDimensiones 260 x 210 mm\rGrano surtido ( 50/60 - 80/100 - 120/150 )"},"31300":{"itemCode":"31300","brand":{"name":"Hunter","slug":"hunter"},"invoices":28,"finalPrice":129,"hasStock":true,"title":"Espátula Para Enduido Nº 100 Hunter","family":"","category":"","subCategory":"","discount":0,"currency":null,"price":0,"tax":22,"unitsPerItem":"PIEZA","unitMult":1,"relatedItems":[],"shops":[{"cardCode":"401005","cardName":"Guglialmelli Oscar S.A.","cardFName":"Armeria Jabali","address2":"Paraguay 1109 y Rodo"}],"listOrder":"00910-001660","id":31300,"slug":"31300","code":"31300","subcategory":null,"images":["https://goldfarb.blob.core.windows.net/goldfarb/imagenes/31300.jpg"],"documents":[],"description":"Ancho 100 mm x 90 mm de profundidad ( trapezoidal )\rCabo de madera"},"31307":{"itemCode":"31307","brand":{"name":"Hunter","slug":"hunter"},"invoices":19,"finalPrice":89.2,"hasStock":true,"title":"Espátula Para Pintor Nº 3 Hunter","family":"","category":"","subCategory":"","discount":0,"currency":null,"price":0,"tax":22,"unitsPerItem":"PIEZA","unitMult":1,"relatedItems":["31308","31311","31313","31312","31300"],"shops":[{"cardCode":"401005","cardName":"Guglialmelli Oscar S.A.","cardFName":"Armeria Jabali","address2":"Paraguay 1109 y Rodo"}],"listOrder":"00910-001730","id":31307,"slug":"31307","code":"31307","subcategory":null,"images":["https://goldfarb.blob.core.windows.net/goldfarb/imagenes/31307.jpg"],"documents":[],"description":"3 cm de ancho x 10 cm de largo ( lados paralelos )\rMango de madera barnizado"},"31308":{"itemCode":"31308","brand":{"name":"Hunter","slug":"hunter"},"invoices":16,"finalPrice":97.6,"hasStock":true,"title":"Espátula Para Pintor Nº 4 Hunter","family":"","category":"","subCategory":"","discount":0,"currency":null,"price":0,"tax":22,"unitsPerItem":"PIEZA","unitMult":1,"relatedItems":["31307","31311","31313","31312","31300"],"shops":[{"cardCode":"401005","cardName":"Guglialmelli Oscar S.A.","cardFName":"Armeria Jabali","address2":"Paraguay 1109 y Rodo"}],"listOrder":"00910-001740","id":31308,"slug":"31308","code":"31308","subcategory":null,"images":["https://goldfarb.blob.core.windows.net/goldfarb/imagenes/31308.jpg"],"documents":[],"description":"4 cm de ancho x 10 cm de largo ( lados paralelos )\rMango de madera barnizado"},"31311":{"itemCode":"31311","brand":{"name":"Hunter","slug":"hunter"},"invoices":15,"finalPrice":121,"hasStock":true,"title":"Espátula Para Pintor Nº 7 Hunter","family":"","category":"","subCategory":"","discount":0,"currency":null,"price":0,"tax":22,"unitsPerItem":"PIEZA","unitMult":1,"relatedItems":["31307","31308","31313","31312","31300"],"shops":[{"cardCode":"401005","cardName":"Guglialmelli Oscar S.A.","cardFName":"Armeria Jabali","address2":"Paraguay 1109 y Rodo"}],"listOrder":"00910-001770","id":31311,"slug":"31311","code":"31311","subcategory":null,"images":["https://goldfarb.blob.core.windows.net/goldfarb/imagenes/31311.jpg"],"documents":[],"description":"7 cm de ancho x 10 cm de largo \rMango de madera barnizado"},"31312":{"itemCode":"31312","brand":{"name":"Hunter","slug":"hunter"},"invoices":20,"finalPrice":130,"hasStock":true,"title":"Espátula Para Pintor Nº 8 Hunter","family":"","category":"","subCategory":"","discount":0,"currency":null,"price":0,"tax":22,"unitsPerItem":"PIEZA","unitMult":1,"relatedItems":["31307","31308","31311","31313","31300"],"shops":[{"cardCode":"401005","cardName":"Guglialmelli Oscar S.A.","cardFName":"Armeria Jabali","address2":"Paraguay 1109 y Rodo"}],"listOrder":"00910-001780","id":31312,"slug":"31312","code":"31312","subcategory":null,"images":["https://goldfarb.blob.core.windows.net/goldfarb/imagenes/31312.jpg"],"documents":[],"description":"8 cm de ancho x 10 cm de largo \rMango de madera barnizado"},"31313":{"itemCode":"31313","brand":{"name":"Hunter","slug":"hunter"},"invoices":16,"finalPrice":133,"hasStock":true,"title":"Espátula Para Pintor Nº 9 Hunter","family":"","category":"","subCategory":"","discount":0,"currency":null,"price":0,"tax":22,"unitsPerItem":"PIEZA","unitMult":1,"relatedItems":["31307","31308","31311","31312","31300"],"shops":[{"cardCode":"401005","cardName":"Guglialmelli Oscar S.A.","cardFName":"Armeria Jabali","address2":"Paraguay 1109 y Rodo"}],"listOrder":"00910-001790","id":31313,"slug":"31313","code":"31313","subcategory":null,"images":["https://goldfarb.blob.core.windows.net/goldfarb/imagenes/31313.jpg"],"documents":[],"description":"9 cm de ancho x 10 cm de largo \rMango de madera barnizado"},"31318":{"itemCode":"31318","brand":{"name":"Hunter","slug":"hunter"},"invoices":8,"finalPrice":768,"hasStock":true,"title":"Llanas Metalicas Yesero 12 X 30 Hunter","family":"","category":"","subCategory":"","discount":0,"currency":null,"price":0,"tax":22,"unitsPerItem":"PIEZA","unitMult":1,"relatedItems":[],"shops":[{"cardCode":"401005","cardName":"Guglialmelli Oscar S.A.","cardFName":"Armeria Jabali","address2":"Paraguay 1109 y Rodo"}],"listOrder":"01340-000100","id":31318,"slug":"31318","code":"31318","subcategory":null,"images":["https://goldfarb.blob.core.windows.net/goldfarb/imagenes/31318.jpg"],"documents":[],"description":"Mango de madera abulonado\rBase fijada con 3 remaches"},"31394":{"itemCode":"31394","brand":{"name":"Rongpeng","slug":"rongpeng"},"invoices":745,"finalPrice":1028.2,"hasStock":true,"title":"Kit Accs.P/Compresor 5Pz.(C/Pistola Gravedad) RP8031K5 Rongpeng","family":"Pinturas","category":"Equipos de pintar","subCategory":"Accesorios","discount":0,"currency":null,"price":0,"tax":22,"unitsPerItem":"KIT","unitMult":1,"relatedItems":[],"shops":[{"cardCode":"401005","cardName":"Guglialmelli Oscar S.A.","cardFName":"Armeria Jabali","address2":"Paraguay 1109 y Rodo"}],"listOrder":"00620-000430","id":31394,"slug":"31394","code":"31394","subcategory":"Accesorios","images":["https://goldfarb.blob.core.windows.net/goldfarb/imagenes/31394.jpg"],"documents":[],"description":"Kits de 5pcs AirTools\r*Pistola de aire comprimido,presiòn maxima 6bar.\r*Pistola de limpieza de motores, tacho metalico de 600cc,presiòn maxima 4 bar.\r*Pistola de pintar de gravedad,tacho metalico de 600cc, presiòn maxima de 3.0bar boquilla de 1.5mm 4-7 cfm,180-250mm.\r*Pistola para inflar con manometro de goma hasta  8.5 bar.\r*Manguera de aire 5 mts.\rConexion de rosca 1/4\".\r(Kit de accesorios viene en caja)"},"31395":{"itemCode":"31395","brand":{"name":"Rongpeng","slug":"rongpeng"},"invoices":324,"finalPrice":740.304,"hasStock":false,"title":"Pistola De Pintar De Gravedad 600cc. Mod.1020 Rongpeng","family":"Pinturas","category":"Equipos de pintar","subCategory":"Pistolas","discount":0,"currency":null,"price":0,"tax":22,"unitsPerItem":"PIEZA","unitMult":1,"relatedItems":["1478","31396","30540","31398","30938"],"shops":[{"cardCode":"401005","cardName":"Guglialmelli Oscar S.A.","cardFName":"Armeria Jabali","address2":"Paraguay 1109 y Rodo"}],"listOrder":"01750-000283","id":31395,"slug":"31395","code":"31395","subcategory":"Pistolas","images":["https://goldfarb.blob.core.windows.net/goldfarb/imagenes/31395.jpg"],"documents":[],"description":"• Suministro de pistolas de aplicación HVLP (alto volumen de baja presión) a 10 psi. Presión baja a través del cabezal de aire que hace que la pulverización sea más suave, de fácil control y menos exceso de pulverización con una alta eficiencia de transferencia.\r• Incluye controles de fluido, patrón y aire ajustables.\r• Diseñado para proporcionar igual atomización y tamaño de partícula para todo tipo de pintura de superficie.\r• La aguja y la boquilla de acero inoxidable.\r• Diseño liviano, ergonómico y fácil pivote de gatillo para reducir la fatiga operativa.\r-Preciòn laboral 2.0-3.5 bar.\r-Boquilla de 1.4mm\r-Tacho plastico con capacidad de  600cc."},"31396":{"itemCode":"31396","brand":{"name":"Rongpeng","slug":"rongpeng"},"invoices":143,"finalPrice":740.304,"hasStock":true,"title":"Pistola De Pintar De Baja Presion 750cc. 472 Rongpeng","family":"Pinturas","category":"Equipos de pintar","subCategory":"Pistolas","discount":0,"currency":null,"price":0,"tax":22,"unitsPerItem":"PIEZA","unitMult":1,"relatedItems":["1478","31395","30540","31398","30938"],"shops":[{"cardCode":"401005","cardName":"Guglialmelli Oscar S.A.","cardFName":"Armeria Jabali","address2":"Paraguay 1109 y Rodo"}],"listOrder":"01750-000286","id":31396,"slug":"31396","code":"31396","subcategory":"Pistolas","images":["https://goldfarb.blob.core.windows.net/goldfarb/imagenes/31396.jpg"],"documents":[],"description":"• Spray de diseño de alimentación a presión de materiales de baja a media viscosidad.\r• El control del fluido regula la cantidad de pintura rociada durante el trabajo.\r• Incluye tapa de aire de línea, ventilador y mariposa o forma redonda.\r*Pistola con cuerpo y tacho de aluminio.\r*Boquilla de 0.8 mm .\r*Capacidad de tacho 750cc.\r*Presiòn laboral 2.0-3.5 bar.\r*No usar mas de 50 psi de presiòn."},"31397":{"itemCode":"31397","brand":{"name":"Rongpeng","slug":"rongpeng"},"invoices":152,"finalPrice":493.536,"hasStock":false,"title":"Pistola De Limpieza R8036E Rongpeng","family":"Pinturas","category":"Equipos de pintar","subCategory":"Pistolas","discount":0,"currency":null,"price":0,"tax":22,"unitsPerItem":"PIEZA","unitMult":1,"relatedItems":[],"shops":[{"cardCode":"401005","cardName":"Guglialmelli Oscar S.A.","cardFName":"Armeria Jabali","address2":"Paraguay 1109 y Rodo"}],"listOrder":"01750-000072","id":31397,"slug":"31397","code":"31397","subcategory":"Pistolas","images":["https://goldfarb.blob.core.windows.net/goldfarb/imagenes/31397.jpg"],"documents":[],"description":"Presión de funcionamiento: 3-6Bar \rMaxima presiòn 9Bar.\rTacho metalico con capacidad750cc\rPistola con cuerpo de aluminio \rRosca 1/4\"."},"31398":{"itemCode":"31398","brand":{"name":"Rongpeng","slug":"rongpeng"},"invoices":179,"finalPrice":370.152,"hasStock":false,"title":"Pistola De Inflar Con Manometro R8037-3/DG-30C Rongpeng","family":"Pinturas","category":"Equipos de pintar","subCategory":"Pistolas","discount":0,"currency":null,"price":0,"tax":22,"unitsPerItem":"PIEZA","unitMult":1,"relatedItems":[],"shops":[{"cardCode":"401005","cardName":"Guglialmelli Oscar S.A.","cardFName":"Armeria Jabali","address2":"Paraguay 1109 y Rodo"}],"listOrder":"01750-000076","id":31398,"slug":"31398","code":"31398","subcategory":"Pistolas","images":["https://goldfarb.blob.core.windows.net/goldfarb/imagenes/31398.jpg"],"documents":[],"description":"Rosca 1/4\" .\rManometro de goma y cuerpo de aluminio.(mas duradero).\rPresión máxima: 100psi (7 bar)\rInclye accesorio medidor de presiòn hasta 120 psi (8.5 bar)"},"31399":{"itemCode":"31399","brand":{"name":"Rongpeng","slug":"rongpeng"},"invoices":140,"finalPrice":164.512,"hasStock":true,"title":"Pistola De Sopletear Corta R8035-1 Rongpeng","family":"Pinturas","category":"Equipos de pintar","subCategory":"Pistolas","discount":0,"currency":null,"price":0,"tax":22,"unitsPerItem":"PIEZA","unitMult":1,"relatedItems":["35600"],"shops":[{"cardCode":"401005","cardName":"Guglialmelli Oscar S.A.","cardFName":"Armeria Jabali","address2":"Paraguay 1109 y Rodo"}],"listOrder":"01750-000064","id":31399,"slug":"31399","code":"31399","subcategory":"Pistolas","images":["https://goldfarb.blob.core.windows.net/goldfarb/imagenes/31399.jpg"],"documents":[],"description":"Rosca 1/4\"\rPistola de plastico con puntero metalico de 10cm(4\")\rMaxima presiòn laboral 90psi(6.2bar)."},"31400":{"itemCode":"31400","brand":{"name":"Workline","slug":"workline"},"invoices":17,"finalPrice":1172.148,"hasStock":true,"title":"Zapato Negro C/Puntera Nro.35 Workline","family":"Ferreteria","category":"Proteccion","subCategory":"Zapatos de seguridad","discount":0,"currency":null,"price":0,"tax":22,"unitsPerItem":"PAR","unitMult":1,"relatedItems":["31401","31402","31403","31404","31405"],"shops":[{"cardCode":"401005","cardName":"Guglialmelli Oscar S.A.","cardFName":"Armeria Jabali","address2":"Paraguay 1109 y Rodo"}],"listOrder":"02250-000840","id":31400,"slug":"31400","code":"31400","subcategory":"Zapatos de seguridad","images":["https://goldfarb.blob.core.windows.net/goldfarb/imagenes/31400.jpg"],"documents":[],"description":"* Zapatos de seguridad.\r\r* Con puntera de acero.\r\r* Collarín acolchado.\r\r* Hechos de cuero.\r\r* Cierre con cordones.\r\r* Forro interno y suela doble densidad."},"31401":{"itemCode":"31401","brand":{"name":"Workline","slug":"workline"},"invoices":21,"finalPrice":1172.148,"hasStock":true,"title":"Zapato Negro C/Puntera Nro.36 Workline","family":"Ferreteria","category":"Proteccion","subCategory":"Zapatos de seguridad","discount":0,"currency":null,"price":0,"tax":22,"unitsPerItem":"PAR","unitMult":1,"relatedItems":["31400","31402","31403","31404","31405"],"shops":[{"cardCode":"401005","cardName":"Guglialmelli Oscar S.A.","cardFName":"Armeria Jabali","address2":"Paraguay 1109 y Rodo"}],"listOrder":"02250-000850","id":31401,"slug":"31401","code":"31401","subcategory":"Zapatos de seguridad","images":["https://goldfarb.blob.core.windows.net/goldfarb/imagenes/31401.jpg"],"documents":[],"description":"* Zapatos de seguridad con puntera de plastico.\r\r* Collarin acolchado.\r\r* Hechos de cuero.\r\r* Cierre con cordones.\r\r* Forro interno y suela doble densidad."},"31402":{"itemCode":"31402","brand":{"name":"Workline","slug":"workline"},"invoices":35,"finalPrice":1172.148,"hasStock":true,"title":"Zapato Negro C/Puntera Nro.37 Workline","family":"Ferreteria","category":"Proteccion","subCategory":"Zapatos de seguridad","discount":0,"currency":null,"price":0,"tax":22,"unitsPerItem":"PAR","unitMult":1,"relatedItems":["31400","31401","31403","31404","31405"],"shops":[{"cardCode":"401005","cardName":"Guglialmelli Oscar S.A.","cardFName":"Armeria Jabali","address2":"Paraguay 1109 y Rodo"}],"listOrder":"02250-000860","id":31402,"slug":"31402","code":"31402","subcategory":"Zapatos de seguridad","images":["https://goldfarb.blob.core.windows.net/goldfarb/imagenes/31402.jpg"],"documents":[],"description":"* Zapatos de seguridad con puntera de plastico.\r\r* Collarin acolchado.\r\r* Hechos de cuero.\r\r* Cierre con cordones.\r\r* Forro interno y suela doble densidad."},"31403":{"itemCode":"31403","brand":{"name":"Workline","slug":"workline"},"invoices":49,"finalPrice":1172.148,"hasStock":true,"title":"Zapato Negro C/Puntera Nro.38 Workline","family":"Ferreteria","category":"Proteccion","subCategory":"Zapatos de seguridad","discount":0,"currency":null,"price":0,"tax":22,"unitsPerItem":"PAR","unitMult":1,"relatedItems":["31400","31401","31402","31404","31405"],"shops":[{"cardCode":"401005","cardName":"Guglialmelli Oscar S.A.","cardFName":"Armeria Jabali","address2":"Paraguay 1109 y Rodo"}],"listOrder":"02250-000870","id":31403,"slug":"31403","code":"31403","subcategory":"Zapatos de seguridad","images":["https://goldfarb.blob.core.windows.net/goldfarb/imagenes/31403.jpg"],"documents":[],"description":""},"31404":{"itemCode":"31404","brand":{"name":"Workline","slug":"workline"},"invoices":133,"finalPrice":1172.148,"hasStock":true,"title":"Zapato Negro C/Puntera Nro.39 Workline","family":"Ferreteria","category":"Proteccion","subCategory":"Zapatos de seguridad","discount":0,"currency":null,"price":0,"tax":22,"unitsPerItem":"PAR","unitMult":1,"relatedItems":["31400","31401","31402","31403","31405"],"shops":[{"cardCode":"401005","cardName":"Guglialmelli Oscar S.A.","cardFName":"Armeria Jabali","address2":"Paraguay 1109 y Rodo"}],"listOrder":"02250-000880","id":31404,"slug":"31404","code":"31404","subcategory":"Zapatos de seguridad","images":["https://goldfarb.blob.core.windows.net/goldfarb/imagenes/31404.jpg"],"documents":[],"description":"* Zapatos de seguridad con puntera de plastico.\r\r* Collarin acolchado.\r\r* Hechos de cuero.\r\r* Cierre con cordones.\r\r* Forro interno y suela doble densidad."},"31405":{"itemCode":"31405","brand":{"name":"Workline","slug":"workline"},"invoices":199,"finalPrice":1172.148,"hasStock":true,"title":"Zapato Negro C/Puntera Nro.40 Workline","family":"Ferreteria","category":"Proteccion","subCategory":"Zapatos de seguridad","discount":0,"currency":null,"price":0,"tax":22,"unitsPerItem":"PAR","unitMult":1,"relatedItems":["31400","31401","31402","31403","31404"],"shops":[{"cardCode":"401005","cardName":"Guglialmelli Oscar S.A.","cardFName":"Armeria Jabali","address2":"Paraguay 1109 y Rodo"}],"listOrder":"02250-000890","id":31405,"slug":"31405","code":"31405","subcategory":"Zapatos de seguridad","images":["https://goldfarb.blob.core.windows.net/goldfarb/imagenes/31405.jpg"],"documents":[],"description":"* Zapatos de seguridad con puntera de plastico.\r\r* Collarin acolchado.\r\r* Hechos de cuero.\r\r* Cierre con cordones.\r\r* Forro interno y suela doble densidad."},"31406":{"itemCode":"31406","brand":{"name":"Workline","slug":"workline"},"invoices":281,"finalPrice":1172.148,"hasStock":true,"title":"Zapato Negro C/Puntera Nro.41 Workline","family":"Ferreteria","category":"Proteccion","subCategory":"Zapatos de seguridad","discount":0,"currency":null,"price":0,"tax":22,"unitsPerItem":"PAR","unitMult":1,"relatedItems":["31400","31401","31402","31403","31404"],"shops":[{"cardCode":"401005","cardName":"Guglialmelli Oscar S.A.","cardFName":"Armeria Jabali","address2":"Paraguay 1109 y Rodo"}],"listOrder":"02250-000900","id":31406,"slug":"31406","code":"31406","subcategory":"Zapatos de seguridad","images":["https://goldfarb.blob.core.windows.net/goldfarb/imagenes/31406.jpg"],"documents":[],"description":"* Zapatos de seguridad con puntera de plastico.\r\r* Collarin acolchado.\r\r* Hechos de cuero.\r\r* Cierre con cordones.\r\r* Forro interno y suela doble densidad."},"31407":{"itemCode":"31407","brand":{"name":"Workline","slug":"workline"},"invoices":313,"finalPrice":1172.148,"hasStock":true,"title":"Zapato Negro C/Puntera Nro.42 Workline","family":"Ferreteria","category":"Proteccion","subCategory":"Zapatos de seguridad","discount":0,"currency":null,"price":0,"tax":22,"unitsPerItem":"PAR","unitMult":1,"relatedItems":["31400","31401","31402","31403","31404"],"shops":[{"cardCode":"401005","cardName":"Guglialmelli Oscar S.A.","cardFName":"Armeria Jabali","address2":"Paraguay 1109 y Rodo"}],"listOrder":"02250-000910","id":31407,"slug":"31407","code":"31407","subcategory":"Zapatos de seguridad","images":["https://goldfarb.blob.core.windows.net/goldfarb/imagenes/31407.jpg"],"documents":[],"description":"* Zapatos de seguridad con puntera de plastico.\r\r* Collarin acolchado.\r\r* Hechos de cuero.\r\r* Cierre con cordones.\r\r* Forro interno y suela doble densidad."},"31408":{"itemCode":"31408","brand":{"name":"Workline","slug":"workline"},"invoices":182,"finalPrice":1172.148,"hasStock":true,"title":"Zapato Negro C/Puntera Nro.43 Workline","family":"Ferreteria","category":"Proteccion","subCategory":"Zapatos de seguridad","discount":0,"currency":null,"price":0,"tax":22,"unitsPerItem":"PAR","unitMult":1,"relatedItems":["31400","31401","31402","31403","31404"],"shops":[{"cardCode":"401005","cardName":"Guglialmelli Oscar S.A.","cardFName":"Armeria Jabali","address2":"Paraguay 1109 y Rodo"}],"listOrder":"02250-000920","id":31408,"slug":"31408","code":"31408","subcategory":"Zapatos de seguridad","images":["https://goldfarb.blob.core.windows.net/goldfarb/imagenes/31408.jpg"],"documents":[],"description":"* Zapatos de seguridad con puntera de plastico.\r\r* Collarin acolchado.\r\r* Hechos de cuero.\r\r* Cierre con cordones.\r\r* Forro interno y suela doble densidad."},"31409":{"itemCode":"31409","brand":{"name":"Workline","slug":"workline"},"invoices":113,"finalPrice":1172.148,"hasStock":true,"title":"Zapato Negro C/Puntera Nro.44 Workline","family":"Ferreteria","category":"Proteccion","subCategory":"Zapatos de seguridad","discount":0,"currency":null,"price":0,"tax":22,"unitsPerItem":"PAR","unitMult":1,"relatedItems":["31400","31401","31402","31403","31404"],"shops":[{"cardCode":"401005","cardName":"Guglialmelli Oscar S.A.","cardFName":"Armeria Jabali","address2":"Paraguay 1109 y Rodo"}],"listOrder":"02250-000930","id":31409,"slug":"31409","code":"31409","subcategory":"Zapatos de seguridad","images":["https://goldfarb.blob.core.windows.net/goldfarb/imagenes/31409.jpg"],"documents":[],"description":"* Zapatos de seguridad con puntera de plastico.\r\r* Collarin acolchado.\r\r* Hechos de cuero.\r\r* Cierre con cordones.\r\r* Forro interno y suela doble densidad."},"31410":{"itemCode":"31410","brand":{"name":"Workline","slug":"workline"},"invoices":103,"finalPrice":1172.148,"hasStock":true,"title":"Zapato Negro C/Puntera Nro.45 Workline","family":"Ferreteria","category":"Proteccion","subCategory":"Zapatos de seguridad","discount":0,"currency":null,"price":0,"tax":22,"unitsPerItem":"PAR","unitMult":1,"relatedItems":["31400","31401","31402","31403","31404"],"shops":[{"cardCode":"401005","cardName":"Guglialmelli Oscar S.A.","cardFName":"Armeria Jabali","address2":"Paraguay 1109 y Rodo"}],"listOrder":"02250-000940","id":31410,"slug":"31410","code":"31410","subcategory":"Zapatos de seguridad","images":["https://goldfarb.blob.core.windows.net/goldfarb/imagenes/31410.jpg"],"documents":[],"description":"* Zapatos de seguridad con puntera de plastico.\r\r* Collarin acolchado.\r\r* Hechos de cuero.\r\r* Cierre con cordones.\r\r* Forro interno y suela doble densidad."},"31411":{"itemCode":"31411","brand":{"name":"Workline","slug":"workline"},"invoices":22,"finalPrice":1172.148,"hasStock":true,"title":"Zapato Negro C/Puntera Nro.46 Workline","family":"Ferreteria","category":"Proteccion","subCategory":"Zapatos de seguridad","discount":0,"currency":null,"price":0,"tax":22,"unitsPerItem":"PAR","unitMult":1,"relatedItems":["31400","31401","31402","31403","31404"],"shops":[{"cardCode":"401005","cardName":"Guglialmelli Oscar S.A.","cardFName":"Armeria Jabali","address2":"Paraguay 1109 y Rodo"}],"listOrder":"02250-000950","id":31411,"slug":"31411","code":"31411","subcategory":"Zapatos de seguridad","images":["https://goldfarb.blob.core.windows.net/goldfarb/imagenes/31411.jpg"],"documents":[],"description":"* Zapatos de seguridad con puntera de plastico.\r\r* Collarin acolchado.\r\r* Hechos de cuero.\r\r* Cierre con cordones.\r\r* Forro interno y suela doble densidad."},"31413":{"itemCode":"31413","brand":{"name":"Workline","slug":"workline"},"invoices":40,"finalPrice":1065.2152,"hasStock":true,"title":"Zapato Negro S/Puntera Nro.35 Workline","family":"Ferreteria","category":"Proteccion","subCategory":"Zapatos de seguridad","discount":0,"currency":null,"price":0,"tax":22,"unitsPerItem":"PAR","unitMult":1,"relatedItems":["31414","31415","31416","31417","31418"],"shops":[{"cardCode":"401005","cardName":"Guglialmelli Oscar S.A.","cardFName":"Armeria Jabali","address2":"Paraguay 1109 y Rodo"}],"listOrder":"02250-000960","id":31413,"slug":"31413","code":"31413","subcategory":"Zapatos de seguridad","images":["https://goldfarb.blob.core.windows.net/goldfarb/imagenes/31413.jpg"],"documents":[],"description":"* Zapatos de seguridad con puntera de plastico.\r\r* Collarin acolchado.\r\r* Hechos de cuero.\r\r* Cierre con cordones.\r\r* Forro interno y suela doble densidad."},"31414":{"itemCode":"31414","brand":{"name":"Workline","slug":"workline"},"invoices":76,"finalPrice":1065.2152,"hasStock":true,"title":"Zapato Negro S/Puntera Nro.36 Workline","family":"Ferreteria","category":"Proteccion","subCategory":"Zapatos de seguridad","discount":0,"currency":null,"price":0,"tax":22,"unitsPerItem":"PAR","unitMult":1,"relatedItems":["31413","31415","31416","31417","31418"],"shops":[{"cardCode":"401005","cardName":"Guglialmelli Oscar S.A.","cardFName":"Armeria Jabali","address2":"Paraguay 1109 y Rodo"}],"listOrder":"02250-000970","id":31414,"slug":"31414","code":"31414","subcategory":"Zapatos de seguridad","images":["https://goldfarb.blob.core.windows.net/goldfarb/imagenes/31414.jpg"],"documents":[],"description":"* Zapatos de seguridad con puntera de plastico.\r\r* Collarin acolchado.\r\r* Hechos de cuero.\r\r* Cierre con cordones.\r\r* Forro interno y suela doble densidad."},"31415":{"itemCode":"31415","brand":{"name":"Workline","slug":"workline"},"invoices":137,"finalPrice":1065.2152,"hasStock":true,"title":"Zapato Negro S/Puntera Nro.37 Workline","family":"Ferreteria","category":"Proteccion","subCategory":"Zapatos de seguridad","discount":0,"currency":null,"price":0,"tax":22,"unitsPerItem":"PAR","unitMult":1,"relatedItems":["31413","31414","31416","31417","31418"],"shops":[{"cardCode":"401005","cardName":"Guglialmelli Oscar S.A.","cardFName":"Armeria Jabali","address2":"Paraguay 1109 y Rodo"}],"listOrder":"02250-000980","id":31415,"slug":"31415","code":"31415","subcategory":"Zapatos de seguridad","images":["https://goldfarb.blob.core.windows.net/goldfarb/imagenes/31415.jpg"],"documents":[],"description":"* Zapatos de seguridad con puntera de plastico.\r\r* Collarin acolchado.\r\r* Hechos de cuero.\r\r* Cierre con cordones.\r\r* Forro interno y suela doble densidad."},"31416":{"itemCode":"31416","brand":{"name":"Workline","slug":"workline"},"invoices":283,"finalPrice":1065.2152,"hasStock":true,"title":"Zapato Negro S/Puntera Nro.38 Workline","family":"Ferreteria","category":"Proteccion","subCategory":"Zapatos de seguridad","discount":0,"currency":null,"price":0,"tax":22,"unitsPerItem":"PAR","unitMult":1,"relatedItems":["31413","31414","31415","31417","31418"],"shops":[{"cardCode":"401005","cardName":"Guglialmelli Oscar S.A.","cardFName":"Armeria Jabali","address2":"Paraguay 1109 y Rodo"}],"listOrder":"02250-000990","id":31416,"slug":"31416","code":"31416","subcategory":"Zapatos de seguridad","images":["https://goldfarb.blob.core.windows.net/goldfarb/imagenes/31416.jpg"],"documents":[],"description":"* Zapatos de seguridad con puntera de plastico.\r\r* Collarin acolchado.\r\r* Hechos de cuero.\r\r* Cierre con cordones.\r\r* Forro interno y suela doble densidad."},"31417":{"itemCode":"31417","brand":{"name":"Workline","slug":"workline"},"invoices":466,"finalPrice":1065.2152,"hasStock":true,"title":"Zapato Negro S/Puntera Nro.39 Workline","family":"Ferreteria","category":"Proteccion","subCategory":"Zapatos de seguridad","discount":0,"currency":null,"price":0,"tax":22,"unitsPerItem":"PAR","unitMult":1,"relatedItems":["31413","31414","31415","31416","31418"],"shops":[{"cardCode":"401005","cardName":"Guglialmelli Oscar S.A.","cardFName":"Armeria Jabali","address2":"Paraguay 1109 y Rodo"}],"listOrder":"02250-001000","id":31417,"slug":"31417","code":"31417","subcategory":"Zapatos de seguridad","images":["https://goldfarb.blob.core.windows.net/goldfarb/imagenes/31417.jpg"],"documents":[],"description":"* Zapatos de seguridad con puntera de plastico.\r\r* Collarin acolchado.\r\r* Hechos de cuero.\r\r* Cierre con cordones.\r\r* Forro interno y suela doble densidad."},"31418":{"itemCode":"31418","brand":{"name":"Workline","slug":"workline"},"invoices":840,"finalPrice":1065.2152,"hasStock":true,"title":"Zapato Negro S/Puntera Nro.40 Workline","family":"Ferreteria","category":"Proteccion","subCategory":"Zapatos de seguridad","discount":0,"currency":null,"price":0,"tax":22,"unitsPerItem":"PAR","unitMult":1,"relatedItems":["31413","31414","31415","31416","31417"],"shops":[{"cardCode":"401005","cardName":"Guglialmelli Oscar S.A.","cardFName":"Armeria Jabali","address2":"Paraguay 1109 y Rodo"}],"listOrder":"02250-001010","id":31418,"slug":"31418","code":"31418","subcategory":"Zapatos de seguridad","images":["https://goldfarb.blob.core.windows.net/goldfarb/imagenes/31418.jpg"],"documents":[],"description":"* Zapatos de seguridad con puntera de plastico.\r\r* Collarin acolchado.\r\r* Hechos de cuero.\r\r* Cierre con cordones.\r\r* Forro interno y suela doble densidad."},"31419":{"itemCode":"31419","brand":{"name":"Workline","slug":"workline"},"invoices":1070,"finalPrice":1065.2152,"hasStock":true,"title":"Zapato Negro S/Puntera Nro.41 Workline","family":"Ferreteria","category":"Proteccion","subCategory":"Zapatos de seguridad","discount":0,"currency":null,"price":0,"tax":22,"unitsPerItem":"PAR","unitMult":1,"relatedItems":["31413","31414","31415","31416","31417"],"shops":[{"cardCode":"401005","cardName":"Guglialmelli Oscar S.A.","cardFName":"Armeria Jabali","address2":"Paraguay 1109 y Rodo"}],"listOrder":"02250-001020","id":31419,"slug":"31419","code":"31419","subcategory":"Zapatos de seguridad","images":["https://goldfarb.blob.core.windows.net/goldfarb/imagenes/31419.jpg"],"documents":[],"description":"* Zapatos de seguridad con puntera de plastico.\r\r* Collarin acolchado.\r\r* Hechos de cuero.\r\r* Cierre con cordones.\r\r* Forro interno y suela doble densidad."},"31420":{"itemCode":"31420","brand":{"name":"Workline","slug":"workline"},"invoices":1216,"finalPrice":1065.2152,"hasStock":true,"title":"Zapato Negro S/Puntera Nro.42 Workline","family":"Ferreteria","category":"Proteccion","subCategory":"Zapatos de seguridad","discount":0,"currency":null,"price":0,"tax":22,"unitsPerItem":"PAR","unitMult":1,"relatedItems":["31413","31414","31415","31416","31417"],"shops":[{"cardCode":"401005","cardName":"Guglialmelli Oscar S.A.","cardFName":"Armeria Jabali","address2":"Paraguay 1109 y Rodo"}],"listOrder":"02250-001030","id":31420,"slug":"31420","code":"31420","subcategory":"Zapatos de seguridad","images":["https://goldfarb.blob.core.windows.net/goldfarb/imagenes/31420.jpg"],"documents":[],"description":"* Zapatos de seguridad con puntera de plastico.\r\r* Collarin acolchado.\r\r* Hechos de cuero.\r\r* Cierre con cordones.\r\r* Forro interno y suela doble densidad."},"31421":{"itemCode":"31421","brand":{"name":"Workline","slug":"workline"},"invoices":954,"finalPrice":1065.2152,"hasStock":true,"title":"Zapato Negro S/Puntera Nro.43 Workline","family":"Ferreteria","category":"Proteccion","subCategory":"Zapatos de seguridad","discount":0,"currency":null,"price":0,"tax":22,"unitsPerItem":"PAR","unitMult":1,"relatedItems":["31413","31414","31415","31416","31417"],"shops":[{"cardCode":"401005","cardName":"Guglialmelli Oscar S.A.","cardFName":"Armeria Jabali","address2":"Paraguay 1109 y Rodo"}],"listOrder":"02250-001040","id":31421,"slug":"31421","code":"31421","subcategory":"Zapatos de seguridad","images":["https://goldfarb.blob.core.windows.net/goldfarb/imagenes/31421.jpg"],"documents":[],"description":"* Zapatos de seguridad con puntera de plastico.\r\r* Collarin acolchado.\r\r* Hechos de cuero.\r\r* Cierre con cordones.\r\r* Forro interno y suela doble densidad."},"31422":{"itemCode":"31422","brand":{"name":"Workline","slug":"workline"},"invoices":660,"finalPrice":1065.2152,"hasStock":true,"title":"Zapato Negro S/Puntera Nro.44 Workline","family":"Ferreteria","category":"Proteccion","subCategory":"Zapatos de seguridad","discount":0,"currency":null,"price":0,"tax":22,"unitsPerItem":"PAR","unitMult":1,"relatedItems":["31413","31414","31415","31416","31417"],"shops":[{"cardCode":"401005","cardName":"Guglialmelli Oscar S.A.","cardFName":"Armeria Jabali","address2":"Paraguay 1109 y Rodo"}],"listOrder":"02250-001050","id":31422,"slug":"31422","code":"31422","subcategory":"Zapatos de seguridad","images":["https://goldfarb.blob.core.windows.net/goldfarb/imagenes/31422.jpg"],"documents":[],"description":"* Zapatos de seguridad con puntera de plastico.\r\r* Collarin acolchado.\r\r* Hechos de cuero.\r\r* Cierre con cordones.\r\r* Forro interno y suela doble densidad."},"31423":{"itemCode":"31423","brand":{"name":"Workline","slug":"workline"},"invoices":456,"finalPrice":1065.2152,"hasStock":true,"title":"Zapato Negro S/Puntera Nro.45 Workline","family":"Ferreteria","category":"Proteccion","subCategory":"Zapatos de seguridad","discount":0,"currency":null,"price":0,"tax":22,"unitsPerItem":"PAR","unitMult":1,"relatedItems":["31413","31414","31415","31416","31417"],"shops":[{"cardCode":"401005","cardName":"Guglialmelli Oscar S.A.","cardFName":"Armeria Jabali","address2":"Paraguay 1109 y Rodo"}],"listOrder":"02250-001060","id":31423,"slug":"31423","code":"31423","subcategory":"Zapatos de seguridad","images":["https://goldfarb.blob.core.windows.net/goldfarb/imagenes/31423.jpg"],"documents":[],"description":"* Zapatos de seguridad con puntera de plastico.\r\r* Collarin acolchado.\r\r* Hechos de cuero.\r\r* Cierre con cordones.\r\r* Forro interno y suela doble densidad."},"31424":{"itemCode":"31424","brand":{"name":"Workline","slug":"workline"},"invoices":199,"finalPrice":1065.2152,"hasStock":true,"title":"Zapato Negro S/Puntera Nro.46 Workline","family":"Ferreteria","category":"Proteccion","subCategory":"Zapatos de seguridad","discount":0,"currency":null,"price":0,"tax":22,"unitsPerItem":"PAR","unitMult":1,"relatedItems":["31413","31414","31415","31416","31417"],"shops":[{"cardCode":"401005","cardName":"Guglialmelli Oscar S.A.","cardFName":"Armeria Jabali","address2":"Paraguay 1109 y Rodo"}],"listOrder":"02250-001070","id":31424,"slug":"31424","code":"31424","subcategory":"Zapatos de seguridad","images":["https://goldfarb.blob.core.windows.net/goldfarb/imagenes/31424.jpg"],"documents":[],"description":"* Zapatos de seguridad con puntera de plastico.\r\r* Collarin acolchado.\r\r* Hechos de cuero.\r\r* Cierre con cordones.\r\r* Forro interno y suela doble densidad."},"31447":{"itemCode":"31447","brand":{"name":"Workline","slug":"workline"},"invoices":9,"finalPrice":1213.276,"hasStock":true,"title":"Zapato Amarillo S/Puntera Nro.43 Workline","family":"","category":"","subCategory":"","discount":0,"currency":null,"price":0,"tax":22,"unitsPerItem":"PAR","unitMult":1,"relatedItems":[],"shops":[{"cardCode":"401005","cardName":"Guglialmelli Oscar S.A.","cardFName":"Armeria Jabali","address2":"Paraguay 1109 y Rodo"}],"listOrder":"02250-000830","id":31447,"slug":"31447","code":"31447","subcategory":null,"images":["https://goldfarb.blob.core.windows.net/goldfarb/imagenes/31447.jpg"],"documents":[],"description":""},"31458":{"itemCode":"31458","brand":{"name":"Workline","slug":"workline"},"invoices":27,"finalPrice":1233.84,"hasStock":true,"title":"Botín Negro C/Puntera Nro.41 Workline","family":"Ferreteria","category":"Proteccion","subCategory":"Zapatos de seguridad","discount":0,"currency":null,"price":0,"tax":22,"unitsPerItem":"PAR","unitMult":1,"relatedItems":["15321","15322","31459","31460","31461"],"shops":[{"cardCode":"401005","cardName":"Guglialmelli Oscar S.A.","cardFName":"Armeria Jabali","address2":"Paraguay 1109 y Rodo"}],"listOrder":"02250-000660","id":31458,"slug":"31458","code":"31458","subcategory":"Zapatos de seguridad","images":["https://goldfarb.blob.core.windows.net/goldfarb/imagenes/31458.jpg"],"documents":[],"description":"* Botines ocupacionales con puntera.\r\r* Con puntera de plastico.\r\r* Collarin acolchado,\r\r* Hechos de cuero.\r\r* Cierre con cordones.\r\r* Forro interno y suela doble densidad."},"31459":{"itemCode":"31459","brand":{"name":"Workline","slug":"workline"},"invoices":33,"finalPrice":1233.84,"hasStock":true,"title":"Botín Negro C/Puntera Nro.42 Workline","family":"Ferreteria","category":"Proteccion","subCategory":"Zapatos de seguridad","discount":0,"currency":null,"price":0,"tax":22,"unitsPerItem":"PAR","unitMult":1,"relatedItems":["15321","15322","31458","31460","31461"],"shops":[{"cardCode":"401005","cardName":"Guglialmelli Oscar S.A.","cardFName":"Armeria Jabali","address2":"Paraguay 1109 y Rodo"}],"listOrder":"02250-000670","id":31459,"slug":"31459","code":"31459","subcategory":"Zapatos de seguridad","images":[],"documents":[],"description":"* Botines ocupacionales con puntera.\r\r* Con puntera de plastico.\r\r* Collarin acolchado,\r\r* Hechos de cuero.\r\r* Cierre con cordones.\r\r* Forro interno y suela doble densidad."},"31460":{"itemCode":"31460","brand":{"name":"Workline","slug":"workline"},"invoices":36,"finalPrice":1233.84,"hasStock":true,"title":"Botín Negro C/Puntera Nro.43 Workline","family":"Ferreteria","category":"Proteccion","subCategory":"Zapatos de seguridad","discount":0,"currency":null,"price":0,"tax":22,"unitsPerItem":"PAR","unitMult":1,"relatedItems":["15321","15322","31458","31459","31461"],"shops":[{"cardCode":"401005","cardName":"Guglialmelli Oscar S.A.","cardFName":"Armeria Jabali","address2":"Paraguay 1109 y Rodo"}],"listOrder":"02250-000680","id":31460,"slug":"31460","code":"31460","subcategory":"Zapatos de seguridad","images":["https://goldfarb.blob.core.windows.net/goldfarb/imagenes/31460.jpg"],"documents":[],"description":"* Botines ocupacionales con puntera.\r\r* Con puntera de plastico.\r\r* Collarin acolchado,\r\r* Hechos de cuero.\r\r* Cierre con cordones.\r\r* Forro interno y suela doble densidad."},"31461":{"itemCode":"31461","brand":{"name":"Workline","slug":"workline"},"invoices":20,"finalPrice":1233.84,"hasStock":true,"title":"Botín Negro C/Puntera Nro.44 Workline","family":"Ferreteria","category":"Proteccion","subCategory":"Zapatos de seguridad","discount":0,"currency":null,"price":0,"tax":22,"unitsPerItem":"PAR","unitMult":1,"relatedItems":["15321","15322","31458","31459","31460"],"shops":[{"cardCode":"401005","cardName":"Guglialmelli Oscar S.A.","cardFName":"Armeria Jabali","address2":"Paraguay 1109 y Rodo"}],"listOrder":"02250-000690","id":31461,"slug":"31461","code":"31461","subcategory":"Zapatos de seguridad","images":[],"documents":[],"description":"* Botines ocupacionales con puntera.\r\r* Con puntera de plastico.\r\r* Collarin acolchado,\r\r* Hechos de cuero.\r\r* Cierre con cordones.\r\r* Forro interno y suela doble densidad."},"31462":{"itemCode":"31462","brand":{"name":"Workline","slug":"workline"},"invoices":8,"finalPrice":1233.84,"hasStock":true,"title":"Botín Negro C/Puntera Nro.45 Workline","family":"Ferreteria","category":"Proteccion","subCategory":"Zapatos de seguridad","discount":0,"currency":null,"price":0,"tax":22,"unitsPerItem":"PAR","unitMult":1,"relatedItems":["15321","15322","31458","31459","31460"],"shops":[{"cardCode":"401005","cardName":"Guglialmelli Oscar S.A.","cardFName":"Armeria Jabali","address2":"Paraguay 1109 y Rodo"}],"listOrder":"02250-000700","id":31462,"slug":"31462","code":"31462","subcategory":"Zapatos de seguridad","images":["https://goldfarb.blob.core.windows.net/goldfarb/imagenes/31462.jpg"],"documents":[],"description":"* Botines ocupacionales con puntera.\r\r* Con puntera de plastico.\r\r* Collarin acolchado,\r\r* Hechos de cuero.\r\r* Cierre con cordones.\r\r* Forro interno y suela doble densidad."},"31463":{"itemCode":"31463","brand":{"name":"Workline","slug":"workline"},"invoices":5,"finalPrice":1233.84,"hasStock":true,"title":"Botín Negro C/Puntera Nro.46 Workline","family":"Ferreteria","category":"Proteccion","subCategory":"Zapatos de seguridad","discount":0,"currency":null,"price":0,"tax":22,"unitsPerItem":"PAR","unitMult":1,"relatedItems":["15321","15322","31458","31459","31460"],"shops":[{"cardCode":"401005","cardName":"Guglialmelli Oscar S.A.","cardFName":"Armeria Jabali","address2":"Paraguay 1109 y Rodo"}],"listOrder":"02250-000710","id":31463,"slug":"31463","code":"31463","subcategory":"Zapatos de seguridad","images":[],"documents":[],"description":"* Botines ocupacionales con puntera.\r\r* Con puntera de plastico.\r\r* Collarin acolchado,\r\r* Hechos de cuero.\r\r* Cierre con cordones.\r\r* Forro interno y suela doble densidad."},"31466":{"itemCode":"31466","brand":{"name":"Workline","slug":"workline"},"invoices":5,"finalPrice":1131.02,"hasStock":true,"title":"Botín Negro S/Puntera Nro.36 Workline","family":"Ferreteria","category":"Proteccion","subCategory":"Zapatos de seguridad","discount":0,"currency":null,"price":0,"tax":22,"unitsPerItem":"PAR","unitMult":1,"relatedItems":["15329","15335","15336","31468","31469"],"shops":[{"cardCode":"401005","cardName":"Guglialmelli Oscar S.A.","cardFName":"Armeria Jabali","address2":"Paraguay 1109 y Rodo"}],"listOrder":"02250-000720","id":31466,"slug":"31466","code":"31466","subcategory":"Zapatos de seguridad","images":["https://goldfarb.blob.core.windows.net/goldfarb/imagenes/31466.jpg"],"documents":[],"description":"* Botines ocupacionales con puntera de plastico.\r\r* Con puntera de plastico.\r\r* Collarin acolchado,\r\r* Hchos de cuero.\r\r* Cierre con cordones.\r\r* Forro interno y suela doble densidad."},"31468":{"itemCode":"31468","brand":{"name":"Workline","slug":"workline"},"invoices":20,"finalPrice":1131.02,"hasStock":true,"title":"Botín Negro S/Puntera Nro.38 Workline","family":"Ferreteria","category":"Proteccion","subCategory":"Zapatos de seguridad","discount":0,"currency":null,"price":0,"tax":22,"unitsPerItem":"PAR","unitMult":1,"relatedItems":["15329","15335","15336","31466","31469"],"shops":[{"cardCode":"401005","cardName":"Guglialmelli Oscar S.A.","cardFName":"Armeria Jabali","address2":"Paraguay 1109 y Rodo"}],"listOrder":"02250-000740","id":31468,"slug":"31468","code":"31468","subcategory":"Zapatos de seguridad","images":["https://goldfarb.blob.core.windows.net/goldfarb/imagenes/31468.jpg"],"documents":[],"description":"* Botines ocupacionales con puntera de plastico.\r\r* Con puntera de plastico.\r\r* Collarin acolchado,\r\r* Hchos de cuero.\r\r* Cierre con cordones.\r\r* Forro interno y suela doble densidad."},"31469":{"itemCode":"31469","brand":{"name":"Workline","slug":"workline"},"invoices":32,"finalPrice":1131.02,"hasStock":true,"title":"Botín Negro S/Puntera Nro.39 Workline","family":"Ferreteria","category":"Proteccion","subCategory":"Zapatos de seguridad","discount":0,"currency":null,"price":0,"tax":22,"unitsPerItem":"PAR","unitMult":1,"relatedItems":["15329","15335","15336","31466","31468"],"shops":[{"cardCode":"401005","cardName":"Guglialmelli Oscar S.A.","cardFName":"Armeria Jabali","address2":"Paraguay 1109 y Rodo"}],"listOrder":"02250-000750","id":31469,"slug":"31469","code":"31469","subcategory":"Zapatos de seguridad","images":[],"documents":[],"description":"* Botines ocupacionales con puntera de plastico.\r\r* Con puntera de plastico.\r\r* Collarin acolchado,\r\r* Hchos de cuero.\r\r* Cierre con cordones.\r\r* Forro interno y suela doble densidad."},"31470":{"itemCode":"31470","brand":{"name":"Workline","slug":"workline"},"invoices":59,"finalPrice":1131.02,"hasStock":true,"title":"Botín Negro S/Puntera Nro.40 Workline","family":"Ferreteria","category":"Proteccion","subCategory":"Zapatos de seguridad","discount":0,"currency":null,"price":0,"tax":22,"unitsPerItem":"PAR","unitMult":1,"relatedItems":["15329","15335","15336","31466","31468"],"shops":[{"cardCode":"401005","cardName":"Guglialmelli Oscar S.A.","cardFName":"Armeria Jabali","address2":"Paraguay 1109 y Rodo"}],"listOrder":"02250-000760","id":31470,"slug":"31470","code":"31470","subcategory":"Zapatos de seguridad","images":["https://goldfarb.blob.core.windows.net/goldfarb/imagenes/31470.jpg"],"documents":[],"description":"* Botines ocupacionales con puntera de plastico.\r\r* Con puntera de plastico.\r\r* Collarin acolchado,\r\r* Hechos de cuero.\r\r* Cierre con cordones.\r\r* Forro interno y suela doble densidad."},"31471":{"itemCode":"31471","brand":{"name":"Workline","slug":"workline"},"invoices":77,"finalPrice":1131.02,"hasStock":true,"title":"Botín Negro S/Puntera Nro.41 Workline","family":"Ferreteria","category":"Proteccion","subCategory":"Zapatos de seguridad","discount":0,"currency":null,"price":0,"tax":22,"unitsPerItem":"PAR","unitMult":1,"relatedItems":["15329","15335","15336","31466","31468"],"shops":[{"cardCode":"401005","cardName":"Guglialmelli Oscar S.A.","cardFName":"Armeria Jabali","address2":"Paraguay 1109 y Rodo"}],"listOrder":"02250-000770","id":31471,"slug":"31471","code":"31471","subcategory":"Zapatos de seguridad","images":[],"documents":[],"description":"* Botines ocupacionales con puntera de plastico.\r\r* Con puntera de plastico.\r\r* Collarin acolchado,\r\r* Hchos de cuero.\r\r* Cierre con cordones.\r\r* Forro interno y suela doble densidad."},"31472":{"itemCode":"31472","brand":{"name":"Workline","slug":"workline"},"invoices":109,"finalPrice":1131.02,"hasStock":true,"title":"Botín Negro S/Puntera Nro.42 Workline","family":"Ferreteria","category":"Proteccion","subCategory":"Zapatos de seguridad","discount":0,"currency":null,"price":0,"tax":22,"unitsPerItem":"PAR","unitMult":1,"relatedItems":["15329","15335","15336","31466","31468"],"shops":[{"cardCode":"401005","cardName":"Guglialmelli Oscar S.A.","cardFName":"Armeria Jabali","address2":"Paraguay 1109 y Rodo"}],"listOrder":"02250-000780","id":31472,"slug":"31472","code":"31472","subcategory":"Zapatos de seguridad","images":[],"documents":[],"description":"* Botines ocupacionales con puntera de plastico.\r\r* Con puntera de plastico.\r\r* Collarin acolchado,\r\r* Hchos de cuero.\r\r* Cierre con cordones.\r\r* Forro interno y suela doble densidad."},"31475":{"itemCode":"31475","brand":{"name":"Workline","slug":"workline"},"invoices":28,"finalPrice":1131.02,"hasStock":true,"title":"Botín Negro S/Puntera Nro.45 Workline","family":"Ferreteria","category":"Proteccion","subCategory":"Zapatos de seguridad","discount":0,"currency":null,"price":0,"tax":22,"unitsPerItem":"PAR","unitMult":1,"relatedItems":["15329","15335","15336","31466","31468"],"shops":[{"cardCode":"401005","cardName":"Guglialmelli Oscar S.A.","cardFName":"Armeria Jabali","address2":"Paraguay 1109 y Rodo"}],"listOrder":"02250-000810","id":31475,"slug":"31475","code":"31475","subcategory":"Zapatos de seguridad","images":["https://goldfarb.blob.core.windows.net/goldfarb/imagenes/31475.jpg"],"documents":[],"description":"* Botines ocupacionales con puntera de plastico.\r\r* Con puntera de plastico.\r\r* Collarin acolchado,\r\r* Hchos de cuero.\r\r* Cierre con cordones.\r\r* Forro interno y suela doble densidad."},"31476":{"itemCode":"31476","brand":{"name":"Workline","slug":"workline"},"invoices":8,"finalPrice":1131.02,"hasStock":true,"title":"Botín Negro S/Puntera Nro.46 Workline","family":"Ferreteria","category":"Proteccion","subCategory":"Zapatos de seguridad","discount":0,"currency":null,"price":0,"tax":22,"unitsPerItem":"PAR","unitMult":1,"relatedItems":["15329","15335","15336","31466","31468"],"shops":[{"cardCode":"401005","cardName":"Guglialmelli Oscar S.A.","cardFName":"Armeria Jabali","address2":"Paraguay 1109 y Rodo"}],"listOrder":"02250-000820","id":31476,"slug":"31476","code":"31476","subcategory":"Zapatos de seguridad","images":["https://goldfarb.blob.core.windows.net/goldfarb/imagenes/31476.jpg"],"documents":[],"description":"* Botines ocupacionales con puntera de plastico.\r\r* Con puntera de plastico.\r\r* Collarin acolchado,\r\r* Hchos de cuero.\r\r* Cierre con cordones.\r\r* Forro interno y suela doble densidad."},"31534":{"itemCode":"31534","brand":{"name":"Goldex","slug":"goldex"},"invoices":14,"finalPrice":431.844,"hasStock":true,"title":"Zapato Amarillo C/Puntera Nro.39 Goldex","family":"","category":"","subCategory":"","discount":0,"currency":null,"price":0,"tax":22,"unitsPerItem":"PAR","unitMult":1,"relatedItems":[],"shops":[{"cardCode":"401005","cardName":"Guglialmelli Oscar S.A.","cardFName":"Armeria Jabali","address2":"Paraguay 1109 y Rodo"}],"listOrder":"02250-000540","id":31534,"slug":"31534","code":"31534","subcategory":null,"images":["https://goldfarb.blob.core.windows.net/goldfarb/imagenes/31534.jpg"],"documents":[],"description":"Puntera de acero  Capellada 100% en poliuretano  Foroo de tela BK  Plantilla de tela BK y goma eva  Suela 100% en caucho  Resistente contra resbalones en superficies aceitosas"},"31920":{"itemCode":"31920","brand":{"name":"Mazzaferro","slug":"mazzaferro"},"invoices":77,"finalPrice":481.1976,"hasStock":true,"title":"Tanza Para Bordeadora Redonda 1.6mm. x 1Kg. 436m. Mazzaferro","family":"Agro y Jardin","category":"Accesorios","subCategory":"Tanzas","discount":0,"currency":null,"price":0,"tax":22,"unitsPerItem":"PIEZA","unitMult":1,"relatedItems":["31921","31922","31923","31924","31925"],"shops":[{"cardCode":"401005","cardName":"Guglialmelli Oscar S.A.","cardFName":"Armeria Jabali","address2":"Paraguay 1109 y Rodo"}],"listOrder":"02080-000220","id":31920,"slug":"31920","code":"31920","subcategory":"Tanzas","images":["https://goldfarb.blob.core.windows.net/goldfarb/imagenes/31920.jpg"],"documents":[],"description":""},"31921":{"itemCode":"31921","brand":{"name":"Mazzaferro","slug":"mazzaferro"},"invoices":143,"finalPrice":481.1976,"hasStock":true,"title":"Tanza Para Bordeadora Redonda 2.0mm. x 1Kg. 279m. Mazzaferro","family":"Agro y Jardin","category":"Accesorios","subCategory":"Tanzas","discount":0,"currency":null,"price":0,"tax":22,"unitsPerItem":"PIEZA","unitMult":1,"relatedItems":["31920","31922","31923","31924","31925"],"shops":[{"cardCode":"401005","cardName":"Guglialmelli Oscar S.A.","cardFName":"Armeria Jabali","address2":"Paraguay 1109 y Rodo"}],"listOrder":"02080-000230","id":31921,"slug":"31921","code":"31921","subcategory":"Tanzas","images":["https://goldfarb.blob.core.windows.net/goldfarb/imagenes/31921.jpg"],"documents":[],"description":""},"31922":{"itemCode":"31922","brand":{"name":"Mazzaferro","slug":"mazzaferro"},"invoices":351,"finalPrice":884.252,"hasStock":true,"title":"Tanza Para Bordeadora Redonda 2.4mm. x 2Kg. 388m. Mazzaferro","family":"Agro y Jardin","category":"Accesorios","subCategory":"Tanzas","discount":0,"currency":null,"price":0,"tax":22,"unitsPerItem":"PIEZA","unitMult":1,"relatedItems":["31920","31921","31923","31924","31925"],"shops":[{"cardCode":"401005","cardName":"Guglialmelli Oscar S.A.","cardFName":"Armeria Jabali","address2":"Paraguay 1109 y Rodo"}],"listOrder":"02080-000240","id":31922,"slug":"31922","code":"31922","subcategory":"Tanzas","images":["https://goldfarb.blob.core.windows.net/goldfarb/imagenes/31922.jpg"],"documents":[],"description":""},"31923":{"itemCode":"31923","brand":{"name":"Mazzaferro","slug":"mazzaferro"},"invoices":244,"finalPrice":884.252,"hasStock":true,"title":"Tanza Para Bordeadora Redonda 3.0mm. x 2Kg. 248m. Mazzaferro","family":"Agro y Jardin","category":"Accesorios","subCategory":"Tanzas","discount":0,"currency":null,"price":0,"tax":22,"unitsPerItem":"PIEZA","unitMult":1,"relatedItems":["31920","31921","31922","31924","31925"],"shops":[{"cardCode":"401005","cardName":"Guglialmelli Oscar S.A.","cardFName":"Armeria Jabali","address2":"Paraguay 1109 y Rodo"}],"listOrder":"02080-000250","id":31923,"slug":"31923","code":"31923","subcategory":"Tanzas","images":["https://goldfarb.blob.core.windows.net/goldfarb/imagenes/31923.jpg"],"documents":[],"description":""},"31924":{"itemCode":"31924","brand":{"name":"Mazzaferro","slug":"mazzaferro"},"invoices":276,"finalPrice":884.252,"hasStock":true,"title":"Tanza Para Bordeadora Cuadrada 2.4mm. x 2Kg. 304m. Mazzaferro","family":"Agro y Jardin","category":"Accesorios","subCategory":"Tanzas","discount":0,"currency":null,"price":0,"tax":22,"unitsPerItem":"PIEZA","unitMult":1,"relatedItems":["31920","31921","31922","31923","31925"],"shops":[{"cardCode":"401005","cardName":"Guglialmelli Oscar S.A.","cardFName":"Armeria Jabali","address2":"Paraguay 1109 y Rodo"}],"listOrder":"02080-000260","id":31924,"slug":"31924","code":"31924","subcategory":"Tanzas","images":["https://goldfarb.blob.core.windows.net/goldfarb/imagenes/31924.jpg"],"documents":[],"description":""},"31925":{"itemCode":"31925","brand":{"name":"Mazzaferro","slug":"mazzaferro"},"invoices":177,"finalPrice":884.252,"hasStock":true,"title":"Tanza Para Bordeadora Cuadrada 3.0mm. x 2Kg. 194m. Mazzaferro","family":"Agro y Jardin","category":"Accesorios","subCategory":"Tanzas","discount":0,"currency":null,"price":0,"tax":22,"unitsPerItem":"PIEZA","unitMult":1,"relatedItems":["31920","31921","31922","31923","31924"],"shops":[{"cardCode":"401005","cardName":"Guglialmelli Oscar S.A.","cardFName":"Armeria Jabali","address2":"Paraguay 1109 y Rodo"}],"listOrder":"02080-000270","id":31925,"slug":"31925","code":"31925","subcategory":"Tanzas","images":["https://goldfarb.blob.core.windows.net/goldfarb/imagenes/31925.jpg"],"documents":[],"description":""}}