{"4002":{"itemCode":"4002","brand":{"name":"Goldex","slug":"goldex"},"invoices":203,"finalPrice":361,"hasStock":true,"title":"Llave Ajustable 10\" Fosfatizada   Goldex","family":"Herramientas","category":"Herramientas Manuales","subCategory":"Llaves","discount":0,"currency":null,"price":0,"tax":22,"unitsPerItem":"PIEZA","unitMult":1,"relatedItems":[],"shops":[{"cardCode":"401005","cardName":"Guglialmelli Oscar S.A.","cardFName":"Armeria Jabali","address2":"Paraguay 1109 y Rodo"}],"listOrder":"01350-000140","id":4002,"slug":"4002","code":"4002","subcategory":"Llaves","images":["https://goldfarb.blob.core.windows.net/goldfarb/imagenes/4002.jpg"],"documents":[],"description":""},"4011":{"itemCode":"4011","brand":{"name":"Mustad","slug":"mustad"},"invoices":12,"finalPrice":711.5144,"hasStock":true,"title":"Herraduras 4Pz. P/Mano Maroñas Nº7 Aluminio Mustad","family":"Herramientas","category":"Prevención y Seguridad","subCategory":"Herraduras","discount":0,"currency":null,"price":0,"tax":22,"unitsPerItem":"CAJA","unitMult":1,"relatedItems":["22954","22950","22951","22952","22953"],"shops":[{"cardCode":"401005","cardName":"Guglialmelli Oscar S.A.","cardFName":"Armeria Jabali","address2":"Paraguay 1109 y Rodo"}],"listOrder":"01050-000530","id":4011,"slug":"4011","code":"4011","subcategory":"Herraduras","images":["https://goldfarb.blob.core.windows.net/goldfarb/imagenes/4011.jpg"],"documents":[],"description":""},"4012":{"itemCode":"4012","brand":{"name":"Mustad","slug":"mustad"},"invoices":12,"finalPrice":711.5144,"hasStock":true,"title":"Herraduras 4Pz. P/Pata Maroñas Nº7 Aluminio Mustad","family":"Herramientas","category":"Prevención y Seguridad","subCategory":"Herraduras","discount":0,"currency":null,"price":0,"tax":22,"unitsPerItem":"CAJA","unitMult":1,"relatedItems":["22954","22950","22951","22952","22953"],"shops":[{"cardCode":"401005","cardName":"Guglialmelli Oscar S.A.","cardFName":"Armeria Jabali","address2":"Paraguay 1109 y Rodo"}],"listOrder":"01050-000540","id":4012,"slug":"4012","code":"4012","subcategory":"Herraduras","images":["https://goldfarb.blob.core.windows.net/goldfarb/imagenes/4012.jpg"],"documents":[],"description":""},"4020":{"itemCode":"4020","brand":{"name":"Tramontina","slug":"tramontina"},"invoices":1087,"finalPrice":881,"hasStock":true,"title":"Llaves Combinadas 10Pz. 6 a 17mm. Tramontina 42241/210-4830/10","family":"Herramientas","category":"Herramientas Manuales","subCategory":"Llaves","discount":0,"currency":null,"price":0,"tax":22,"unitsPerItem":"JUEGO","unitMult":1,"relatedItems":["8146","8147","8148","8149","8160"],"shops":[{"cardCode":"401005","cardName":"Guglialmelli Oscar S.A.","cardFName":"Armeria Jabali","address2":"Paraguay 1109 y Rodo"}],"listOrder":"01390-000480","id":4020,"slug":"4020","code":"4020","subcategory":"Llaves","images":["https://goldfarb.blob.core.windows.net/goldfarb/imagenes/4020.jpg"],"documents":[],"description":"Cuerpo forjado en acero especial templado.\rAcabado cromado.\rApertura de las bocas calibradas.\rCuello largo.\rEl test de dureza es realizado en vários puntos para garantizar la resistência al desgaste de la llave por el uso constante.\rIncluye:\r\rllave : 6-7-8-10-11-12-13-14-16-17."},"4025":{"itemCode":"4025","brand":{"name":"Tramontina","slug":"tramontina"},"invoices":1832,"finalPrice":1743,"hasStock":true,"title":"Llaves Combinadas 17Pz. 6 a 22mm. Tramontina 42241/217-4830/17","family":"Herramientas","category":"Herramientas Manuales","subCategory":"Llaves","discount":0,"currency":null,"price":0,"tax":22,"unitsPerItem":"JUEGO","unitMult":1,"relatedItems":["8146","8147","8148","8149","8160"],"shops":[{"cardCode":"401005","cardName":"Guglialmelli Oscar S.A.","cardFName":"Armeria Jabali","address2":"Paraguay 1109 y Rodo"}],"listOrder":"01390-000490","id":4025,"slug":"4025","code":"4025","subcategory":"Llaves","images":["https://goldfarb.blob.core.windows.net/goldfarb/imagenes/4025.jpg"],"documents":[],"description":"Cuerpo forjado en acero especial templado.\rAcabado cromado.\rApertura de las bocas calibradas.\rCuello largo.\rEl test de dureza es realizado en vários puntos para garantizar la resistência al desgaste de la llave por el uso constante.\rIncluye:\r\r01 un - 42246106 - Llave combinada 6 mm\r01 un - 42246107 - Llave combinada 7mm\r01 un - 42246108 - Llave combinada 8 mm\r01 un - 42246109 - Llave combinada 9 mm\r01 un - 42246110 - Llave combinada 10 mm\r01 un - 42246111 - Llave combinada 11 mm\r01 un - 42246112 - Llave combinada 12 mm\r01 un - 42246113 - Llave combinada 13 mm\r01 un - 42246114 - Llave combinada 14 mm\r01 un - 42246115 - Llave combinada 15 mm\r01 un - 42246116 - Llave combinada 16 mm\r01 un - 42246117 - Llave combinada 17 mm\r01 un - 42246118 - Llave combinada 18 mm\r01 un - 42246119 - Llave combinada 19 mm\r01 un - 42246120 - Llave combinada 20 mm\r01 un - 42246121 - Llave combinada 21 mm\r01 un - 42246122 - Llave combinada 22 mm"},"4055":{"itemCode":"4055","brand":{"name":"Tramontina","slug":"tramontina"},"invoices":429,"finalPrice":244,"hasStock":true,"title":"Maceta Octogonal 500gr. Tramontina 40508/001-4350/01","family":"Herramientas","category":"Herramientas Manuales","subCategory":"Macetas","discount":0,"currency":null,"price":0,"tax":22,"unitsPerItem":"PIEZA","unitMult":1,"relatedItems":["33961","33960","33963","33962","33965"],"shops":[{"cardCode":"401005","cardName":"Guglialmelli Oscar S.A.","cardFName":"Armeria Jabali","address2":"Paraguay 1109 y Rodo"}],"listOrder":"01450-000150","id":4055,"slug":"4055","code":"4055","subcategory":"Macetas","images":["https://goldfarb.blob.core.windows.net/goldfarb/imagenes/4055.jpg"],"documents":[],"description":""},"4057":{"itemCode":"4057","brand":{"name":"Tramontina","slug":"tramontina"},"invoices":1126,"finalPrice":339,"hasStock":false,"title":"Maceta Cuadrada 1200gr. Tramontina 40502/002-4550/02","family":"Herramientas","category":"Herramientas Manuales","subCategory":"Macetas","discount":0,"currency":null,"price":0,"tax":22,"unitsPerItem":"PIEZA","unitMult":1,"relatedItems":["33961","33960","33963","33962","33965"],"shops":[{"cardCode":"401005","cardName":"Guglialmelli Oscar S.A.","cardFName":"Armeria Jabali","address2":"Paraguay 1109 y Rodo"}],"listOrder":"01450-000100","id":4057,"slug":"4057","code":"4057","subcategory":"Macetas","images":["https://goldfarb.blob.core.windows.net/goldfarb/imagenes/4057.jpg"],"documents":[],"description":""},"4058":{"itemCode":"4058","brand":{"name":"Tramontina","slug":"tramontina"},"invoices":1132,"finalPrice":422,"hasStock":true,"title":"Maceta Cuadrada 1500gr. Tramontina 40502/003-4550/03","family":"Herramientas","category":"Herramientas Manuales","subCategory":"Macetas","discount":0,"currency":null,"price":0,"tax":22,"unitsPerItem":"PIEZA","unitMult":1,"relatedItems":["33961","33960","33963","33962","33965"],"shops":[{"cardCode":"401005","cardName":"Guglialmelli Oscar S.A.","cardFName":"Armeria Jabali","address2":"Paraguay 1109 y Rodo"}],"listOrder":"01450-000120","id":4058,"slug":"4058","code":"4058","subcategory":"Macetas","images":["https://goldfarb.blob.core.windows.net/goldfarb/imagenes/4058.jpg"],"documents":[],"description":""},"4059":{"itemCode":"4059","brand":{"name":"Tramontina","slug":"tramontina"},"invoices":581,"finalPrice":479,"hasStock":true,"title":"Maceta Cuadrada 2000gr. Tramontina 40502/004-4550/04","family":"Herramientas","category":"Herramientas Manuales","subCategory":"Macetas","discount":0,"currency":null,"price":0,"tax":22,"unitsPerItem":"PIEZA","unitMult":1,"relatedItems":["33961","33960","33963","33962","33965"],"shops":[{"cardCode":"401005","cardName":"Guglialmelli Oscar S.A.","cardFName":"Armeria Jabali","address2":"Paraguay 1109 y Rodo"}],"listOrder":"01450-000130","id":4059,"slug":"4059","code":"4059","subcategory":"Macetas","images":["https://goldfarb.blob.core.windows.net/goldfarb/imagenes/4059.jpg"],"documents":[],"description":""},"4077":{"itemCode":"4077","brand":{"name":"Tramontina","slug":"tramontina"},"invoices":477,"finalPrice":309,"hasStock":true,"title":"Piqueta P/Soldador Tramontina 40455/000-4325","family":"Herramientas","category":"Herramientas Manuales","subCategory":"Piquetas","discount":0,"currency":null,"price":0,"tax":22,"unitsPerItem":"PIEZA","unitMult":1,"relatedItems":[],"shops":[{"cardCode":"401005","cardName":"Guglialmelli Oscar S.A.","cardFName":"Armeria Jabali","address2":"Paraguay 1109 y Rodo"}],"listOrder":"01740-000030","id":4077,"slug":"4077","code":"4077","subcategory":"Piquetas","images":["https://goldfarb.blob.core.windows.net/goldfarb/imagenes/4077.jpg"],"documents":[],"description":""},"4089":{"itemCode":"4089","brand":{"name":"Goldex","slug":"goldex"},"invoices":52,"finalPrice":361,"hasStock":true,"title":"Hoja De Sierra Circular 200mm. 24 Dientes (Incluye Buje 16mm.) Goldex","family":"Herramientas","category":"Accesorios","subCategory":"Sierras","discount":0,"currency":null,"price":0,"tax":22,"unitsPerItem":"PIEZA","unitMult":1,"relatedItems":["4090","4091"],"shops":[{"cardCode":"401005","cardName":"Guglialmelli Oscar S.A.","cardFName":"Armeria Jabali","address2":"Paraguay 1109 y Rodo"}],"listOrder":"01130-000050","id":4089,"slug":"4089","code":"4089","subcategory":"Sierras","images":["https://goldfarb.blob.core.windows.net/goldfarb/imagenes/4089.jpg"],"documents":[],"description":""},"4090":{"itemCode":"4090","brand":{"name":"Goldex","slug":"goldex"},"invoices":73,"finalPrice":820,"hasStock":true,"title":"Hoja De Sierra Circular 250mm. 40 Dientes Goldex","family":"Herramientas","category":"Accesorios","subCategory":"Sierras","discount":0,"currency":null,"price":0,"tax":22,"unitsPerItem":"PIEZA","unitMult":1,"relatedItems":["4089","4091"],"shops":[{"cardCode":"401005","cardName":"Guglialmelli Oscar S.A.","cardFName":"Armeria Jabali","address2":"Paraguay 1109 y Rodo"}],"listOrder":"01130-000080","id":4090,"slug":"4090","code":"4090","subcategory":"Sierras","images":["https://goldfarb.blob.core.windows.net/goldfarb/imagenes/4090.jpg"],"documents":[],"description":""},"4091":{"itemCode":"4091","brand":{"name":"Goldex","slug":"goldex"},"invoices":31,"finalPrice":1237,"hasStock":true,"title":"Hoja De Sierra Circular 300mm. 40 Dientes Goldex","family":"Herramientas","category":"Accesorios","subCategory":"Sierras","discount":0,"currency":null,"price":0,"tax":22,"unitsPerItem":"PIEZA","unitMult":1,"relatedItems":["4089","4090"],"shops":[{"cardCode":"401005","cardName":"Guglialmelli Oscar S.A.","cardFName":"Armeria Jabali","address2":"Paraguay 1109 y Rodo"}],"listOrder":"01130-000090","id":4091,"slug":"4091","code":"4091","subcategory":"Sierras","images":["https://goldfarb.blob.core.windows.net/goldfarb/imagenes/4091.jpg"],"documents":[],"description":""},"4122":{"itemCode":"4122","brand":{"name":"Arndt","slug":"arndt"},"invoices":4,"finalPrice":198,"hasStock":true,"title":"Llaves 911cvr-loch-258 Cr.Van.6Pz.Llaver","family":"Herramientas","category":"Herramientas Manuales","subCategory":"Llaves","discount":0,"currency":null,"price":0,"tax":22,"unitsPerItem":"JUEGO","unitMult":1,"relatedItems":["4125","4131"],"shops":[{"cardCode":"401005","cardName":"Guglialmelli Oscar S.A.","cardFName":"Armeria Jabali","address2":"Paraguay 1109 y Rodo"}],"listOrder":"01420-000140","id":4122,"slug":"4122","code":"4122","subcategory":"Llaves","images":["https://goldfarb.blob.core.windows.net/goldfarb/imagenes/4122.jpg"],"documents":[],"description":""},"4125":{"itemCode":"4125","brand":{"name":"Arndt","slug":"arndt"},"invoices":1,"finalPrice":622,"hasStock":true,"title":"Llaves 440ro511 Cr.Van.7Pz.Sobre Plast.","family":"Herramientas","category":"Herramientas Manuales","subCategory":"Llaves","discount":0,"currency":null,"price":0,"tax":22,"unitsPerItem":"JUEGO","unitMult":1,"relatedItems":["4122","4131"],"shops":[{"cardCode":"401005","cardName":"Guglialmelli Oscar S.A.","cardFName":"Armeria Jabali","address2":"Paraguay 1109 y Rodo"}],"listOrder":"01420-000130","id":4125,"slug":"4125","code":"4125","subcategory":"Llaves","images":["https://goldfarb.blob.core.windows.net/goldfarb/imagenes/4125.jpg"],"documents":[],"description":""},"4131":{"itemCode":"4131","brand":{"name":"Arndt","slug":"arndt"},"invoices":15,"finalPrice":1978,"hasStock":true,"title":"Puntas Para Destornillador 2715 22Pz. En Estuche De Metal Arndt","family":"Herramientas","category":"Herramientas Manuales","subCategory":"Puntas","discount":0,"currency":null,"price":0,"tax":22,"unitsPerItem":"JUEGO","unitMult":1,"relatedItems":["4125","4122"],"shops":[{"cardCode":"401005","cardName":"Guglialmelli Oscar S.A.","cardFName":"Armeria Jabali","address2":"Paraguay 1109 y Rodo"}],"listOrder":"00690-002500","id":4131,"slug":"4131","code":"4131","subcategory":"Puntas","images":["https://goldfarb.blob.core.windows.net/goldfarb/imagenes/4131.jpg"],"documents":[],"description":""},"4136":{"itemCode":"4136","brand":{"name":"Tramontina","slug":"tramontina"},"invoices":860,"finalPrice":393,"hasStock":true,"title":"Escobilla Metálica Regulable C/Mango 22 Dientes Tramontina 77840/721-77847/601","family":"Herramientas","category":"Herramientas Manuales","subCategory":"Escobillas","discount":0,"currency":null,"price":0,"tax":22,"unitsPerItem":"PIEZA","unitMult":1,"relatedItems":["2862","21349","33937","16838","16863"],"shops":[{"cardCode":"401005","cardName":"Guglialmelli Oscar S.A.","cardFName":"Armeria Jabali","address2":"Paraguay 1109 y Rodo"}],"listOrder":"00870-000030","id":4136,"slug":"4136","code":"4136","subcategory":"Escobillas","images":["https://goldfarb.blob.core.windows.net/goldfarb/imagenes/4136.jpg"],"documents":[],"description":""},"4141":{"itemCode":"4141","brand":{"name":"Goldex","slug":"goldex"},"invoices":68,"finalPrice":3191,"hasStock":true,"title":"Corona P/Transmision Hormigonera Diente Recto P/Cod.4270 Goldex","family":"Herramientas","category":"Herramientas Eléctricas","subCategory":"Coronas","discount":0,"currency":null,"price":0,"tax":22,"unitsPerItem":"PIEZA","unitMult":1,"relatedItems":["36619","4270","22504","32195"],"shops":[{"cardCode":"401005","cardName":"Guglialmelli Oscar S.A.","cardFName":"Armeria Jabali","address2":"Paraguay 1109 y Rodo"}],"listOrder":"01190-000070","id":4141,"slug":"4141","code":"4141","subcategory":"Coronas","images":["https://goldfarb.blob.core.windows.net/goldfarb/imagenes/4141.jpg"],"documents":[],"description":"Diamtro 5cm.\rDiametro total:33cm.\rCantidad dientes 104."},"4211":{"itemCode":"4211","brand":{"name":"Goldex","slug":"goldex"},"invoices":13,"finalPrice":225,"hasStock":true,"title":"Mandril Conico  6mm. (1/4'') Chino","family":"Herramientas","category":"Accesorios","subCategory":"Mandriles","discount":0,"currency":null,"price":0,"tax":22,"unitsPerItem":"PIEZA","unitMult":1,"relatedItems":["22541","6398","4213","4214","3239"],"shops":[{"cardCode":"401005","cardName":"Guglialmelli Oscar S.A.","cardFName":"Armeria Jabali","address2":"Paraguay 1109 y Rodo"}],"listOrder":"01470-000120","id":4211,"slug":"4211","code":"4211","subcategory":"Mandriles","images":["https://goldfarb.blob.core.windows.net/goldfarb/imagenes/4211.jpg"],"documents":[],"description":""},"4213":{"itemCode":"4213","brand":{"name":"Goldex","slug":"goldex"},"invoices":270,"finalPrice":494,"hasStock":false,"title":"Mandril Conico (B16) 13mm. (1/2'') Chino","family":"Herramientas","category":"Accesorios","subCategory":"Mandriles","discount":0,"currency":null,"price":0,"tax":22,"unitsPerItem":"PIEZA","unitMult":1,"relatedItems":["22541","6398","4211","4214","3239"],"shops":[{"cardCode":"401005","cardName":"Guglialmelli Oscar S.A.","cardFName":"Armeria Jabali","address2":"Paraguay 1109 y Rodo"}],"listOrder":"01470-000140","id":4213,"slug":"4213","code":"4213","subcategory":"Mandriles","images":["https://goldfarb.blob.core.windows.net/goldfarb/imagenes/4213.jpg"],"documents":[],"description":""},"4214":{"itemCode":"4214","brand":{"name":"Goldex","slug":"goldex"},"invoices":283,"finalPrice":572,"hasStock":true,"title":"Mandril Conico 16mm. (5/8'') Chino","family":"Herramientas","category":"Accesorios","subCategory":"Mandriles","discount":0,"currency":null,"price":0,"tax":22,"unitsPerItem":"PIEZA","unitMult":1,"relatedItems":["22541","6398","4211","4213","3239"],"shops":[{"cardCode":"401005","cardName":"Guglialmelli Oscar S.A.","cardFName":"Armeria Jabali","address2":"Paraguay 1109 y Rodo"}],"listOrder":"01470-000150","id":4214,"slug":"4214","code":"4214","subcategory":"Mandriles","images":["https://goldfarb.blob.core.windows.net/goldfarb/imagenes/4214.jpg"],"documents":[],"description":""},"4220":{"itemCode":"4220","brand":{"name":"Goldex","slug":"goldex"},"invoices":295,"finalPrice":253,"hasStock":true,"title":"Correa Para Hormigonera Cod.4270 Goldex","family":"Herramientas","category":"Herramientas Eléctricas","subCategory":"Correas","discount":0,"currency":null,"price":0,"tax":22,"unitsPerItem":"PIEZA","unitMult":1,"relatedItems":["36619","4270","22504","32195"],"shops":[{"cardCode":"401005","cardName":"Guglialmelli Oscar S.A.","cardFName":"Armeria Jabali","address2":"Paraguay 1109 y Rodo"}],"listOrder":"01190-000090","id":4220,"slug":"4220","code":"4220","subcategory":"Correas","images":["https://goldfarb.blob.core.windows.net/goldfarb/imagenes/4220.jpg"],"documents":[],"description":"Modelo A30"},"4230":{"itemCode":"4230","brand":{"name":"Goldex","slug":"goldex"},"invoices":416,"finalPrice":212,"hasStock":true,"title":"Mandril C/rosca Hembra 3/8x24 H.   Goldex","family":"Herramientas","category":"Accesorios","subCategory":"Mandriles","discount":0,"currency":null,"price":0,"tax":22,"unitsPerItem":"PIEZA","unitMult":1,"relatedItems":["22541","6398","4211","4213","4214"],"shops":[{"cardCode":"401005","cardName":"Guglialmelli Oscar S.A.","cardFName":"Armeria Jabali","address2":"Paraguay 1109 y Rodo"}],"listOrder":"04205-000810","id":4230,"slug":"4230","code":"4230","subcategory":"Mandriles","images":["https://goldfarb.blob.core.windows.net/goldfarb/imagenes/4230.jpg"],"documents":[],"description":""},"4231":{"itemCode":"4231","brand":{"name":"Goldex","slug":"goldex"},"invoices":649,"finalPrice":259,"hasStock":true,"title":"Mandril C/rosca Hembra 1/2x20 H.   Goldex","family":"Herramientas","category":"Accesorios","subCategory":"Mandriles","discount":0,"currency":null,"price":0,"tax":22,"unitsPerItem":"PIEZA","unitMult":1,"relatedItems":["22541","6398","4211","4213","4214"],"shops":[{"cardCode":"401005","cardName":"Guglialmelli Oscar S.A.","cardFName":"Armeria Jabali","address2":"Paraguay 1109 y Rodo"}],"listOrder":"04205-000800","id":4231,"slug":"4231","code":"4231","subcategory":"Mandriles","images":["https://goldfarb.blob.core.windows.net/goldfarb/imagenes/4231.jpg"],"documents":[],"description":""},"4255":{"itemCode":"4255","brand":{"name":"Goldex","slug":"goldex"},"invoices":269,"finalPrice":801,"hasStock":false,"title":"Rueda De Goma P/Hormigonera Econova Cod.22504 Goldex","family":"Herramientas","category":"Herramientas Manuales","subCategory":"Ruedas","discount":0,"currency":null,"price":0,"tax":22,"unitsPerItem":"PIEZA","unitMult":1,"relatedItems":["36619","4270","22504","32195"],"shops":[{"cardCode":"401005","cardName":"Guglialmelli Oscar S.A.","cardFName":"Armeria Jabali","address2":"Paraguay 1109 y Rodo"}],"listOrder":"01190-000240","id":4255,"slug":"4255","code":"4255","subcategory":"Ruedas","images":["https://goldfarb.blob.core.windows.net/goldfarb/imagenes/4255.jpg"],"documents":[],"description":""},"4259":{"itemCode":"4259","brand":{"name":"Goldex","slug":"goldex"},"invoices":162,"finalPrice":465,"hasStock":true,"title":"Piñon Recto Para Hormigonera Cod.4270 Goldex","family":"Herramientas","category":"Herramientas Manuales","subCategory":"Piñones","discount":0,"currency":null,"price":0,"tax":22,"unitsPerItem":"PIEZA","unitMult":1,"relatedItems":["36619","4270","22504","32195"],"shops":[{"cardCode":"401005","cardName":"Guglialmelli Oscar S.A.","cardFName":"Armeria Jabali","address2":"Paraguay 1109 y Rodo"}],"listOrder":"01190-000190","id":4259,"slug":"4259","code":"4259","subcategory":"Piñones","images":["https://goldfarb.blob.core.windows.net/goldfarb/imagenes/4259.jpg"],"documents":[],"description":""},"4260":{"itemCode":"4260","brand":{"name":"Goldex","slug":"goldex"},"invoices":435,"finalPrice":963,"hasStock":true,"title":"Volante Repuesto P/Hormigonera Cod.4270/32193/36619 Goldex","family":"Herramientas","category":"Herramientas Eléctricas","subCategory":"Volantes","discount":0,"currency":null,"price":0,"tax":22,"unitsPerItem":"PIEZA","unitMult":1,"relatedItems":["36619","4270","22504","32195"],"shops":[{"cardCode":"401005","cardName":"Guglialmelli Oscar S.A.","cardFName":"Armeria Jabali","address2":"Paraguay 1109 y Rodo"}],"listOrder":"01190-000290","id":4260,"slug":"4260","code":"4260","subcategory":"Volantes","images":["https://goldfarb.blob.core.windows.net/goldfarb/imagenes/4260.jpg"],"documents":[],"description":"Diametro 23 cm.\rBuje 5/8."},"4265":{"itemCode":"4265","brand":{"name":"Goldex","slug":"goldex"},"invoices":345,"finalPrice":569,"hasStock":true,"title":"Polea Repuesto Para Hormigonera Cod.4270 Goldex","family":"Herramientas","category":"Accesorios","subCategory":"Poleas","discount":0,"currency":null,"price":0,"tax":22,"unitsPerItem":"PIEZA","unitMult":1,"relatedItems":["36619","4270","22504","32195"],"shops":[{"cardCode":"401005","cardName":"Guglialmelli Oscar S.A.","cardFName":"Armeria Jabali","address2":"Paraguay 1109 y Rodo"}],"listOrder":"01190-000220","id":4265,"slug":"4265","code":"4265","subcategory":"Poleas","images":["https://goldfarb.blob.core.windows.net/goldfarb/imagenes/4265.jpg"],"documents":[],"description":""},"4270":{"itemCode":"4270","brand":{"name":"Goldex","slug":"goldex"},"invoices":2398,"finalPrice":15669.768,"hasStock":true,"title":"Hormigonera 130lt. Motor Weg 3/4Hp. Roja Goldex","family":"Herramientas","category":"Herramientas Eléctricas","subCategory":"Hormigoneras","discount":0,"currency":null,"price":0,"tax":22,"unitsPerItem":"PIEZA","unitMult":1,"relatedItems":["36619","22504","32195"],"shops":[{"cardCode":"401005","cardName":"Guglialmelli Oscar S.A.","cardFName":"Armeria Jabali","address2":"Paraguay 1109 y Rodo"}],"listOrder":"01190-000030","id":4270,"slug":"4270","code":"4270","subcategory":"Hormigoneras","images":["https://goldfarb.blob.core.windows.net/goldfarb/imagenes/4270.jpg"],"documents":[],"description":"* Motor electrico montado sobre rulemanes \r* Llave de corte con protector antihumedad de PVC \r* Potencia de 3/4 HP \r* Capacidad de tacho 130 lt.\r* 1 año de garantía"},"4288":{"itemCode":"4288","brand":{"name":"Tramontina","slug":"tramontina"},"invoices":290,"finalPrice":157,"hasStock":true,"title":"Martillo De Uña 18mm. Tramontina 40370/018-40300/018-4130/18","family":"Herramientas","category":"Herramientas Manuales","subCategory":"Martillos","discount":0,"currency":null,"price":0,"tax":22,"unitsPerItem":"PIEZA","unitMult":1,"relatedItems":["4321","4322","15383","15384","15385"],"shops":[{"cardCode":"401005","cardName":"Guglialmelli Oscar S.A.","cardFName":"Armeria Jabali","address2":"Paraguay 1109 y Rodo"}],"listOrder":"01510-000330","id":4288,"slug":"4288","code":"4288","subcategory":"Martillos","images":["https://goldfarb.blob.core.windows.net/goldfarb/imagenes/4288.jpg"],"documents":[],"description":""},"4289":{"itemCode":"4289","brand":{"name":"Tramontina","slug":"tramontina"},"invoices":396,"finalPrice":162,"hasStock":false,"title":"Martillo De Uña 20mm. Tramontina 40370/020-4130/20-40300/020","family":"Herramientas","category":"Herramientas Manuales","subCategory":"Martillos","discount":0,"currency":null,"price":0,"tax":22,"unitsPerItem":"PIEZA","unitMult":1,"relatedItems":["4321","4322","15383","15384","15385"],"shops":[{"cardCode":"401005","cardName":"Guglialmelli Oscar S.A.","cardFName":"Armeria Jabali","address2":"Paraguay 1109 y Rodo"}],"listOrder":"01510-000340","id":4289,"slug":"4289","code":"4289","subcategory":"Martillos","images":["https://goldfarb.blob.core.windows.net/goldfarb/imagenes/4289.jpg"],"documents":[],"description":""},"4290":{"itemCode":"4290","brand":{"name":"Tramontina","slug":"tramontina"},"invoices":807,"finalPrice":176,"hasStock":true,"title":"Martillo De Uña 23mm. Tramontina 40370/023-4130/23-40300/023","family":"Herramientas","category":"Herramientas Manuales","subCategory":"Martillos","discount":0,"currency":null,"price":0,"tax":22,"unitsPerItem":"PIEZA","unitMult":1,"relatedItems":["4321","4322","15383","15384","15385"],"shops":[{"cardCode":"401005","cardName":"Guglialmelli Oscar S.A.","cardFName":"Armeria Jabali","address2":"Paraguay 1109 y Rodo"}],"listOrder":"01510-000350","id":4290,"slug":"4290","code":"4290","subcategory":"Martillos","images":["https://goldfarb.blob.core.windows.net/goldfarb/imagenes/4290.jpg"],"documents":[],"description":""},"4291":{"itemCode":"4291","brand":{"name":"Tramontina","slug":"tramontina"},"invoices":1089,"finalPrice":196,"hasStock":true,"title":"Martillo De Uña 25mm. Tramontina 40370/025-4130/25-40300/025","family":"Herramientas","category":"Herramientas Manuales","subCategory":"Martillos","discount":0,"currency":null,"price":0,"tax":22,"unitsPerItem":"PIEZA","unitMult":1,"relatedItems":["4321","4322","15383","15384","15385"],"shops":[{"cardCode":"401005","cardName":"Guglialmelli Oscar S.A.","cardFName":"Armeria Jabali","address2":"Paraguay 1109 y Rodo"}],"listOrder":"01510-000360","id":4291,"slug":"4291","code":"4291","subcategory":"Martillos","images":["https://goldfarb.blob.core.windows.net/goldfarb/imagenes/4291.jpg"],"documents":[],"description":""},"4306":{"itemCode":"4306","brand":{"name":"Goldex","slug":"goldex"},"invoices":42,"finalPrice":152,"hasStock":true,"title":"Martillo De Bola 1.1/2lb    Goldex/chino","family":"Herramientas","category":"Herramientas Manuales","subCategory":"Martillos","discount":0,"currency":null,"price":0,"tax":22,"unitsPerItem":"PIEZA","unitMult":1,"relatedItems":["22652","22604","22653","22654","4316"],"shops":[{"cardCode":"401005","cardName":"Guglialmelli Oscar S.A.","cardFName":"Armeria Jabali","address2":"Paraguay 1109 y Rodo"}],"listOrder":"01510-000100","id":4306,"slug":"4306","code":"4306","subcategory":"Martillos","images":["https://goldfarb.blob.core.windows.net/goldfarb/imagenes/4306.jpg"],"documents":[],"description":""},"4316":{"itemCode":"4316","brand":{"name":"Goldex","slug":"goldex"},"invoices":81,"finalPrice":131,"hasStock":true,"title":"Martillo De Pena 500gr      Goldex/chino","family":"Herramientas","category":"Herramientas Manuales","subCategory":"Martillos","discount":0,"currency":null,"price":0,"tax":22,"unitsPerItem":"PIEZA","unitMult":1,"relatedItems":["4306","22652","22604","22653","22654"],"shops":[{"cardCode":"401005","cardName":"Guglialmelli Oscar S.A.","cardFName":"Armeria Jabali","address2":"Paraguay 1109 y Rodo"}],"listOrder":"01510-000240","id":4316,"slug":"4316","code":"4316","subcategory":"Martillos","images":["https://goldfarb.blob.core.windows.net/goldfarb/imagenes/4316.jpg"],"documents":[],"description":""},"4321":{"itemCode":"4321","brand":{"name":"Tramontina","slug":"tramontina"},"invoices":261,"finalPrice":190,"hasStock":true,"title":"Martillo De Bola C/Mango Madera 100gr. Tramontina 40410/004","family":"Herramientas","category":"Herramientas Manuales","subCategory":"Martillos","discount":0,"currency":null,"price":0,"tax":22,"unitsPerItem":"PIEZA","unitMult":1,"relatedItems":["4322","15383","15384","15385","15386"],"shops":[{"cardCode":"401005","cardName":"Guglialmelli Oscar S.A.","cardFName":"Armeria Jabali","address2":"Paraguay 1109 y Rodo"}],"listOrder":"01510-000120","id":4321,"slug":"4321","code":"4321","subcategory":"Martillos","images":["https://goldfarb.blob.core.windows.net/goldfarb/imagenes/4321.jpg"],"documents":[],"description":""},"4322":{"itemCode":"4322","brand":{"name":"Tramontina","slug":"tramontina"},"invoices":335,"finalPrice":260,"hasStock":true,"title":"Martillo De Bola C/Mango Madera 200gr. Tramontina 40410/008-40400/008","family":"Herramientas","category":"Herramientas Manuales","subCategory":"Martillos","discount":0,"currency":null,"price":0,"tax":22,"unitsPerItem":"PIEZA","unitMult":1,"relatedItems":["4321","15383","15384","15385","15386"],"shops":[{"cardCode":"401005","cardName":"Guglialmelli Oscar S.A.","cardFName":"Armeria Jabali","address2":"Paraguay 1109 y Rodo"}],"listOrder":"01510-000130","id":4322,"slug":"4322","code":"4322","subcategory":"Martillos","images":["https://goldfarb.blob.core.windows.net/goldfarb/imagenes/4322.jpg"],"documents":[],"description":""},"4325":{"itemCode":"4325","brand":{"name":"Rubi","slug":"rubi"},"invoices":1492,"finalPrice":822.56,"hasStock":true,"title":"Rodel 10mm. Widia 01946 P/cortadores Tr. Ts Y Tf              Rubi","family":"Herramientas","category":"Accesorios","subCategory":"Rodeles","discount":0,"currency":null,"price":0,"tax":22,"unitsPerItem":"PIEZA","unitMult":1,"relatedItems":["4326","17240","17201","17241","17202"],"shops":[{"cardCode":"401005","cardName":"Guglialmelli Oscar S.A.","cardFName":"Armeria Jabali","address2":"Paraguay 1109 y Rodo"}],"listOrder":"04300-000500","id":4325,"slug":"4325","code":"4325","subcategory":"Rodeles","images":["https://goldfarb.blob.core.windows.net/goldfarb/imagenes/4325.jpg"],"documents":[],"description":"Incisión poco profunda y ancha\rIdeal para revestimientos de cerámicas con leve rugosidad\rRulina fabricada en Carburo de Tungsteno de alta resistencia y duración"},"4326":{"itemCode":"4326","brand":{"name":"Rubi","slug":"rubi"},"invoices":1584,"finalPrice":653.9352,"hasStock":true,"title":"Rodel  6mm. Widia 01945 P/cortadores Tr. Ts Y Tf              Rubi","family":"Herramientas","category":"Accesorios","subCategory":"Rodeles","discount":0,"currency":null,"price":0,"tax":22,"unitsPerItem":"PIEZA","unitMult":1,"relatedItems":["17240","4325","17201","17241","17202"],"shops":[{"cardCode":"401005","cardName":"Guglialmelli Oscar S.A.","cardFName":"Armeria Jabali","address2":"Paraguay 1109 y Rodo"}],"listOrder":"04300-000460","id":4326,"slug":"4326","code":"4326","subcategory":"Rodeles","images":["https://goldfarb.blob.core.windows.net/goldfarb/imagenes/4326.jpg"],"documents":[],"description":"Incisión rápida y fina, de profundidad baja\rIdeal para revestimientos de cerámicas \rRulina fabricada en Carburo de Tungsteno de alta resistencia y duración"},"4327":{"itemCode":"4327","brand":{"name":"Rubi","slug":"rubi"},"invoices":80,"finalPrice":1098.1176,"hasStock":true,"title":"Mecha 35mm. Perforación Cerámicas Rubi  04962","family":"Herramientas","category":"Accesorios","subCategory":"Mechas","discount":0,"currency":null,"price":0,"tax":22,"unitsPerItem":"PIEZA","unitMult":5,"relatedItems":["35222","17212","17206","17581","17204"],"shops":[{"cardCode":"401005","cardName":"Guglialmelli Oscar S.A.","cardFName":"Armeria Jabali","address2":"Paraguay 1109 y Rodo"}],"listOrder":"04300-002580","id":4327,"slug":"4327","code":"4327","subcategory":"Mechas","images":["https://goldfarb.blob.core.windows.net/goldfarb/imagenes/4327.jpg"],"documents":[],"description":"Brocas de Carburo de Tungsteno para taladrar azulejos. Adaptables al taladro manual y al cabezal para uso con taladro eléctrico sin percutor (cod.17206"},"4531":{"itemCode":"4531","brand":{"name":"Tramontina","slug":"tramontina"},"invoices":657,"finalPrice":176,"hasStock":true,"title":"Martillo De Pena C/Mango De Madera 100gr. Tramontina 40443/002-40440/002","family":"Herramientas","category":"Herramientas Manuales","subCategory":"Martillos","discount":0,"currency":null,"price":0,"tax":22,"unitsPerItem":"PIEZA","unitMult":1,"relatedItems":["4321","4322","15383","15384","15385"],"shops":[{"cardCode":"401005","cardName":"Guglialmelli Oscar S.A.","cardFName":"Armeria Jabali","address2":"Paraguay 1109 y Rodo"}],"listOrder":"01510-000260","id":4531,"slug":"4531","code":"4531","subcategory":"Martillos","images":["https://goldfarb.blob.core.windows.net/goldfarb/imagenes/4531.jpg"],"documents":[],"description":""},"4532":{"itemCode":"4532","brand":{"name":"Tramontina","slug":"tramontina"},"invoices":371,"finalPrice":195,"hasStock":true,"title":"Martillo De Pena C/Mango De Madera 150gr. Tramontina 40443/003-40440/003","family":"Herramientas","category":"Herramientas Manuales","subCategory":"Martillos","discount":0,"currency":null,"price":0,"tax":22,"unitsPerItem":"PIEZA","unitMult":1,"relatedItems":["4321","4322","15383","15384","15385"],"shops":[{"cardCode":"401005","cardName":"Guglialmelli Oscar S.A.","cardFName":"Armeria Jabali","address2":"Paraguay 1109 y Rodo"}],"listOrder":"01510-000270","id":4532,"slug":"4532","code":"4532","subcategory":"Martillos","images":["https://goldfarb.blob.core.windows.net/goldfarb/imagenes/4532.jpg"],"documents":[],"description":""},"4533":{"itemCode":"4533","brand":{"name":"Tramontina","slug":"tramontina"},"invoices":897,"finalPrice":195,"hasStock":true,"title":"Martillo De Pena C/Mango De Madera 200gr. Tramontina 40443/004-40440/004","family":"Herramientas","category":"Herramientas Manuales","subCategory":"Martillos","discount":0,"currency":null,"price":0,"tax":22,"unitsPerItem":"PIEZA","unitMult":1,"relatedItems":["4321","4322","15383","15384","15385"],"shops":[{"cardCode":"401005","cardName":"Guglialmelli Oscar S.A.","cardFName":"Armeria Jabali","address2":"Paraguay 1109 y Rodo"}],"listOrder":"01510-000280","id":4533,"slug":"4533","code":"4533","subcategory":"Martillos","images":["https://goldfarb.blob.core.windows.net/goldfarb/imagenes/4533.jpg"],"documents":[],"description":""},"4534":{"itemCode":"4534","brand":{"name":"Tramontina","slug":"tramontina"},"invoices":775,"finalPrice":209,"hasStock":true,"title":"Martillo De Pena C/Mango De Madera 300gr. Tramontina 40443/005-40440/005","family":"Herramientas","category":"Herramientas Manuales","subCategory":"Martillos","discount":0,"currency":null,"price":0,"tax":22,"unitsPerItem":"PIEZA","unitMult":1,"relatedItems":["4321","4322","15383","15384","15385"],"shops":[{"cardCode":"401005","cardName":"Guglialmelli Oscar S.A.","cardFName":"Armeria Jabali","address2":"Paraguay 1109 y Rodo"}],"listOrder":"01510-000290","id":4534,"slug":"4534","code":"4534","subcategory":"Martillos","images":["https://goldfarb.blob.core.windows.net/goldfarb/imagenes/4534.jpg"],"documents":[],"description":""},"4535":{"itemCode":"4535","brand":{"name":"Tramontina","slug":"tramontina"},"invoices":449,"finalPrice":232,"hasStock":true,"title":"Martillo De Pena C/Mango De Madera 400gr. Tramontina 40443/006-40440/006","family":"Herramientas","category":"Herramientas Manuales","subCategory":"Martillos","discount":0,"currency":null,"price":0,"tax":22,"unitsPerItem":"PIEZA","unitMult":1,"relatedItems":["4321","4322","15383","15384","15385"],"shops":[{"cardCode":"401005","cardName":"Guglialmelli Oscar S.A.","cardFName":"Armeria Jabali","address2":"Paraguay 1109 y Rodo"}],"listOrder":"01510-000300","id":4535,"slug":"4535","code":"4535","subcategory":"Martillos","images":["https://goldfarb.blob.core.windows.net/goldfarb/imagenes/4535.jpg"],"documents":[],"description":""},"4536":{"itemCode":"4536","brand":{"name":"Tramontina","slug":"tramontina"},"invoices":241,"finalPrice":245,"hasStock":true,"title":"Martillo De Pena C/Mango De Madera 500gr. Tramontina 40443/007-40440/007","family":"Herramientas","category":"Herramientas Manuales","subCategory":"Martillos","discount":0,"currency":null,"price":0,"tax":22,"unitsPerItem":"PIEZA","unitMult":1,"relatedItems":["4321","4322","15383","15384","15385"],"shops":[{"cardCode":"401005","cardName":"Guglialmelli Oscar S.A.","cardFName":"Armeria Jabali","address2":"Paraguay 1109 y Rodo"}],"listOrder":"01510-000310","id":4536,"slug":"4536","code":"4536","subcategory":"Martillos","images":["https://goldfarb.blob.core.windows.net/goldfarb/imagenes/4536.jpg"],"documents":[],"description":""},"4567":{"itemCode":"4567","brand":{"name":"Durafilt","slug":"durafilt"},"invoices":0,"finalPrice":355.7572,"hasStock":false,"title":"Repuesto Original De Elemento Filtrante P/Comp. 3Hp. Goldex","family":"Herramientas","category":"Accesorios","subCategory":"Repuestos","discount":0,"currency":null,"price":0,"tax":22,"unitsPerItem":"PIEZA","unitMult":1,"relatedItems":[],"shops":[{"cardCode":"401005","cardName":"Guglialmelli Oscar S.A.","cardFName":"Armeria Jabali","address2":"Paraguay 1109 y Rodo"}],"listOrder":"00620-000400","id":4567,"slug":"4567","code":"4567","subcategory":"Repuestos","images":["https://goldfarb.blob.core.windows.net/goldfarb/imagenes/4567.jpg"],"documents":[],"description":""},"4661":{"itemCode":"4661","brand":{"name":"Stabila","slug":"stabila"},"invoices":5736,"finalPrice":373,"hasStock":false,"title":"Metro Plegable Madera 2m. 607 Stabila","family":"Herramientas","category":"Ferretería","subCategory":"Metros","discount":0,"currency":null,"price":0,"tax":22,"unitsPerItem":"PIEZA","unitMult":1,"relatedItems":[],"shops":[{"cardCode":"401005","cardName":"Guglialmelli Oscar S.A.","cardFName":"Armeria Jabali","address2":"Paraguay 1109 y Rodo"}],"listOrder":"01570-000040","id":4661,"slug":"4661","code":"4661","subcategory":"Metros","images":["https://goldfarb.blob.core.windows.net/goldfarb/imagenes/4661.jpg"],"documents":[],"description":""},"4673":{"itemCode":"4673","brand":{"name":"Tramontina","slug":"tramontina"},"invoices":1085,"finalPrice":245,"hasStock":true,"title":"Alicate Universal 8'' Doble Aislación Tramontina 41001/118","family":"Herramientas","category":"Herramientas Manuales","subCategory":"Alicates","discount":0,"currency":null,"price":0,"tax":22,"unitsPerItem":"PIEZA","unitMult":1,"relatedItems":["1921","4674","1922","1951","1895"],"shops":[{"cardCode":"401005","cardName":"Guglialmelli Oscar S.A.","cardFName":"Armeria Jabali","address2":"Paraguay 1109 y Rodo"}],"listOrder":"00110-000310","id":4673,"slug":"4673","code":"4673","subcategory":"Alicates","images":["https://goldfarb.blob.core.windows.net/goldfarb/imagenes/4673.jpg"],"documents":[],"description":""},"4674":{"itemCode":"4674","brand":{"name":"Tramontina","slug":"tramontina"},"invoices":971,"finalPrice":245,"hasStock":true,"title":"Alicate Corte Diagonal 6'' Doble Aislación Tramontina 41006/116","family":"Herramientas","category":"Herramientas Manuales","subCategory":"Alicates","discount":0,"currency":null,"price":0,"tax":22,"unitsPerItem":"PIEZA","unitMult":1,"relatedItems":["1921","1922","1951","1895","1896"],"shops":[{"cardCode":"401005","cardName":"Guglialmelli Oscar S.A.","cardFName":"Armeria Jabali","address2":"Paraguay 1109 y Rodo"}],"listOrder":"00110-000240","id":4674,"slug":"4674","code":"4674","subcategory":"Alicates","images":["https://goldfarb.blob.core.windows.net/goldfarb/imagenes/4674.jpg"],"documents":[],"description":""},"4678":{"itemCode":"4678","brand":{"name":"Tramontina","slug":"tramontina"},"invoices":531,"finalPrice":1198,"hasStock":true,"title":"Tijera De Podar Profesional Tramontina 78305/501-78305/801","family":"Herramientas","category":"Herramientas Manuales","subCategory":"Tijeras","discount":0,"currency":null,"price":0,"tax":22,"unitsPerItem":"PIEZA","unitMult":1,"relatedItems":["15429","5688","21353","33941","16945"],"shops":[{"cardCode":"401005","cardName":"Guglialmelli Oscar S.A.","cardFName":"Armeria Jabali","address2":"Paraguay 1109 y Rodo"}],"listOrder":"02170-000170","id":4678,"slug":"4678","code":"4678","subcategory":"Tijeras","images":["https://goldfarb.blob.core.windows.net/goldfarb/imagenes/4678.jpg"],"documents":[],"description":""},"4685":{"itemCode":"4685","brand":{"name":"Chino","slug":"chino"},"invoices":115,"finalPrice":74.6,"hasStock":true,"title":"Mirilla 1/2''x180ºzp-03 35-50mm. Met.Cromado","family":"Herramientas","category":"Herramientas Manuales","subCategory":"Mirillas","discount":0,"currency":null,"price":0,"tax":22,"unitsPerItem":"PIEZA","unitMult":1,"relatedItems":[],"shops":[{"cardCode":"401005","cardName":"Guglialmelli Oscar S.A.","cardFName":"Armeria Jabali","address2":"Paraguay 1109 y Rodo"}],"listOrder":"01590-000030","id":4685,"slug":"4685","code":"4685","subcategory":"Mirillas","images":["https://goldfarb.blob.core.windows.net/goldfarb/imagenes/4685.jpg"],"documents":[],"description":""},"4703":{"itemCode":"4703","brand":{"name":"Tramontina","slug":"tramontina"},"invoices":1042,"finalPrice":258,"hasStock":false,"title":"Rastrillo 16 Dientes C/Mango De Madera Tramontina 77110/664","family":"Herramientas","category":"Herramientas Manuales","subCategory":"Rastrillos","discount":0,"currency":null,"price":0,"tax":22,"unitsPerItem":"PIEZA","unitMult":1,"relatedItems":["33956","5087","5088"],"shops":[{"cardCode":"401005","cardName":"Guglialmelli Oscar S.A.","cardFName":"Armeria Jabali","address2":"Paraguay 1109 y Rodo"}],"listOrder":"01910-000050","id":4703,"slug":"4703","code":"4703","subcategory":"Rastrillos","images":["https://goldfarb.blob.core.windows.net/goldfarb/imagenes/4703.jpg"],"documents":[],"description":""},"4708":{"itemCode":"4708","brand":{"name":"Tramontina","slug":"tramontina"},"invoices":2126,"finalPrice":771,"hasStock":false,"title":"Pico Punta y Pala C/Cabo 90cm./2.87kg. Tramontina 77303/553","family":"Herramientas","category":"Herramientas Manuales","subCategory":"Picos","discount":0,"currency":null,"price":0,"tax":22,"unitsPerItem":"PIEZA","unitMult":1,"relatedItems":["16860"],"shops":[{"cardCode":"401005","cardName":"Guglialmelli Oscar S.A.","cardFName":"Armeria Jabali","address2":"Paraguay 1109 y Rodo"}],"listOrder":"01670-000040","id":4708,"slug":"4708","code":"4708","subcategory":"Picos","images":["https://goldfarb.blob.core.windows.net/goldfarb/imagenes/4708.jpg"],"documents":[],"description":""},"4710":{"itemCode":"4710","brand":{"name":"Gherardi","slug":"gherardi"},"invoices":65,"finalPrice":1342,"hasStock":true,"title":"Pala De Palear Cuadrada Sin Cabo 50cm. Gherardi","family":"Herramientas","category":"Herramientas Manuales","subCategory":"Palas","discount":0,"currency":null,"price":0,"tax":22,"unitsPerItem":"PIEZA","unitMult":1,"relatedItems":["4786","1726","4788","4787","4819"],"shops":[{"cardCode":"401005","cardName":"Guglialmelli Oscar S.A.","cardFName":"Armeria Jabali","address2":"Paraguay 1109 y Rodo"}],"listOrder":"01660-000220","id":4710,"slug":"4710","code":"4710","subcategory":"Palas","images":["https://goldfarb.blob.core.windows.net/goldfarb/imagenes/4710.jpg"],"documents":[],"description":""},"4714":{"itemCode":"4714","brand":{"name":"Goldex","slug":"goldex"},"invoices":46,"finalPrice":7444.168,"hasStock":true,"title":"Motor Elect. 1.5Hp. Mono 1400Rpm 90s4 Goldex","family":"Herramientas","category":"Herramientas Eléctricas","subCategory":"Motores","discount":0,"currency":null,"price":0,"tax":22,"unitsPerItem":"PIEZA","unitMult":1,"relatedItems":["22293","22295","36640","36637","36639"],"shops":[{"cardCode":"401005","cardName":"Guglialmelli Oscar S.A.","cardFName":"Armeria Jabali","address2":"Paraguay 1109 y Rodo"}],"listOrder":"01620-000050","id":4714,"slug":"4714","code":"4714","subcategory":"Motores","images":["https://goldfarb.blob.core.windows.net/goldfarb/imagenes/4714.jpg"],"documents":[],"description":""},"4715":{"itemCode":"4715","brand":{"name":"Goldex","slug":"goldex"},"invoices":571,"finalPrice":352,"hasStock":false,"title":"Punta 250mm. Encastre SDS P/Rotomartillo 26mm. Goldex","family":"Herramientas","category":"Accesorios","subCategory":"Puntas","discount":0,"currency":null,"price":0,"tax":22,"unitsPerItem":"PIEZA","unitMult":1,"relatedItems":["23066","22491","22492","22489","22490"],"shops":[{"cardCode":"401005","cardName":"Guglialmelli Oscar S.A.","cardFName":"Armeria Jabali","address2":"Paraguay 1109 y Rodo"}],"listOrder":"04205-000870","id":4715,"slug":"4715","code":"4715","subcategory":"Puntas","images":["https://goldfarb.blob.core.windows.net/goldfarb/imagenes/4715.jpg"],"documents":[],"description":"Encastre SDS Plus.\rLongitud 25 cm."},"4716":{"itemCode":"4716","brand":{"name":"Goldex","slug":"goldex"},"invoices":439,"finalPrice":352,"hasStock":false,"title":"Cincel 250mm. Encastre SDS P/Rotomartillo 26mm. Goldex","family":"Herramientas","category":"Herramientas Manuales","subCategory":"Cinceles","discount":0,"currency":null,"price":0,"tax":22,"unitsPerItem":"PIEZA","unitMult":1,"relatedItems":["23066","22491","22492","22489","22490"],"shops":[{"cardCode":"401005","cardName":"Guglialmelli Oscar S.A.","cardFName":"Armeria Jabali","address2":"Paraguay 1109 y Rodo"}],"listOrder":"04205-000220","id":4716,"slug":"4716","code":"4716","subcategory":"Cinceles","images":["https://goldfarb.blob.core.windows.net/goldfarb/imagenes/4716.jpg"],"documents":[],"description":"Encastre SDS Plus.\rLongitud 25 cm."},"4783":{"itemCode":"4783","brand":{"name":"Tramontina","slug":"tramontina"},"invoices":100,"finalPrice":310,"hasStock":true,"title":"Nivel De Aluminio 45cm. Tramontina 43100/018-4895/18","family":"Herramientas","category":"Herramientas Manuales","subCategory":"Niveles","discount":0,"currency":null,"price":0,"tax":22,"unitsPerItem":"PIEZA","unitMult":1,"relatedItems":["16882","16883"],"shops":[{"cardCode":"401005","cardName":"Guglialmelli Oscar S.A.","cardFName":"Armeria Jabali","address2":"Paraguay 1109 y Rodo"}],"listOrder":"01650-000340","id":4783,"slug":"4783","code":"4783","subcategory":"Niveles","images":["https://goldfarb.blob.core.windows.net/goldfarb/imagenes/4783.jpg"],"documents":[],"description":""},"4785":{"itemCode":"4785","brand":{"name":"Goldex","slug":"goldex"},"invoices":97,"finalPrice":99.3,"hasStock":true,"title":"Nivel Aluminio 35cm. 3 Gotas Chino","family":"Herramientas","category":"Herramientas Manuales","subCategory":"Niveles","discount":0,"currency":null,"price":0,"tax":22,"unitsPerItem":"PIEZA","unitMult":1,"relatedItems":["22598","22656","22657","22658","22659"],"shops":[{"cardCode":"401005","cardName":"Guglialmelli Oscar S.A.","cardFName":"Armeria Jabali","address2":"Paraguay 1109 y Rodo"}],"listOrder":"01650-000360","id":4785,"slug":"4785","code":"4785","subcategory":"Niveles","images":["https://goldfarb.blob.core.windows.net/goldfarb/imagenes/4785.jpg"],"documents":[],"description":""},"4786":{"itemCode":"4786","brand":{"name":"Gherardi","slug":"gherardi"},"invoices":456,"finalPrice":1895,"hasStock":true,"title":"Pala De Palear Cabo Madera 1.03m. Mango En ''Y'' Gherardi","family":"Herramientas","category":"Herramientas Manuales","subCategory":"Palas","discount":0,"currency":null,"price":0,"tax":22,"unitsPerItem":"PIEZA","unitMult":1,"relatedItems":["4710","1726","4788","4787","4819"],"shops":[{"cardCode":"401005","cardName":"Guglialmelli Oscar S.A.","cardFName":"Armeria Jabali","address2":"Paraguay 1109 y Rodo"}],"listOrder":"01660-000230","id":4786,"slug":"4786","code":"4786","subcategory":"Palas","images":["https://goldfarb.blob.core.windows.net/goldfarb/imagenes/4786.jpg"],"documents":[],"description":""},"4787":{"itemCode":"4787","brand":{"name":"Gherardi","slug":"gherardi"},"invoices":105,"finalPrice":1897,"hasStock":true,"title":"Pala 1/2 Luna Angosta Pestaña Adentro Cabo Madera 1.07m. Mango ''Y'' Gherardi","family":"Herramientas","category":"Herramientas Manuales","subCategory":"Palas","discount":0,"currency":null,"price":0,"tax":22,"unitsPerItem":"PIEZA","unitMult":1,"relatedItems":["4710","4786","1726","4788","4819"],"shops":[{"cardCode":"401005","cardName":"Guglialmelli Oscar S.A.","cardFName":"Armeria Jabali","address2":"Paraguay 1109 y Rodo"}],"listOrder":"01660-000260","id":4787,"slug":"4787","code":"4787","subcategory":"Palas","images":["https://goldfarb.blob.core.windows.net/goldfarb/imagenes/4787.jpg"],"documents":[],"description":""},"4788":{"itemCode":"4788","brand":{"name":"Gherardi","slug":"gherardi"},"invoices":366,"finalPrice":1895,"hasStock":true,"title":"Pala Recta P/Césped Cabo Madera 1.07m. Mango ''Y'' Gherardi","family":"Herramientas","category":"Herramientas Manuales","subCategory":"Palas","discount":0,"currency":null,"price":0,"tax":22,"unitsPerItem":"PIEZA","unitMult":1,"relatedItems":["4710","4786","1726","4787","4819"],"shops":[{"cardCode":"401005","cardName":"Guglialmelli Oscar S.A.","cardFName":"Armeria Jabali","address2":"Paraguay 1109 y Rodo"}],"listOrder":"01660-000250","id":4788,"slug":"4788","code":"4788","subcategory":"Palas","images":["https://goldfarb.blob.core.windows.net/goldfarb/imagenes/4788.jpg"],"documents":[],"description":""},"4819":{"itemCode":"4819","brand":{"name":"Gherardi","slug":"gherardi"},"invoices":59,"finalPrice":1897,"hasStock":true,"title":"Pala 1/2 Luna Angosta Pestaña Afuera Cabo Madera 1.07m. Mango ''Y'' Gherardi","family":"Herramientas","category":"Herramientas Manuales","subCategory":"Palas","discount":0,"currency":null,"price":0,"tax":22,"unitsPerItem":"PIEZA","unitMult":1,"relatedItems":["4710","4786","1726","4788","4787"],"shops":[{"cardCode":"401005","cardName":"Guglialmelli Oscar S.A.","cardFName":"Armeria Jabali","address2":"Paraguay 1109 y Rodo"}],"listOrder":"01660-000270","id":4819,"slug":"4819","code":"4819","subcategory":"Palas","images":["https://goldfarb.blob.core.windows.net/goldfarb/imagenes/4819.jpg"],"documents":[],"description":""},"4853":{"itemCode":"4853","brand":{"name":"Tramontina","slug":"tramontina"},"invoices":448,"finalPrice":535,"hasStock":false,"title":"Pala Cerealera C/Mango De Madera 71cm. Tramontina 77481/424","family":"Herramientas","category":"Herramientas Manuales","subCategory":"Palas","discount":0,"currency":null,"price":0,"tax":22,"unitsPerItem":"PIEZA","unitMult":1,"relatedItems":["4862","4870","33912","4866","4867"],"shops":[{"cardCode":"401005","cardName":"Guglialmelli Oscar S.A.","cardFName":"Armeria Jabali","address2":"Paraguay 1109 y Rodo"}],"listOrder":"01660-000100","id":4853,"slug":"4853","code":"4853","subcategory":"Palas","images":["https://goldfarb.blob.core.windows.net/goldfarb/imagenes/4853.jpg"],"documents":[],"description":""},"4855":{"itemCode":"4855","brand":{"name":"Tramontina","slug":"tramontina"},"invoices":1080,"finalPrice":666,"hasStock":false,"title":"Pala Pozo B.Largos 1.20m. Tramontina 77562/503-7534/70","family":"Herramientas","category":"Herramientas Manuales","subCategory":"Palas","discount":0,"currency":null,"price":0,"tax":22,"unitsPerItem":"PIEZA","unitMult":1,"relatedItems":["4862","4853","4870","33912","4866"],"shops":[{"cardCode":"401005","cardName":"Guglialmelli Oscar S.A.","cardFName":"Armeria Jabali","address2":"Paraguay 1109 y Rodo"}],"listOrder":"01660-000160","id":4855,"slug":"4855","code":"4855","subcategory":"Palas","images":["https://goldfarb.blob.core.windows.net/goldfarb/imagenes/4855.jpg"],"documents":[],"description":""},"4862":{"itemCode":"4862","brand":{"name":"Tramontina","slug":"tramontina"},"invoices":1035,"finalPrice":74.3,"hasStock":true,"title":"Pala De Jardín C/Mango De Madera 30cm. Tramontina 77907/001-77902","family":"Herramientas","category":"Herramientas Manuales","subCategory":"Palas","discount":0,"currency":null,"price":0,"tax":22,"unitsPerItem":"PIEZA","unitMult":1,"relatedItems":["4853","4870","33912","4866","4867"],"shops":[{"cardCode":"401005","cardName":"Guglialmelli Oscar S.A.","cardFName":"Armeria Jabali","address2":"Paraguay 1109 y Rodo"}],"listOrder":"01230-000120","id":4862,"slug":"4862","code":"4862","subcategory":"Palas","images":["https://goldfarb.blob.core.windows.net/goldfarb/imagenes/4862.jpg"],"documents":[],"description":""},"4865":{"itemCode":"4865","brand":{"name":"Tramontina","slug":"tramontina"},"invoices":1900,"finalPrice":356,"hasStock":false,"title":"Pala Recta C/Mango De Madera 71cm. Tramontina 77400/424-7400/42","family":"Herramientas","category":"Herramientas Manuales","subCategory":"Palas","discount":0,"currency":null,"price":0,"tax":22,"unitsPerItem":"PIEZA","unitMult":1,"relatedItems":["4862","4853","4870","33912","4866"],"shops":[{"cardCode":"401005","cardName":"Guglialmelli Oscar S.A.","cardFName":"Armeria Jabali","address2":"Paraguay 1109 y Rodo"}],"listOrder":"01660-000190","id":4865,"slug":"4865","code":"4865","subcategory":"Palas","images":["https://goldfarb.blob.core.windows.net/goldfarb/imagenes/4865.jpg"],"documents":[],"description":""},"4866":{"itemCode":"4866","brand":{"name":"Tramontina","slug":"tramontina"},"invoices":3027,"finalPrice":422,"hasStock":true,"title":"Pala De Palear C/Mango De Madera 71cm. Tramontina 77417/424-77465/434-77415/434","family":"Herramientas","category":"Herramientas Manuales","subCategory":"Palas","discount":0,"currency":null,"price":0,"tax":22,"unitsPerItem":"PIEZA","unitMult":1,"relatedItems":["4862","4853","4870","33912","4867"],"shops":[{"cardCode":"401005","cardName":"Guglialmelli Oscar S.A.","cardFName":"Armeria Jabali","address2":"Paraguay 1109 y Rodo"}],"listOrder":"01660-000140","id":4866,"slug":"4866","code":"4866","subcategory":"Palas","images":["https://goldfarb.blob.core.windows.net/goldfarb/imagenes/4866.jpg"],"documents":[],"description":"Pala Cuadrada c/mango\r\r\rPeso    1,68 kg\rLongitud    1088 mm\rAncho    242 mm\rAltura    110 mm\r\r La pala se fabrica en acero al carbono especial de alta calidad, y se corta con láser.\r Es templada en todo el cuerpo de la pieza, proporcionando más resistencia y menos desgaste durante el uso.\r Recibe pintura electrostática a polvo, que tiene mejor presentación visual y mayor protección contra la oxidación.\r El mango de 71 cm de esta herramienta, además de tener excelente resistencia, se fabrica con madera de origen renovable.\r Mango con terminación barnizada para una mejor presentación del producto.\r La capa protectora de barniz incoloro realza su tonalidad, concediéndole brillo y un toque más liso al producto.\r Tiene empuñadura plástica.\rHecho en Brasil"},"4867":{"itemCode":"4867","brand":{"name":"Tramontina","slug":"tramontina"},"invoices":433,"finalPrice":408,"hasStock":false,"title":"Pala Media Luna C/Mango De Madera 71cm. Tramontina 77426/404-7426/40","family":"Herramientas","category":"Herramientas Manuales","subCategory":"Palas","discount":0,"currency":null,"price":0,"tax":22,"unitsPerItem":"PIEZA","unitMult":1,"relatedItems":["4862","4853","4870","33912","4866"],"shops":[{"cardCode":"401005","cardName":"Guglialmelli Oscar S.A.","cardFName":"Armeria Jabali","address2":"Paraguay 1109 y Rodo"}],"listOrder":"01660-000150","id":4867,"slug":"4867","code":"4867","subcategory":"Palas","images":["https://goldfarb.blob.core.windows.net/goldfarb/imagenes/4867.jpg"],"documents":[],"description":""},"4868":{"itemCode":"4868","brand":{"name":"Tramontina","slug":"tramontina"},"invoices":280,"finalPrice":358,"hasStock":false,"title":"Pala De Palear C/Mango De Madera 71cm. Tramontina 77472/424-7472/2","family":"Herramientas","category":"Herramientas Manuales","subCategory":"Palas","discount":0,"currency":null,"price":0,"tax":22,"unitsPerItem":"PIEZA","unitMult":1,"relatedItems":["17419","17415","28751","20666","20665"],"shops":[{"cardCode":"401005","cardName":"Guglialmelli Oscar S.A.","cardFName":"Armeria Jabali","address2":"Paraguay 1109 y Rodo"}],"listOrder":"01660-000130","id":4868,"slug":"4868","code":"4868","subcategory":"Palas","images":["https://goldfarb.blob.core.windows.net/goldfarb/imagenes/4868.jpg"],"documents":[],"description":"La pala se fabrica en acero al carbono especial de alta calidad, y se corta con láser.\rEs templada en todo el cuerpo de la pieza, proporcionando más resistencia y menos desgaste durante el uso.\rRecibe pintura electrostática a polvo, que tiene mejor presentación visual y mayor protección contra la oxidación.\rEl mango de 71 cm de esta herramienta, además de tener excelente resistencia, se fabrica con madera de origen renovable.\rMango con terminación barnizada para una mejor presentación el producto. \rTiene empuñadura plástica ergonómica.\r Pala liviana, que le genera menos esfuerzo físico al usuario y le proporciona más productividad.\rRecomendaciones de uso\t- La pala se utiliza en agricultura, jardinería y construcción civil, para juntar o cargar diversos materiales (como arena, pedregullo y tierra) en superficies planas."},"4870":{"itemCode":"4870","brand":{"name":"Tramontina","slug":"tramontina"},"invoices":589,"finalPrice":356,"hasStock":true,"title":"Pala Corazón C/Mango De Madera 71cm. Tramontina 77402/404-7402/40","family":"Herramientas","category":"Herramientas Manuales","subCategory":"Palas","discount":0,"currency":null,"price":0,"tax":22,"unitsPerItem":"PIEZA","unitMult":1,"relatedItems":["4862","4853","33912","4866","4867"],"shops":[{"cardCode":"401005","cardName":"Guglialmelli Oscar S.A.","cardFName":"Armeria Jabali","address2":"Paraguay 1109 y Rodo"}],"listOrder":"01660-000110","id":4870,"slug":"4870","code":"4870","subcategory":"Palas","images":["https://goldfarb.blob.core.windows.net/goldfarb/imagenes/4870.jpg"],"documents":[],"description":""},"4877":{"itemCode":"4877","brand":{"name":"Corea","slug":"corea"},"invoices":187,"finalPrice":6.62,"hasStock":false,"title":"Broche Plastico De Sujecion P/Tejido Sombra","family":"Herramientas","category":"Ferretería","subCategory":"Broches","discount":0,"currency":null,"price":0,"tax":0,"unitsPerItem":"PIEZA","unitMult":25,"relatedItems":["5081","5082","20460"],"shops":[{"cardCode":"401005","cardName":"Guglialmelli Oscar S.A.","cardFName":"Armeria Jabali","address2":"Paraguay 1109 y Rodo"}],"listOrder":"02090-000070","id":4877,"slug":"4877","code":"4877","subcategory":"Broches","images":["https://goldfarb.blob.core.windows.net/goldfarb/imagenes/4877.jpg"],"documents":[],"description":""},"4878":{"itemCode":"4878","brand":{"name":"Aleman","slug":"aleman"},"invoices":24,"finalPrice":113,"hasStock":true,"title":"Piedras 5Pz. Punta Montada P.Taladro Ale","family":"Herramientas","category":"Herramientas Manuales","subCategory":"Piedras","discount":0,"currency":null,"price":0,"tax":22,"unitsPerItem":"JUEGO","unitMult":1,"relatedItems":[],"shops":[{"cardCode":"401005","cardName":"Guglialmelli Oscar S.A.","cardFName":"Armeria Jabali","address2":"Paraguay 1109 y Rodo"}],"listOrder":"01690-000030","id":4878,"slug":"4878","code":"4878","subcategory":"Piedras","images":["https://goldfarb.blob.core.windows.net/goldfarb/imagenes/4878.jpg"],"documents":[],"description":""},"4882":{"itemCode":"4882","brand":{"name":"Durafilt","slug":"durafilt"},"invoices":199,"finalPrice":205.64,"hasStock":true,"title":"Filtro De Aire Rosca 1/2 Gas P/Compresor 3Hp. Goldex","family":"Herramientas","category":"Accesorios","subCategory":"Filtros","discount":0,"currency":null,"price":0,"tax":22,"unitsPerItem":"PIEZA","unitMult":1,"relatedItems":[],"shops":[{"cardCode":"401005","cardName":"Guglialmelli Oscar S.A.","cardFName":"Armeria Jabali","address2":"Paraguay 1109 y Rodo"}],"listOrder":"00620-000340","id":4882,"slug":"4882","code":"4882","subcategory":"Filtros","images":["https://goldfarb.blob.core.windows.net/goldfarb/imagenes/4882.jpg"],"documents":[],"description":""},"4932":{"itemCode":"4932","brand":{"name":"Chino","slug":"chino"},"invoices":90,"finalPrice":151,"hasStock":true,"title":"Pitones Cerrados Nº4 Hierro Cromado","family":"Herramientas","category":"Ferretería","subCategory":"Pitones","discount":0,"currency":null,"price":0,"tax":22,"unitsPerItem":"GR","unitMult":1,"relatedItems":["4944","4945","4946","4947","4948"],"shops":[{"cardCode":"401005","cardName":"Guglialmelli Oscar S.A.","cardFName":"Armeria Jabali","address2":"Paraguay 1109 y Rodo"}],"listOrder":"01780-000150","id":4932,"slug":"4932","code":"4932","subcategory":"Pitones","images":["https://goldfarb.blob.core.windows.net/goldfarb/imagenes/4932.jpg"],"documents":[],"description":""},"4933":{"itemCode":"4933","brand":{"name":"Chino","slug":"chino"},"invoices":115,"finalPrice":81.7,"hasStock":true,"title":"Pitones Cerrados Nº1 Hierro Cromado","family":"Herramientas","category":"Ferretería","subCategory":"Pitones","discount":0,"currency":null,"price":0,"tax":22,"unitsPerItem":"GR","unitMult":1,"relatedItems":["4944","4945","4946","4947","4948"],"shops":[{"cardCode":"401005","cardName":"Guglialmelli Oscar S.A.","cardFName":"Armeria Jabali","address2":"Paraguay 1109 y Rodo"}],"listOrder":"01780-000120","id":4933,"slug":"4933","code":"4933","subcategory":"Pitones","images":["https://goldfarb.blob.core.windows.net/goldfarb/imagenes/4933.jpg"],"documents":[],"description":""},"4934":{"itemCode":"4934","brand":{"name":"Chino","slug":"chino"},"invoices":87,"finalPrice":93.8,"hasStock":true,"title":"Pitones Cerrados Nº2 Hierro Cromado","family":"Herramientas","category":"Ferretería","subCategory":"Pitones","discount":0,"currency":null,"price":0,"tax":22,"unitsPerItem":"GR","unitMult":1,"relatedItems":["4944","4945","4946","4947","4948"],"shops":[{"cardCode":"401005","cardName":"Guglialmelli Oscar S.A.","cardFName":"Armeria Jabali","address2":"Paraguay 1109 y Rodo"}],"listOrder":"01780-000130","id":4934,"slug":"4934","code":"4934","subcategory":"Pitones","images":["https://goldfarb.blob.core.windows.net/goldfarb/imagenes/4934.jpg"],"documents":[],"description":""},"4935":{"itemCode":"4935","brand":{"name":"Chino","slug":"chino"},"invoices":157,"finalPrice":117,"hasStock":true,"title":"Pitones Cerrados Nº3 Hierro Cromado","family":"Herramientas","category":"Ferretería","subCategory":"Pitones","discount":0,"currency":null,"price":0,"tax":22,"unitsPerItem":"GR","unitMult":1,"relatedItems":["4944","4945","4946","4947","4948"],"shops":[{"cardCode":"401005","cardName":"Guglialmelli Oscar S.A.","cardFName":"Armeria Jabali","address2":"Paraguay 1109 y Rodo"}],"listOrder":"01780-000140","id":4935,"slug":"4935","code":"4935","subcategory":"Pitones","images":["https://goldfarb.blob.core.windows.net/goldfarb/imagenes/4935.jpg"],"documents":[],"description":""},"4936":{"itemCode":"4936","brand":{"name":"Chino","slug":"chino"},"invoices":89,"finalPrice":184,"hasStock":true,"title":"Pitones Cerrados Nº5 Hierro Cromado","family":"Herramientas","category":"Ferretería","subCategory":"Pitones","discount":0,"currency":null,"price":0,"tax":22,"unitsPerItem":"GR","unitMult":1,"relatedItems":["4944","4945","4946","4947","4948"],"shops":[{"cardCode":"401005","cardName":"Guglialmelli Oscar S.A.","cardFName":"Armeria Jabali","address2":"Paraguay 1109 y Rodo"}],"listOrder":"01780-000160","id":4936,"slug":"4936","code":"4936","subcategory":"Pitones","images":["https://goldfarb.blob.core.windows.net/goldfarb/imagenes/4936.jpg"],"documents":[],"description":""},"4937":{"itemCode":"4937","brand":{"name":"Chino","slug":"chino"},"invoices":101,"finalPrice":234,"hasStock":false,"title":"Pitones Cerrados Nº6 Hierro Cromado","family":"Herramientas","category":"Ferretería","subCategory":"Pitones","discount":0,"currency":null,"price":0,"tax":22,"unitsPerItem":"GR","unitMult":1,"relatedItems":["4944","4945","4946","4947","4948"],"shops":[{"cardCode":"401005","cardName":"Guglialmelli Oscar S.A.","cardFName":"Armeria Jabali","address2":"Paraguay 1109 y Rodo"}],"listOrder":"01780-000170","id":4937,"slug":"4937","code":"4937","subcategory":"Pitones","images":["https://goldfarb.blob.core.windows.net/goldfarb/imagenes/4937.jpg"],"documents":[],"description":""},"4938":{"itemCode":"4938","brand":{"name":"Chino","slug":"chino"},"invoices":63,"finalPrice":290,"hasStock":true,"title":"Pitones Cerrados Nº7 Hierro Cromado","family":"Herramientas","category":"Ferretería","subCategory":"Pitones","discount":0,"currency":null,"price":0,"tax":22,"unitsPerItem":"CAJA","unitMult":1,"relatedItems":["4944","4945","4946","4947","4948"],"shops":[{"cardCode":"401005","cardName":"Guglialmelli Oscar S.A.","cardFName":"Armeria Jabali","address2":"Paraguay 1109 y Rodo"}],"listOrder":"01780-000180","id":4938,"slug":"4938","code":"4938","subcategory":"Pitones","images":["https://goldfarb.blob.core.windows.net/goldfarb/imagenes/4938.jpg"],"documents":[],"description":""},"4939":{"itemCode":"4939","brand":{"name":"Chino","slug":"chino"},"invoices":112,"finalPrice":384,"hasStock":false,"title":"Pitones Cerrados Nº8 Hierro Cromado","family":"Herramientas","category":"Ferretería","subCategory":"Pitones","discount":0,"currency":null,"price":0,"tax":22,"unitsPerItem":"CAJA","unitMult":1,"relatedItems":["4944","4945","4946","4947","4948"],"shops":[{"cardCode":"401005","cardName":"Guglialmelli Oscar S.A.","cardFName":"Armeria Jabali","address2":"Paraguay 1109 y Rodo"}],"listOrder":"01780-000190","id":4939,"slug":"4939","code":"4939","subcategory":"Pitones","images":["https://goldfarb.blob.core.windows.net/goldfarb/imagenes/4939.jpg"],"documents":[],"description":""},"4941":{"itemCode":"4941","brand":{"name":"Chino","slug":"chino"},"invoices":43,"finalPrice":582,"hasStock":false,"title":"Pitones Cerrados Nº10 Hierro Cromado","family":"Herramientas","category":"Ferretería","subCategory":"Pitones","discount":0,"currency":null,"price":0,"tax":22,"unitsPerItem":"GR","unitMult":1,"relatedItems":["4944","4945","4946","4947","4948"],"shops":[{"cardCode":"401005","cardName":"Guglialmelli Oscar S.A.","cardFName":"Armeria Jabali","address2":"Paraguay 1109 y Rodo"}],"listOrder":"01780-000200","id":4941,"slug":"4941","code":"4941","subcategory":"Pitones","images":["https://goldfarb.blob.core.windows.net/goldfarb/imagenes/4941.jpg"],"documents":[],"description":""},"4942":{"itemCode":"4942","brand":{"name":"Chino","slug":"chino"},"invoices":44,"finalPrice":809,"hasStock":false,"title":"Pitones Cerrados Nº12 Hierro Cromado","family":"Herramientas","category":"Ferretería","subCategory":"Pitones","discount":0,"currency":null,"price":0,"tax":22,"unitsPerItem":"GR","unitMult":1,"relatedItems":["4944","4945","4946","4947","4948"],"shops":[{"cardCode":"401005","cardName":"Guglialmelli Oscar S.A.","cardFName":"Armeria Jabali","address2":"Paraguay 1109 y Rodo"}],"listOrder":"01780-000210","id":4942,"slug":"4942","code":"4942","subcategory":"Pitones","images":["https://goldfarb.blob.core.windows.net/goldfarb/imagenes/4942.jpg"],"documents":[],"description":""},"4944":{"itemCode":"4944","brand":{"name":"Chino","slug":"chino"},"invoices":244,"finalPrice":209,"hasStock":false,"title":"Pitones Abiertos Nº2 Hierro Cromado","family":"Herramientas","category":"Ferretería","subCategory":"Pitones","discount":0,"currency":null,"price":0,"tax":22,"unitsPerItem":"GR","unitMult":1,"relatedItems":["4945","4946","4947","4948","4949"],"shops":[{"cardCode":"401005","cardName":"Guglialmelli Oscar S.A.","cardFName":"Armeria Jabali","address2":"Paraguay 1109 y Rodo"}],"listOrder":"01780-000030","id":4944,"slug":"4944","code":"4944","subcategory":"Pitones","images":["https://goldfarb.blob.core.windows.net/goldfarb/imagenes/4944.jpg"],"documents":[],"description":""},"4945":{"itemCode":"4945","brand":{"name":"Chino","slug":"chino"},"invoices":144,"finalPrice":234,"hasStock":true,"title":"Pitones Abiertos Nº3 Hierro Cromado","family":"Herramientas","category":"Ferretería","subCategory":"Pitones","discount":0,"currency":null,"price":0,"tax":22,"unitsPerItem":"GR","unitMult":1,"relatedItems":["4944","4946","4947","4948","4949"],"shops":[{"cardCode":"401005","cardName":"Guglialmelli Oscar S.A.","cardFName":"Armeria Jabali","address2":"Paraguay 1109 y Rodo"}],"listOrder":"01780-000040","id":4945,"slug":"4945","code":"4945","subcategory":"Pitones","images":["https://goldfarb.blob.core.windows.net/goldfarb/imagenes/4945.jpg"],"documents":[],"description":""},"4946":{"itemCode":"4946","brand":{"name":"Chino","slug":"chino"},"invoices":158,"finalPrice":354,"hasStock":true,"title":"Pitones Abiertos Nº5 Hierro Cromado","family":"Herramientas","category":"Ferretería","subCategory":"Pitones","discount":0,"currency":null,"price":0,"tax":22,"unitsPerItem":"GR","unitMult":1,"relatedItems":["4944","4945","4947","4948","4949"],"shops":[{"cardCode":"401005","cardName":"Guglialmelli Oscar S.A.","cardFName":"Armeria Jabali","address2":"Paraguay 1109 y Rodo"}],"listOrder":"01780-000050","id":4946,"slug":"4946","code":"4946","subcategory":"Pitones","images":["https://goldfarb.blob.core.windows.net/goldfarb/imagenes/4946.jpg"],"documents":[],"description":""},"4947":{"itemCode":"4947","brand":{"name":"Chino","slug":"chino"},"invoices":174,"finalPrice":430,"hasStock":true,"title":"Pitones Abiertos Nº6 Hierro Cromado","family":"Herramientas","category":"Ferretería","subCategory":"Pitones","discount":0,"currency":null,"price":0,"tax":22,"unitsPerItem":"GR","unitMult":1,"relatedItems":["4944","4945","4946","4948","4949"],"shops":[{"cardCode":"401005","cardName":"Guglialmelli Oscar S.A.","cardFName":"Armeria Jabali","address2":"Paraguay 1109 y Rodo"}],"listOrder":"01780-000060","id":4947,"slug":"4947","code":"4947","subcategory":"Pitones","images":["https://goldfarb.blob.core.windows.net/goldfarb/imagenes/4947.jpg"],"documents":[],"description":""},"4948":{"itemCode":"4948","brand":{"name":"Chino","slug":"chino"},"invoices":92,"finalPrice":609,"hasStock":false,"title":"Pitones Abiertos Nº8 Hierro Cromado","family":"Herramientas","category":"Ferretería","subCategory":"Pitones","discount":0,"currency":null,"price":0,"tax":22,"unitsPerItem":"GR","unitMult":1,"relatedItems":["4944","4945","4946","4947","4949"],"shops":[{"cardCode":"401005","cardName":"Guglialmelli Oscar S.A.","cardFName":"Armeria Jabali","address2":"Paraguay 1109 y Rodo"}],"listOrder":"01780-000070","id":4948,"slug":"4948","code":"4948","subcategory":"Pitones","images":["https://goldfarb.blob.core.windows.net/goldfarb/imagenes/4948.jpg"],"documents":[],"description":""},"4949":{"itemCode":"4949","brand":{"name":"Chino","slug":"chino"},"invoices":123,"finalPrice":866,"hasStock":false,"title":"Pitones Abiertos Nº10 Hierro Cromado","family":"Herramientas","category":"Ferretería","subCategory":"Pitones","discount":0,"currency":null,"price":0,"tax":22,"unitsPerItem":"CAJA","unitMult":1,"relatedItems":["4944","4945","4946","4947","4948"],"shops":[{"cardCode":"401005","cardName":"Guglialmelli Oscar S.A.","cardFName":"Armeria Jabali","address2":"Paraguay 1109 y Rodo"}],"listOrder":"01780-000080","id":4949,"slug":"4949","code":"4949","subcategory":"Pitones","images":["https://goldfarb.blob.core.windows.net/goldfarb/imagenes/4949.jpg"],"documents":[],"description":""},"4950":{"itemCode":"4950","brand":{"name":"Chino","slug":"chino"},"invoices":39,"finalPrice":1254,"hasStock":false,"title":"Pitones Abiertos Nº12 Hierro Cromado","family":"Herramientas","category":"Ferretería","subCategory":"Pitones","discount":0,"currency":null,"price":0,"tax":22,"unitsPerItem":"GR","unitMult":1,"relatedItems":["4944","4945","4946","4947","4948"],"shops":[{"cardCode":"401005","cardName":"Guglialmelli Oscar S.A.","cardFName":"Armeria Jabali","address2":"Paraguay 1109 y Rodo"}],"listOrder":"01780-000090","id":4950,"slug":"4950","code":"4950","subcategory":"Pitones","images":["https://goldfarb.blob.core.windows.net/goldfarb/imagenes/4950.jpg"],"documents":[],"description":""},"4951":{"itemCode":"4951","brand":{"name":"Chino","slug":"chino"},"invoices":46,"finalPrice":1892,"hasStock":true,"title":"Pitones Abiertos Nº14 Hierro Cromado","family":"Herramientas","category":"Ferretería","subCategory":"Pitones","discount":0,"currency":null,"price":0,"tax":22,"unitsPerItem":"GR","unitMult":0.5,"relatedItems":["4944","4945","4946","4947","4948"],"shops":[{"cardCode":"401005","cardName":"Guglialmelli Oscar S.A.","cardFName":"Armeria Jabali","address2":"Paraguay 1109 y Rodo"}],"listOrder":"01780-000100","id":4951,"slug":"4951","code":"4951","subcategory":"Pitones","images":["https://goldfarb.blob.core.windows.net/goldfarb/imagenes/4951.jpg"],"documents":[],"description":""},"4977":{"itemCode":"4977","brand":{"name":"Tramontina","slug":"tramontina"},"invoices":1185,"finalPrice":201,"hasStock":true,"title":"Plomada Albañil Tramontina 43180/001-4899/01","family":"Herramientas","category":"Herramientas Manuales","subCategory":"Plomadas","discount":0,"currency":null,"price":0,"tax":22,"unitsPerItem":"PIEZA","unitMult":1,"relatedItems":["15396"],"shops":[{"cardCode":"401005","cardName":"Guglialmelli Oscar S.A.","cardFName":"Armeria Jabali","address2":"Paraguay 1109 y Rodo"}],"listOrder":"01790-000040","id":4977,"slug":"4977","code":"4977","subcategory":"Plomadas","images":["https://goldfarb.blob.core.windows.net/goldfarb/imagenes/4977.jpg"],"documents":[],"description":""},"4987":{"itemCode":"4987","brand":{"name":"Pacetta","slug":"pacetta"},"invoices":32,"finalPrice":280,"hasStock":true,"title":"Puntas 10''  2080 Pacetta","family":"Herramientas","category":"Herramientas Manuales","subCategory":"Puntas","discount":0,"currency":null,"price":0,"tax":22,"unitsPerItem":"PIEZA","unitMult":1,"relatedItems":["4988","2487"],"shops":[{"cardCode":"401005","cardName":"Guglialmelli Oscar S.A.","cardFName":"Armeria Jabali","address2":"Paraguay 1109 y Rodo"}],"listOrder":"00490-000160","id":4987,"slug":"4987","code":"4987","subcategory":"Puntas","images":["https://goldfarb.blob.core.windows.net/goldfarb/imagenes/4987.jpg"],"documents":[],"description":""},"4988":{"itemCode":"4988","brand":{"name":"Pacetta","slug":"pacetta"},"invoices":23,"finalPrice":330,"hasStock":true,"title":"Puntas 12''  2080/12 Pacetta","family":"Herramientas","category":"Herramientas Manuales","subCategory":"Puntas","discount":0,"currency":null,"price":0,"tax":22,"unitsPerItem":"PIEZA","unitMult":1,"relatedItems":["4987","2487"],"shops":[{"cardCode":"401005","cardName":"Guglialmelli Oscar S.A.","cardFName":"Armeria Jabali","address2":"Paraguay 1109 y Rodo"}],"listOrder":"00490-000170","id":4988,"slug":"4988","code":"4988","subcategory":"Puntas","images":["https://goldfarb.blob.core.windows.net/goldfarb/imagenes/4988.jpg"],"documents":[],"description":""}}