{"3031":{"itemCode":"3031","brand":{"name":"Mustad","slug":"mustad"},"invoices":79,"finalPrice":0,"hasStock":true,"title":"Herraduras Vareo 0/26 C/Pestaña   Mustad","family":"Herramientas","category":"Prevención y Seguridad","subCategory":"Herraduras","discount":0,"currency":"","price":0,"tax":0,"unitsPerItem":"JUEGO","unitMult":1,"relatedItems":["3452","4270","22009"],"shops":[{"cardCode":"401005","cardName":"Guglialmelli Oscar S.A.","cardFName":"Armeria Jabali","address2":"Paraguay 1109 y Rodo"}],"listOrder":"01050-000310","id":3031,"slug":"3031","code":"3031","subcategory":"Herraduras","images":["https://goldfarb.blob.core.windows.net/goldfarb/imagenes/3031.jpg"],"documents":[],"description":""},"3032":{"itemCode":"3032","brand":{"name":"Mustad","slug":"mustad"},"invoices":176,"finalPrice":0,"hasStock":false,"title":"Herraduras Vareo 1/27 C/Pestaña   Mustad","family":"Herramientas","category":"Prevención y Seguridad","subCategory":"Herraduras","discount":0,"currency":"","price":0,"tax":0,"unitsPerItem":"JUEGO","unitMult":1,"relatedItems":["3452","4270","22009"],"shops":[{"cardCode":"401005","cardName":"Guglialmelli Oscar S.A.","cardFName":"Armeria Jabali","address2":"Paraguay 1109 y Rodo"}],"listOrder":"01050-000330","id":3032,"slug":"3032","code":"3032","subcategory":"Herraduras","images":["https://goldfarb.blob.core.windows.net/goldfarb/imagenes/3032.jpg"],"documents":[],"description":""},"3033":{"itemCode":"3033","brand":{"name":"Mustad","slug":"mustad"},"invoices":300,"finalPrice":0,"hasStock":false,"title":"Herraduras Vareo 2/28 C/Pestaña   Mustad","family":"Herramientas","category":"Prevención y Seguridad","subCategory":"Herraduras","discount":0,"currency":"","price":0,"tax":0,"unitsPerItem":"JUEGO","unitMult":1,"relatedItems":["3452","4270","22009"],"shops":[{"cardCode":"401005","cardName":"Guglialmelli Oscar S.A.","cardFName":"Armeria Jabali","address2":"Paraguay 1109 y Rodo"}],"listOrder":"01050-000350","id":3033,"slug":"3033","code":"3033","subcategory":"Herraduras","images":["https://goldfarb.blob.core.windows.net/goldfarb/imagenes/3033.jpg"],"documents":["https://goldfarb.blob.core.windows.net/goldfarb/documentos/3033.pdf"],"description":""},"3034":{"itemCode":"3034","brand":{"name":"Mustad","slug":"mustad"},"invoices":267,"finalPrice":0,"hasStock":false,"title":"Herraduras Vareo 3/29 C/Pestaña   Mustad","family":"Herramientas","category":"Prevención y Seguridad","subCategory":"Herraduras","discount":0,"currency":"","price":0,"tax":0,"unitsPerItem":"JUEGO","unitMult":1,"relatedItems":["3452","4270","22009"],"shops":[{"cardCode":"401005","cardName":"Guglialmelli Oscar S.A.","cardFName":"Armeria Jabali","address2":"Paraguay 1109 y Rodo"}],"listOrder":"01050-000370","id":3034,"slug":"3034","code":"3034","subcategory":"Herraduras","images":["https://goldfarb.blob.core.windows.net/goldfarb/imagenes/3034.jpg"],"documents":["https://goldfarb.blob.core.windows.net/goldfarb/documentos/3034.pdf"],"description":""},"3035":{"itemCode":"3035","brand":{"name":"Mustad","slug":"mustad"},"invoices":155,"finalPrice":0,"hasStock":true,"title":"Herraduras Vareo 4/30 C/Pestaña   Mustad","family":"Herramientas","category":"Prevención y Seguridad","subCategory":"Herraduras","discount":0,"currency":"","price":0,"tax":0,"unitsPerItem":"JUEGO","unitMult":1,"relatedItems":["3452","4270","22009"],"shops":[{"cardCode":"401005","cardName":"Guglialmelli Oscar S.A.","cardFName":"Armeria Jabali","address2":"Paraguay 1109 y Rodo"}],"listOrder":"01050-000390","id":3035,"slug":"3035","code":"3035","subcategory":"Herraduras","images":["https://goldfarb.blob.core.windows.net/goldfarb/imagenes/3035.jpg"],"documents":[],"description":""},"3036":{"itemCode":"3036","brand":{"name":"Mustad","slug":"mustad"},"invoices":135,"finalPrice":0,"hasStock":false,"title":"Herraduras Vareo 0/26 S/Pestaña   Mustad","family":"Herramientas","category":"Prevención y Seguridad","subCategory":"Herraduras","discount":0,"currency":"","price":0,"tax":0,"unitsPerItem":"JUEGO","unitMult":1,"relatedItems":["3452","4270","22009"],"shops":[{"cardCode":"401005","cardName":"Guglialmelli Oscar S.A.","cardFName":"Armeria Jabali","address2":"Paraguay 1109 y Rodo"}],"listOrder":"01050-000300","id":3036,"slug":"3036","code":"3036","subcategory":"Herraduras","images":["https://goldfarb.blob.core.windows.net/goldfarb/imagenes/3036.jpg"],"documents":[],"description":""},"3037":{"itemCode":"3037","brand":{"name":"Mustad","slug":"mustad"},"invoices":267,"finalPrice":0,"hasStock":false,"title":"Herraduras Vareo 1/27 S/Pestaña   Mustad","family":"Herramientas","category":"Prevención y Seguridad","subCategory":"Herraduras","discount":0,"currency":"","price":0,"tax":0,"unitsPerItem":"JUEGO","unitMult":1,"relatedItems":["3452","4270","22009"],"shops":[{"cardCode":"401005","cardName":"Guglialmelli Oscar S.A.","cardFName":"Armeria Jabali","address2":"Paraguay 1109 y Rodo"}],"listOrder":"01050-000320","id":3037,"slug":"3037","code":"3037","subcategory":"Herraduras","images":["https://goldfarb.blob.core.windows.net/goldfarb/imagenes/3037.jpg"],"documents":[],"description":""},"3038":{"itemCode":"3038","brand":{"name":"Mustad","slug":"mustad"},"invoices":475,"finalPrice":0,"hasStock":false,"title":"Herraduras Vareo 2/28 S/Pestaña   Mustad","family":"Herramientas","category":"Prevención y Seguridad","subCategory":"Herraduras","discount":0,"currency":"","price":0,"tax":0,"unitsPerItem":"JUEGO","unitMult":1,"relatedItems":["3452","4270","22009"],"shops":[{"cardCode":"401005","cardName":"Guglialmelli Oscar S.A.","cardFName":"Armeria Jabali","address2":"Paraguay 1109 y Rodo"}],"listOrder":"01050-000340","id":3038,"slug":"3038","code":"3038","subcategory":"Herraduras","images":["https://goldfarb.blob.core.windows.net/goldfarb/imagenes/3038.jpg"],"documents":[],"description":""},"3039":{"itemCode":"3039","brand":{"name":"Mustad","slug":"mustad"},"invoices":498,"finalPrice":0,"hasStock":false,"title":"Herraduras Vareo 3/29 S/Pestaña   Mustad","family":"Herramientas","category":"Prevención y Seguridad","subCategory":"Herraduras","discount":0,"currency":"","price":0,"tax":0,"unitsPerItem":"JUEGO","unitMult":1,"relatedItems":["3452","4270","22009"],"shops":[{"cardCode":"401005","cardName":"Guglialmelli Oscar S.A.","cardFName":"Armeria Jabali","address2":"Paraguay 1109 y Rodo"}],"listOrder":"01050-000360","id":3039,"slug":"3039","code":"3039","subcategory":"Herraduras","images":["https://goldfarb.blob.core.windows.net/goldfarb/imagenes/3039.jpg"],"documents":[],"description":""},"3040":{"itemCode":"3040","brand":{"name":"Mustad","slug":"mustad"},"invoices":285,"finalPrice":0,"hasStock":true,"title":"Herraduras Vareo 4/30 S/Pestaña   Mustad","family":"Herramientas","category":"Prevención y Seguridad","subCategory":"Herraduras","discount":0,"currency":"","price":0,"tax":0,"unitsPerItem":"JUEGO","unitMult":1,"relatedItems":["3452","4270","22009"],"shops":[{"cardCode":"401005","cardName":"Guglialmelli Oscar S.A.","cardFName":"Armeria Jabali","address2":"Paraguay 1109 y Rodo"}],"listOrder":"01050-000380","id":3040,"slug":"3040","code":"3040","subcategory":"Herraduras","images":["https://goldfarb.blob.core.windows.net/goldfarb/imagenes/3040.jpg"],"documents":["https://goldfarb.blob.core.windows.net/goldfarb/documentos/3040.pdf"],"description":""},"3049":{"itemCode":"3049","brand":{"name":"Mustad","slug":"mustad"},"invoices":25,"finalPrice":0,"hasStock":true,"title":"Herraduras Charrua Nº 6 S/Pestaña Mustad","family":"Herramientas","category":"Prevención y Seguridad","subCategory":"Herraduras","discount":0,"currency":"","price":0,"tax":0,"unitsPerItem":"JUEGO","unitMult":1,"relatedItems":["3452","4270","22009"],"shops":[{"cardCode":"401005","cardName":"Guglialmelli Oscar S.A.","cardFName":"Armeria Jabali","address2":"Paraguay 1109 y Rodo"}],"listOrder":"01050-000240","id":3049,"slug":"3049","code":"3049","subcategory":"Herraduras","images":["https://goldfarb.blob.core.windows.net/goldfarb/imagenes/3049.jpg"],"documents":[],"description":""},"3051":{"itemCode":"3051","brand":{"name":"Goldex","slug":"goldex"},"invoices":165,"finalPrice":0,"hasStock":true,"title":"Gafas Para Soldar Goldex","family":"Herramientas","category":"Prevención y Seguridad","subCategory":"Gafas","discount":0,"currency":"","price":0,"tax":22,"unitsPerItem":"PIEZA","unitMult":1,"relatedItems":["3452","4270","22009"],"shops":[{"cardCode":"401005","cardName":"Guglialmelli Oscar S.A.","cardFName":"Armeria Jabali","address2":"Paraguay 1109 y Rodo"}],"listOrder":"01890-000190","id":3051,"slug":"3051","code":"3051","subcategory":"Gafas","images":["https://goldfarb.blob.core.windows.net/goldfarb/imagenes/3051.jpg"],"documents":["https://goldfarb.blob.core.windows.net/goldfarb/documentos/3051.pdf"],"description":""},"3072":{"itemCode":"3072","brand":{"name":"Rapid","slug":"rapid"},"invoices":10,"finalPrice":0,"hasStock":true,"title":"Grapas 28/9 Con 2000 Unidades P.Mod.28","family":"Herramientas","category":"Ferretería","subCategory":"Grapas","discount":0,"currency":"","price":0,"tax":22,"unitsPerItem":"CAJA","unitMult":1,"relatedItems":["3452","4270","22009"],"shops":[{"cardCode":"401005","cardName":"Guglialmelli Oscar S.A.","cardFName":"Armeria Jabali","address2":"Paraguay 1109 y Rodo"}],"listOrder":"00990-000270","id":3072,"slug":"3072","code":"3072","subcategory":"Grapas","images":["https://goldfarb.blob.core.windows.net/goldfarb/imagenes/3072.jpg"],"documents":[],"description":""},"3073":{"itemCode":"3073","brand":{"name":"Rapid","slug":"rapid"},"invoices":13,"finalPrice":0,"hasStock":true,"title":"Grapas 28/11 Con 2000 Unidades P.Mod.28","family":"Herramientas","category":"Ferretería","subCategory":"Grapas","discount":0,"currency":"","price":0,"tax":22,"unitsPerItem":"CAJA","unitMult":1,"relatedItems":["3452","4270","22009"],"shops":[{"cardCode":"401005","cardName":"Guglialmelli Oscar S.A.","cardFName":"Armeria Jabali","address2":"Paraguay 1109 y Rodo"}],"listOrder":"00990-000290","id":3073,"slug":"3073","code":"3073","subcategory":"Grapas","images":["https://goldfarb.blob.core.windows.net/goldfarb/imagenes/3073.jpg"],"documents":[],"description":""},"3079":{"itemCode":"3079","brand":{"name":"Rapid","slug":"rapid"},"invoices":14,"finalPrice":0,"hasStock":true,"title":"Grapas 53/20 Con 1250 Unidades P.Mod.53","family":"Herramientas","category":"Ferretería","subCategory":"Grapas","discount":0,"currency":"","price":0,"tax":22,"unitsPerItem":"CAJA","unitMult":1,"relatedItems":["3452","4270","22009"],"shops":[{"cardCode":"401005","cardName":"Guglialmelli Oscar S.A.","cardFName":"Armeria Jabali","address2":"Paraguay 1109 y Rodo"}],"listOrder":"00990-000250","id":3079,"slug":"3079","code":"3079","subcategory":"Grapas","images":["https://goldfarb.blob.core.windows.net/goldfarb/imagenes/3079.jpg"],"documents":[],"description":""},"3086":{"itemCode":"3086","brand":{"name":"Rapid","slug":"rapid"},"invoices":13,"finalPrice":0,"hasStock":true,"title":"Clavos Grap.Ele 20mm 1000Pz.","family":"Herramientas","category":"Ferretería","subCategory":"Clavos","discount":0,"currency":"","price":0,"tax":22,"unitsPerItem":"CAJA","unitMult":1,"relatedItems":["3452","4270","22009"],"shops":[{"cardCode":"401005","cardName":"Guglialmelli Oscar S.A.","cardFName":"Armeria Jabali","address2":"Paraguay 1109 y Rodo"}],"listOrder":"00990-000370","id":3086,"slug":"3086","code":"3086","subcategory":"Clavos","images":["https://goldfarb.blob.core.windows.net/goldfarb/imagenes/3086.jpg"],"documents":[],"description":"CANTIDAD X CAJITA (ROJA) 880 UNI"},"3121":{"itemCode":"3121","brand":{"name":"Mustad","slug":"mustad"},"invoices":288,"finalPrice":0,"hasStock":false,"title":"Herraduras Palermo 0/26 S/Pestaña Mustad","family":"Herramientas","category":"Prevención y Seguridad","subCategory":"Herraduras","discount":0,"currency":"","price":0,"tax":0,"unitsPerItem":"JUEGO","unitMult":1,"relatedItems":["3452","4270","22009"],"shops":[{"cardCode":"401005","cardName":"Guglialmelli Oscar S.A.","cardFName":"Armeria Jabali","address2":"Paraguay 1109 y Rodo"}],"listOrder":"01050-000250","id":3121,"slug":"3121","code":"3121","subcategory":"Herraduras","images":["https://goldfarb.blob.core.windows.net/goldfarb/imagenes/3121.jpg"],"documents":[],"description":""},"3122":{"itemCode":"3122","brand":{"name":"Mustad","slug":"mustad"},"invoices":432,"finalPrice":0,"hasStock":false,"title":"Herraduras Palermo 1/27 S/Pestaña Mustad","family":"Herramientas","category":"Prevención y Seguridad","subCategory":"Herraduras","discount":0,"currency":"","price":0,"tax":0,"unitsPerItem":"JUEGO","unitMult":1,"relatedItems":["3452","4270","22009"],"shops":[{"cardCode":"401005","cardName":"Guglialmelli Oscar S.A.","cardFName":"Armeria Jabali","address2":"Paraguay 1109 y Rodo"}],"listOrder":"01050-000260","id":3122,"slug":"3122","code":"3122","subcategory":"Herraduras","images":["https://goldfarb.blob.core.windows.net/goldfarb/imagenes/3122.jpg"],"documents":[],"description":""},"3124":{"itemCode":"3124","brand":{"name":"Mustad","slug":"mustad"},"invoices":675,"finalPrice":0,"hasStock":true,"title":"Herraduras Palermo 2/28 S/Pestaña Mustad","family":"Herramientas","category":"Prevención y Seguridad","subCategory":"Herraduras","discount":0,"currency":"","price":0,"tax":0,"unitsPerItem":"JUEGO","unitMult":1,"relatedItems":["3452","4270","22009"],"shops":[{"cardCode":"401005","cardName":"Guglialmelli Oscar S.A.","cardFName":"Armeria Jabali","address2":"Paraguay 1109 y Rodo"}],"listOrder":"01050-000270","id":3124,"slug":"3124","code":"3124","subcategory":"Herraduras","images":["https://goldfarb.blob.core.windows.net/goldfarb/imagenes/3124.jpg"],"documents":["https://goldfarb.blob.core.windows.net/goldfarb/documentos/3124.pdf"],"description":""},"3125":{"itemCode":"3125","brand":{"name":"Mustad","slug":"mustad"},"invoices":574,"finalPrice":0,"hasStock":true,"title":"Herraduras Palermo 3/29 S/Pestaña Mustad","family":"Herramientas","category":"Prevención y Seguridad","subCategory":"Herraduras","discount":0,"currency":"","price":0,"tax":0,"unitsPerItem":"JUEGO","unitMult":1,"relatedItems":["3452","4270","22009"],"shops":[{"cardCode":"401005","cardName":"Guglialmelli Oscar S.A.","cardFName":"Armeria Jabali","address2":"Paraguay 1109 y Rodo"}],"listOrder":"01050-000280","id":3125,"slug":"3125","code":"3125","subcategory":"Herraduras","images":["https://goldfarb.blob.core.windows.net/goldfarb/imagenes/3125.jpg"],"documents":[],"description":""},"3126":{"itemCode":"3126","brand":{"name":"Mustad","slug":"mustad"},"invoices":302,"finalPrice":0,"hasStock":false,"title":"Herraduras Palermo 4/30 S/Pestaña Mustad","family":"Herramientas","category":"Prevención y Seguridad","subCategory":"Herraduras","discount":0,"currency":"","price":0,"tax":0,"unitsPerItem":"JUEGO","unitMult":1,"relatedItems":["3452","4270","22009"],"shops":[{"cardCode":"401005","cardName":"Guglialmelli Oscar S.A.","cardFName":"Armeria Jabali","address2":"Paraguay 1109 y Rodo"}],"listOrder":"01050-000290","id":3126,"slug":"3126","code":"3126","subcategory":"Herraduras","images":["https://goldfarb.blob.core.windows.net/goldfarb/imagenes/3126.jpg"],"documents":["https://goldfarb.blob.core.windows.net/goldfarb/documentos/3126.pdf"],"description":""},"3168":{"itemCode":"3168","brand":{"name":"Cortmad","slug":"cortmad"},"invoices":248,"finalPrice":0,"hasStock":true,"title":"Hoja Montaraz 46cm Diente Alternado C/Tronzador P/Mad.Verde Cortmad","family":"Herramientas","category":"Accesorios","subCategory":"Hojas","discount":0,"currency":"","price":0,"tax":22,"unitsPerItem":"PIEZA","unitMult":1,"relatedItems":["3452","4270","22009"],"shops":[{"cardCode":"401005","cardName":"Guglialmelli Oscar S.A.","cardFName":"Armeria Jabali","address2":"Paraguay 1109 y Rodo"}],"listOrder":"01140-000090","id":3168,"slug":"3168","code":"3168","subcategory":"Hojas","images":["https://goldfarb.blob.core.windows.net/goldfarb/imagenes/3168.jpg"],"documents":[],"description":""},"3169":{"itemCode":"3169","brand":{"name":"Cortmad","slug":"cortmad"},"invoices":371,"finalPrice":0,"hasStock":true,"title":"Hoja Montaraz 53cm Diente Alternado C/Tronzador P/Mad.Verde Cortmad","family":"Herramientas","category":"Accesorios","subCategory":"Hojas","discount":0,"currency":"","price":0,"tax":22,"unitsPerItem":"PIEZA","unitMult":1,"relatedItems":["3452","4270","22009"],"shops":[{"cardCode":"401005","cardName":"Guglialmelli Oscar S.A.","cardFName":"Armeria Jabali","address2":"Paraguay 1109 y Rodo"}],"listOrder":"01140-000100","id":3169,"slug":"3169","code":"3169","subcategory":"Hojas","images":["https://goldfarb.blob.core.windows.net/goldfarb/imagenes/3169.jpg"],"documents":[],"description":""},"3170":{"itemCode":"3170","brand":{"name":"Cortmad","slug":"cortmad"},"invoices":413,"finalPrice":0,"hasStock":true,"title":"Hoja Montaraz 61cm Diente Alternado C/Tronzador P/Mad.Verde Cortmad","family":"Herramientas","category":"Accesorios","subCategory":"Hojas","discount":0,"currency":"","price":0,"tax":22,"unitsPerItem":"PIEZA","unitMult":1,"relatedItems":["3452","4270","22009"],"shops":[{"cardCode":"401005","cardName":"Guglialmelli Oscar S.A.","cardFName":"Armeria Jabali","address2":"Paraguay 1109 y Rodo"}],"listOrder":"01140-000110","id":3170,"slug":"3170","code":"3170","subcategory":"Hojas","images":["https://goldfarb.blob.core.windows.net/goldfarb/imagenes/3170.jpg"],"documents":[],"description":""},"3171":{"itemCode":"3171","brand":{"name":"Cortmad","slug":"cortmad"},"invoices":319,"finalPrice":0,"hasStock":true,"title":"Hoja Montaraz 76cm Diente Alternado C/Tronzador P/Mad.Verde Cortmad","family":"Herramientas","category":"Accesorios","subCategory":"Hojas","discount":0,"currency":"","price":0,"tax":22,"unitsPerItem":"PIEZA","unitMult":1,"relatedItems":["3452","4270","22009"],"shops":[{"cardCode":"401005","cardName":"Guglialmelli Oscar S.A.","cardFName":"Armeria Jabali","address2":"Paraguay 1109 y Rodo"}],"listOrder":"01140-000120","id":3171,"slug":"3171","code":"3171","subcategory":"Hojas","images":["https://goldfarb.blob.core.windows.net/goldfarb/imagenes/3171.jpg"],"documents":[],"description":""},"3172":{"itemCode":"3172","brand":{"name":"Cortmad","slug":"cortmad"},"invoices":147,"finalPrice":0,"hasStock":true,"title":"Hoja Montaraz 91cm Diente Alternado C/Tronzador P/Mad.Verde Cortmad","family":"Herramientas","category":"Accesorios","subCategory":"Hojas","discount":0,"currency":"","price":0,"tax":22,"unitsPerItem":"PIEZA","unitMult":1,"relatedItems":["3452","4270","22009"],"shops":[{"cardCode":"401005","cardName":"Guglialmelli Oscar S.A.","cardFName":"Armeria Jabali","address2":"Paraguay 1109 y Rodo"}],"listOrder":"01140-000130","id":3172,"slug":"3172","code":"3172","subcategory":"Hojas","images":["https://goldfarb.blob.core.windows.net/goldfarb/imagenes/3172.jpg"],"documents":[],"description":""},"3174":{"itemCode":"3174","brand":{"name":"Tramontina","slug":"tramontina"},"invoices":212,"finalPrice":0,"hasStock":true,"title":"Hacha De Mano 700gr Tramontina 40562/002-4308/2","family":"Herramientas","category":"Herramientas Manuales","subCategory":"Hachas","discount":0,"currency":"","price":0,"tax":22,"unitsPerItem":"PIEZA","unitMult":1,"relatedItems":["3452","4270","22009"],"shops":[{"cardCode":"401005","cardName":"Guglialmelli Oscar S.A.","cardFName":"Armeria Jabali","address2":"Paraguay 1109 y Rodo"}],"listOrder":"01040-000060","id":3174,"slug":"3174","code":"3174","subcategory":"Hachas","images":["https://goldfarb.blob.core.windows.net/goldfarb/imagenes/3174.jpg"],"documents":["https://goldfarb.blob.core.windows.net/goldfarb/documentos/3174.pdf"],"description":""},"3176":{"itemCode":"3176","brand":{"name":"Cortmad","slug":"cortmad"},"invoices":321,"finalPrice":0,"hasStock":false,"title":"Hoja Montaraz 46cm Diente Corrido P/Mad.Seca Cortmad","family":"Herramientas","category":"Accesorios","subCategory":"Hojas","discount":0,"currency":"","price":0,"tax":22,"unitsPerItem":"PIEZA","unitMult":1,"relatedItems":["3452","4270","22009"],"shops":[{"cardCode":"401005","cardName":"Guglialmelli Oscar S.A.","cardFName":"Armeria Jabali","address2":"Paraguay 1109 y Rodo"}],"listOrder":"01140-000030","id":3176,"slug":"3176","code":"3176","subcategory":"Hojas","images":["https://goldfarb.blob.core.windows.net/goldfarb/imagenes/3176.jpg"],"documents":[],"description":""},"3177":{"itemCode":"3177","brand":{"name":"Cortmad","slug":"cortmad"},"invoices":557,"finalPrice":0,"hasStock":true,"title":"Hoja Montaraz 53cm Diente Corrido P/Mad.Seca Cortmad","family":"Herramientas","category":"Accesorios","subCategory":"Hojas","discount":0,"currency":"","price":0,"tax":22,"unitsPerItem":"PIEZA","unitMult":1,"relatedItems":["3452","4270","22009"],"shops":[{"cardCode":"401005","cardName":"Guglialmelli Oscar S.A.","cardFName":"Armeria Jabali","address2":"Paraguay 1109 y Rodo"}],"listOrder":"01140-000040","id":3177,"slug":"3177","code":"3177","subcategory":"Hojas","images":["https://goldfarb.blob.core.windows.net/goldfarb/imagenes/3177.jpg"],"documents":[],"description":""},"3178":{"itemCode":"3178","brand":{"name":"Cortmad","slug":"cortmad"},"invoices":601,"finalPrice":0,"hasStock":false,"title":"Hoja Montaraz 61cm Diente Corrido P/Mad.Seca Cortmad","family":"Herramientas","category":"Accesorios","subCategory":"Hojas","discount":0,"currency":"","price":0,"tax":22,"unitsPerItem":"PIEZA","unitMult":1,"relatedItems":["3452","4270","22009"],"shops":[{"cardCode":"401005","cardName":"Guglialmelli Oscar S.A.","cardFName":"Armeria Jabali","address2":"Paraguay 1109 y Rodo"}],"listOrder":"01140-000050","id":3178,"slug":"3178","code":"3178","subcategory":"Hojas","images":["https://goldfarb.blob.core.windows.net/goldfarb/imagenes/3178.jpg"],"documents":[],"description":""},"3179":{"itemCode":"3179","brand":{"name":"Cortmad","slug":"cortmad"},"invoices":481,"finalPrice":0,"hasStock":false,"title":"Hoja Montaraz 76cm Diente Corrido P/Mad.Seca Cortmad","family":"Herramientas","category":"Accesorios","subCategory":"Hojas","discount":0,"currency":"","price":0,"tax":22,"unitsPerItem":"PIEZA","unitMult":1,"relatedItems":["3452","4270","22009"],"shops":[{"cardCode":"401005","cardName":"Guglialmelli Oscar S.A.","cardFName":"Armeria Jabali","address2":"Paraguay 1109 y Rodo"}],"listOrder":"01140-000060","id":3179,"slug":"3179","code":"3179","subcategory":"Hojas","images":["https://goldfarb.blob.core.windows.net/goldfarb/imagenes/3179.jpg"],"documents":[],"description":""},"3180":{"itemCode":"3180","brand":{"name":"Cortmad","slug":"cortmad"},"invoices":223,"finalPrice":0,"hasStock":true,"title":"Hoja Montaraz 91cm Diente Corrido P/Mad.Seca Cortmad","family":"Herramientas","category":"Accesorios","subCategory":"Hojas","discount":0,"currency":"","price":0,"tax":22,"unitsPerItem":"PIEZA","unitMult":1,"relatedItems":["3452","4270","22009"],"shops":[{"cardCode":"401005","cardName":"Guglialmelli Oscar S.A.","cardFName":"Armeria Jabali","address2":"Paraguay 1109 y Rodo"}],"listOrder":"01140-000070","id":3180,"slug":"3180","code":"3180","subcategory":"Hojas","images":["https://goldfarb.blob.core.windows.net/goldfarb/imagenes/3180.jpg"],"documents":[],"description":""},"3193":{"itemCode":"3193","brand":{"name":"Tramontina","slug":"tramontina"},"invoices":851,"finalPrice":0,"hasStock":true,"title":"Hachuela Albañil Tramontina 40458/000-4250","family":"Herramientas","category":"Herramientas Manuales","subCategory":"Hachas","discount":0,"currency":"","price":0,"tax":22,"unitsPerItem":"PIEZA","unitMult":1,"relatedItems":["3452","4270","22009"],"shops":[{"cardCode":"401005","cardName":"Guglialmelli Oscar S.A.","cardFName":"Armeria Jabali","address2":"Paraguay 1109 y Rodo"}],"listOrder":"01040-000090","id":3193,"slug":"3193","code":"3193","subcategory":"Hachas","images":["https://goldfarb.blob.core.windows.net/goldfarb/imagenes/3193.jpg"],"documents":[],"description":""},"3195":{"itemCode":"3195","brand":{"name":"Mustad","slug":"mustad"},"invoices":90,"finalPrice":0,"hasStock":true,"title":"Herradura Ac.Acanalada Pesada Nº2 Mustad","family":"Herramientas","category":"Prevención y Seguridad","subCategory":"Herraduras","discount":0,"currency":"","price":0,"tax":0,"unitsPerItem":"JUEGO","unitMult":1,"relatedItems":["3452","4270","22009"],"shops":[{"cardCode":"401005","cardName":"Guglialmelli Oscar S.A.","cardFName":"Armeria Jabali","address2":"Paraguay 1109 y Rodo"}],"listOrder":"01050-000210","id":3195,"slug":"3195","code":"3195","subcategory":"Herraduras","images":["https://goldfarb.blob.core.windows.net/goldfarb/imagenes/3195.jpg"],"documents":[],"description":""},"3197":{"itemCode":"3197","brand":{"name":"Mustad","slug":"mustad"},"invoices":125,"finalPrice":0,"hasStock":true,"title":"Herradura Ac.Acanalada Pesada Nº3 Mustad","family":"Herramientas","category":"Prevención y Seguridad","subCategory":"Herraduras","discount":0,"currency":"","price":0,"tax":0,"unitsPerItem":"JUEGO","unitMult":1,"relatedItems":["3452","4270","22009"],"shops":[{"cardCode":"401005","cardName":"Guglialmelli Oscar S.A.","cardFName":"Armeria Jabali","address2":"Paraguay 1109 y Rodo"}],"listOrder":"01050-000220","id":3197,"slug":"3197","code":"3197","subcategory":"Herraduras","images":["https://goldfarb.blob.core.windows.net/goldfarb/imagenes/3197.jpg"],"documents":[],"description":""},"3198":{"itemCode":"3198","brand":{"name":"Mustad","slug":"mustad"},"invoices":110,"finalPrice":0,"hasStock":true,"title":"Herradura Ac.Acanalada Pesada Nº4 Mustad","family":"Herramientas","category":"Prevención y Seguridad","subCategory":"Herraduras","discount":0,"currency":"","price":0,"tax":0,"unitsPerItem":"JUEGO","unitMult":1,"relatedItems":["3452","4270","22009"],"shops":[{"cardCode":"401005","cardName":"Guglialmelli Oscar S.A.","cardFName":"Armeria Jabali","address2":"Paraguay 1109 y Rodo"}],"listOrder":"01050-000230","id":3198,"slug":"3198","code":"3198","subcategory":"Herraduras","images":["https://goldfarb.blob.core.windows.net/goldfarb/imagenes/3198.jpg"],"documents":[],"description":""},"3220":{"itemCode":"3220","brand":{"name":"Goldex","slug":"goldex"},"invoices":162,"finalPrice":0,"hasStock":true,"title":"Carbones P/Amoladora 9'' Goldex","family":"Herramientas","category":"Repuestos","subCategory":"Esmerilad.Y Pulidora","discount":0,"currency":"","price":0,"tax":22,"unitsPerItem":"JUEGO","unitMult":1,"relatedItems":["3452","4270","22009"],"shops":[{"cardCode":"401005","cardName":"Guglialmelli Oscar S.A.","cardFName":"Armeria Jabali","address2":"Paraguay 1109 y Rodo"}],"listOrder":"04220-000130","id":3220,"slug":"3220","code":"3220","subcategory":"Esmerilad.Y Pulidora","images":["https://goldfarb.blob.core.windows.net/goldfarb/imagenes/3220.jpg"],"documents":[],"description":""},"3221":{"itemCode":"3221","brand":{"name":"Goldex","slug":"goldex"},"invoices":277,"finalPrice":0,"hasStock":true,"title":"Carbones P/Amoladora 7'' Goldex","family":"Herramientas","category":"Repuestos","subCategory":"Esmerilad.Y Pulidora","discount":0,"currency":"","price":0,"tax":22,"unitsPerItem":"JUEGO","unitMult":1,"relatedItems":["3452","4270","22009"],"shops":[{"cardCode":"401005","cardName":"Guglialmelli Oscar S.A.","cardFName":"Armeria Jabali","address2":"Paraguay 1109 y Rodo"}],"listOrder":"04220-000120","id":3221,"slug":"3221","code":"3221","subcategory":"Esmerilad.Y Pulidora","images":["https://goldfarb.blob.core.windows.net/goldfarb/imagenes/3221.jpg"],"documents":[],"description":""},"3223":{"itemCode":"3223","brand":{"name":"Goldex","slug":"goldex"},"invoices":1385,"finalPrice":0,"hasStock":true,"title":"Carbones P/Taladro 3/8''-1/2'' - Amoladora 4.1/2'' 500W/550W Goldex","family":"Herramientas Electr.","category":"Repuestos","subCategory":"Esmerilad.Y Pulidora","discount":0,"currency":"","price":0,"tax":22,"unitsPerItem":"JUEGO","unitMult":1,"relatedItems":["3452","4270","22009"],"shops":[{"cardCode":"401005","cardName":"Guglialmelli Oscar S.A.","cardFName":"Armeria Jabali","address2":"Paraguay 1109 y Rodo"}],"listOrder":"04220-000280","id":3223,"slug":"3223","code":"3223","subcategory":"Esmerilad.Y Pulidora","images":[],"documents":["https://goldfarb.blob.core.windows.net/goldfarb/documentos/3223.pdf"],"description":""},"3237":{"itemCode":"3237","brand":{"name":"Goldex","slug":"goldex"},"invoices":225,"finalPrice":0,"hasStock":true,"title":"Cuchilla P/Cepillo M1B-AKJ8-82X2 / M1b.82x1 Goldex","family":"Herramientas Electr.","category":"Repuestos","subCategory":"Cepillos","discount":0,"currency":"","price":0,"tax":22,"unitsPerItem":"JUEGO","unitMult":1,"relatedItems":["3452","4270","22009"],"shops":[{"cardCode":"401005","cardName":"Guglialmelli Oscar S.A.","cardFName":"Armeria Jabali","address2":"Paraguay 1109 y Rodo"}],"listOrder":"04205-000270","id":3237,"slug":"3237","code":"3237","subcategory":"Cepillos","images":[],"documents":[],"description":""},"3238":{"itemCode":"3238","brand":{"name":"Goldex","slug":"goldex"},"invoices":777,"finalPrice":0,"hasStock":true,"title":"Llave Para Mandril 1/2'' Goldex","family":"Herramientas","category":"Herramientas Manuales","subCategory":"Llaves","discount":0,"currency":"","price":0,"tax":22,"unitsPerItem":"PIEZA","unitMult":1,"relatedItems":["3452","4270","22009"],"shops":[{"cardCode":"401005","cardName":"Guglialmelli Oscar S.A.","cardFName":"Armeria Jabali","address2":"Paraguay 1109 y Rodo"}],"listOrder":"01470-000170","id":3238,"slug":"3238","code":"3238","subcategory":"Llaves","images":["https://goldfarb.blob.core.windows.net/goldfarb/imagenes/3238.jpg"],"documents":["https://goldfarb.blob.core.windows.net/goldfarb/documentos/3238.pdf"],"description":""},"3239":{"itemCode":"3239","brand":{"name":"Goldex","slug":"goldex"},"invoices":269,"finalPrice":0,"hasStock":true,"title":"Llave Para Mandril 3/8'' Goldex","family":"Herramientas","category":"Herramientas Manuales","subCategory":"Llaves","discount":0,"currency":"","price":0,"tax":22,"unitsPerItem":"PIEZA","unitMult":1,"relatedItems":["3452","4270","22009"],"shops":[{"cardCode":"401005","cardName":"Guglialmelli Oscar S.A.","cardFName":"Armeria Jabali","address2":"Paraguay 1109 y Rodo"}],"listOrder":"04205-000780","id":3239,"slug":"3239","code":"3239","subcategory":"Llaves","images":["https://goldfarb.blob.core.windows.net/goldfarb/imagenes/3239.jpg"],"documents":[],"description":""},"3243":{"itemCode":"3243","brand":{"name":"Mustad","slug":"mustad"},"invoices":41,"finalPrice":0,"hasStock":false,"title":"Herraduras 4Pz. P/Mano Maroñas Nº5 Aluminio Mustad","family":"Herramientas","category":"Prevención y Seguridad","subCategory":"Herraduras","discount":0,"currency":"","price":0,"tax":22,"unitsPerItem":"CAJA","unitMult":1,"relatedItems":["3452","4270","22009"],"shops":[{"cardCode":"401005","cardName":"Guglialmelli Oscar S.A.","cardFName":"Armeria Jabali","address2":"Paraguay 1109 y Rodo"}],"listOrder":"01050-000640","id":3243,"slug":"3243","code":"3243","subcategory":"Herraduras","images":["https://goldfarb.blob.core.windows.net/goldfarb/imagenes/3243.jpg"],"documents":[],"description":""},"3244":{"itemCode":"3244","brand":{"name":"Mustad","slug":"mustad"},"invoices":50,"finalPrice":0,"hasStock":false,"title":"Herraduras 4Pz. P/Pata Maroñas Nº5 Aluminio Mustad","family":"Herramientas","category":"Prevención y Seguridad","subCategory":"Herraduras","discount":0,"currency":"","price":0,"tax":22,"unitsPerItem":"CAJA","unitMult":1,"relatedItems":["3452","4270","22009"],"shops":[{"cardCode":"401005","cardName":"Guglialmelli Oscar S.A.","cardFName":"Armeria Jabali","address2":"Paraguay 1109 y Rodo"}],"listOrder":"01050-000650","id":3244,"slug":"3244","code":"3244","subcategory":"Herraduras","images":["https://goldfarb.blob.core.windows.net/goldfarb/imagenes/3244.jpg"],"documents":[],"description":""},"3245":{"itemCode":"3245","brand":{"name":"Mustad","slug":"mustad"},"invoices":38,"finalPrice":0,"hasStock":false,"title":"Herraduras 4Pz. P/Mano Maroñas Nº6 Aluminio Mustad","family":"Herramientas","category":"Prevención y Seguridad","subCategory":"Herraduras","discount":0,"currency":"","price":0,"tax":22,"unitsPerItem":"CAJA","unitMult":1,"relatedItems":["3452","4270","22009"],"shops":[{"cardCode":"401005","cardName":"Guglialmelli Oscar S.A.","cardFName":"Armeria Jabali","address2":"Paraguay 1109 y Rodo"}],"listOrder":"01050-000660","id":3245,"slug":"3245","code":"3245","subcategory":"Herraduras","images":["https://goldfarb.blob.core.windows.net/goldfarb/imagenes/3245.jpg"],"documents":[],"description":""},"3246":{"itemCode":"3246","brand":{"name":"Mustad","slug":"mustad"},"invoices":34,"finalPrice":0,"hasStock":false,"title":"Herraduras 4Pz. P/Pata Maroñas Nº6 Aluminio Mustad","family":"Herramientas","category":"Prevención y Seguridad","subCategory":"Herraduras","discount":0,"currency":"","price":0,"tax":22,"unitsPerItem":"CAJA","unitMult":1,"relatedItems":["3452","4270","22009"],"shops":[{"cardCode":"401005","cardName":"Guglialmelli Oscar S.A.","cardFName":"Armeria Jabali","address2":"Paraguay 1109 y Rodo"}],"listOrder":"01050-000670","id":3246,"slug":"3246","code":"3246","subcategory":"Herraduras","images":["https://goldfarb.blob.core.windows.net/goldfarb/imagenes/3246.jpg"],"documents":[],"description":""},"3261":{"itemCode":"3261","brand":{"name":"Tramontina","slug":"tramontina"},"invoices":18,"finalPrice":0,"hasStock":true,"title":"Cuchilla P/Cepillo Tramontina 43370/302-4908/02","family":"Herramientas","category":"Accesorios","subCategory":"Hierros","discount":0,"currency":"","price":0,"tax":22,"unitsPerItem":"PIEZA","unitMult":1,"relatedItems":["3452","4270","22009"],"shops":[{"cardCode":"401005","cardName":"Guglialmelli Oscar S.A.","cardFName":"Armeria Jabali","address2":"Paraguay 1109 y Rodo"}],"listOrder":"00460-000040","id":3261,"slug":"3261","code":"3261","subcategory":"Hierros","images":["https://goldfarb.blob.core.windows.net/goldfarb/imagenes/3261.jpg"],"documents":[],"description":""},"3262":{"itemCode":"3262","brand":{"name":"Tramontina","slug":"tramontina"},"invoices":0,"finalPrice":0,"hasStock":true,"title":"Cuchilla P/Cepillo Tramontina 43370/303-4908/03","family":"Herramientas","category":"Accesorios","subCategory":"Hierros","discount":0,"currency":"","price":0,"tax":22,"unitsPerItem":"PIEZA","unitMult":1,"relatedItems":["3452","4270","22009"],"shops":[{"cardCode":"401005","cardName":"Guglialmelli Oscar S.A.","cardFName":"Armeria Jabali","address2":"Paraguay 1109 y Rodo"}],"listOrder":"00460-000050","id":3262,"slug":"3262","code":"3262","subcategory":"Hierros","images":["https://goldfarb.blob.core.windows.net/goldfarb/imagenes/3262.jpg"],"documents":[],"description":""},"3274":{"itemCode":"3274","brand":{"name":"Goldex","slug":"goldex"},"invoices":127,"finalPrice":0,"hasStock":false,"title":"Hoja De Lija 10 Unid. P/Lijadora Excentrica Goldex","family":"Herramientas","category":"Accesorios","subCategory":"Accesorios","discount":0,"currency":"","price":0,"tax":22,"unitsPerItem":"JUEGO","unitMult":1,"relatedItems":["3452","4270","22009"],"shops":[{"cardCode":"401005","cardName":"Guglialmelli Oscar S.A.","cardFName":"Armeria Jabali","address2":"Paraguay 1109 y Rodo"}],"listOrder":"04205-000420","id":3274,"slug":"3274","code":"3274","subcategory":"Accesorios","images":["https://goldfarb.blob.core.windows.net/goldfarb/imagenes/3274.jpg"],"documents":[],"description":"Incluye dos dicos de cada grano:\rgr 60; gr 80; gr 100; gr 120; gr 180."},"3280":{"itemCode":"3280","brand":{"name":"Goldex","slug":"goldex"},"invoices":83,"finalPrice":0,"hasStock":true,"title":"Tenaza Armador Todo Corte 8'' Ais.Liviana China","family":"Herramientas","category":"Herramientas Manuales","subCategory":"Tenazas","discount":0,"currency":"","price":0,"tax":22,"unitsPerItem":"PIEZA","unitMult":1,"relatedItems":["3452","4270","22009"],"shops":[{"cardCode":"401005","cardName":"Guglialmelli Oscar S.A.","cardFName":"Armeria Jabali","address2":"Paraguay 1109 y Rodo"}],"listOrder":"02100-000210","id":3280,"slug":"3280","code":"3280","subcategory":"Tenazas","images":["https://goldfarb.blob.core.windows.net/goldfarb/imagenes/3280.jpg"],"documents":[],"description":""},"3328":{"itemCode":"3328","brand":{"name":"Goldex","slug":"goldex"},"invoices":143,"finalPrice":0,"hasStock":true,"title":"Carbones P/Rotomartillo 26mm Goldex","family":"Herramientas","category":"Repuestos","subCategory":"Rotopercutores","discount":0,"currency":"","price":0,"tax":22,"unitsPerItem":"JUEGO","unitMult":1,"relatedItems":["3452","4270","22009"],"shops":[{"cardCode":"401005","cardName":"Guglialmelli Oscar S.A.","cardFName":"Armeria Jabali","address2":"Paraguay 1109 y Rodo"}],"listOrder":"04220-000210","id":3328,"slug":"3328","code":"3328","subcategory":"Rotopercutores","images":["https://goldfarb.blob.core.windows.net/goldfarb/imagenes/3328.jpg"],"documents":[],"description":""},"3330":{"itemCode":"3330","brand":{"name":"Goldex","slug":"goldex"},"invoices":66,"finalPrice":0,"hasStock":true,"title":"Carbones P/Rotomartillo 38mm Goldex","family":"Herramientas","category":"Repuestos","subCategory":"Rotopercutores","discount":0,"currency":"","price":0,"tax":22,"unitsPerItem":"JUEGO","unitMult":1,"relatedItems":["3452","4270","22009"],"shops":[{"cardCode":"401005","cardName":"Guglialmelli Oscar S.A.","cardFName":"Armeria Jabali","address2":"Paraguay 1109 y Rodo"}],"listOrder":"04220-000220","id":3330,"slug":"3330","code":"3330","subcategory":"Rotopercutores","images":["https://goldfarb.blob.core.windows.net/goldfarb/imagenes/3330.jpg"],"documents":[],"description":""},"3340":{"itemCode":"3340","brand":{"name":"Sandflex","slug":"sandflex"},"invoices":1597,"finalPrice":0,"hasStock":false,"title":"Hoja Sierra Bimetálica 24 Dientes Sandflex Bahco","family":"Herramientas","category":"Accesorios","subCategory":"Hojas","discount":0,"currency":"","price":0,"tax":22,"unitsPerItem":"PIEZA","unitMult":10,"relatedItems":["3452","4270","22009"],"shops":[{"cardCode":"401005","cardName":"Guglialmelli Oscar S.A.","cardFName":"Armeria Jabali","address2":"Paraguay 1109 y Rodo"}],"listOrder":"01160-000040","id":3340,"slug":"3340","code":"3340","subcategory":"Hojas","images":["https://goldfarb.blob.core.windows.net/goldfarb/imagenes/3340.jpg"],"documents":[],"description":"Hoja bimetálica con dientes de precisión para todo tipo de aserrado de metales\rLa hoja Sandflex® combina un rendimiento de corte extremo y resistencia al desgaste\rAlto grado de flexibilidad y es muy superior a todas las hojas duras de alta velocidad o hojas flexibles convencionales.\rCon una parte posterior de la hoja de acero para muelles resistente y flexible y una línea de dientes en super HSS de alta aleación\rPrácticamente irrompible e inastillable\rExcelentes propiedades de desgaste de la banda dentada de acero de súper alta velocidad en una parte posterior flexible\rEsta hoja está garantizada para mantener su nitidez durante mucho tiempo.\rMayor comodidad y corte más fácil\rRendimiento superior, corte rápido y mayor longevidad."},"3346":{"itemCode":"3346","brand":{"name":"Tramontina","slug":"tramontina"},"invoices":483,"finalPrice":0,"hasStock":true,"title":"Hoz P/Pasto Tramontina 77682/015-7682/01","family":"Herramientas","category":"Herramientas Manuales","subCategory":"Hoces","discount":0,"currency":"","price":0,"tax":22,"unitsPerItem":"PIEZA","unitMult":1,"relatedItems":["3452","4270","22009"],"shops":[{"cardCode":"401005","cardName":"Guglialmelli Oscar S.A.","cardFName":"Armeria Jabali","address2":"Paraguay 1109 y Rodo"}],"listOrder":"01180-000030","id":3346,"slug":"3346","code":"3346","subcategory":"Hoces","images":["https://goldfarb.blob.core.windows.net/goldfarb/imagenes/3346.jpg"],"documents":[],"description":""},"3347":{"itemCode":"3347","brand":{"name":"Tramontina","slug":"tramontina"},"invoices":719,"finalPrice":0,"hasStock":false,"title":"Hoz P/Pasto Tramontina 77682/025-7682/02","family":"Herramientas","category":"Herramientas Manuales","subCategory":"Hoces","discount":0,"currency":"","price":0,"tax":22,"unitsPerItem":"PIEZA","unitMult":1,"relatedItems":["3452","4270","22009"],"shops":[{"cardCode":"401005","cardName":"Guglialmelli Oscar S.A.","cardFName":"Armeria Jabali","address2":"Paraguay 1109 y Rodo"}],"listOrder":"01180-000040","id":3347,"slug":"3347","code":"3347","subcategory":"Hoces","images":["https://goldfarb.blob.core.windows.net/goldfarb/imagenes/3347.jpg"],"documents":[],"description":""},"3349":{"itemCode":"3349","brand":{"name":"Goldex","slug":"goldex"},"invoices":221,"finalPrice":0,"hasStock":true,"title":"Carbones Para Sierra Circular 7.1/4 Goldex","family":"Herramientas","category":"Repuestos","subCategory":"Sierras","discount":0,"currency":"","price":0,"tax":22,"unitsPerItem":"JUEGO","unitMult":1,"relatedItems":["3452","4270","22009"],"shops":[{"cardCode":"401005","cardName":"Guglialmelli Oscar S.A.","cardFName":"Armeria Jabali","address2":"Paraguay 1109 y Rodo"}],"listOrder":"04220-000270","id":3349,"slug":"3349","code":"3349","subcategory":"Sierras","images":["https://goldfarb.blob.core.windows.net/goldfarb/imagenes/3349.jpg"],"documents":[],"description":""},"3350":{"itemCode":"3350","brand":{"name":"Goldex","slug":"goldex"},"invoices":44,"finalPrice":0,"hasStock":false,"title":"Hoja Sierra Junior China","family":"Herramientas","category":"Sierras","subCategory":"Hojas de sierra","discount":0,"currency":"","price":0,"tax":22,"unitsPerItem":"PIEZA","unitMult":1,"relatedItems":["3452","4270","22009"],"shops":[{"cardCode":"401005","cardName":"Guglialmelli Oscar S.A.","cardFName":"Armeria Jabali","address2":"Paraguay 1109 y Rodo"}],"listOrder":"01150-000020","id":3350,"slug":"3350","code":"3350","subcategory":"Hojas de sierra","images":["https://goldfarb.blob.core.windows.net/goldfarb/imagenes/3350.jpg"],"documents":[],"description":""},"3366":{"itemCode":"3366","brand":{"name":"Tramontina","slug":"tramontina"},"invoices":285,"finalPrice":0,"hasStock":true,"title":"Horquilla 5 Dientes C/Cabo De Madera Tramontina 77144/554-77142/554","family":"Herramientas","category":"Herramientas Manuales","subCategory":"Horquillas","discount":0,"currency":"","price":0,"tax":22,"unitsPerItem":"PIEZA","unitMult":1,"relatedItems":["3452","4270","22009"],"shops":[{"cardCode":"401005","cardName":"Guglialmelli Oscar S.A.","cardFName":"Armeria Jabali","address2":"Paraguay 1109 y Rodo"}],"listOrder":"01200-000040","id":3366,"slug":"3366","code":"3366","subcategory":"Horquillas","images":["https://goldfarb.blob.core.windows.net/goldfarb/imagenes/3366.jpg"],"documents":[],"description":""},"3367":{"itemCode":"3367","brand":{"name":"Tramontina","slug":"tramontina"},"invoices":454,"finalPrice":0,"hasStock":true,"title":"Horquilla 4 Dientes C/Cabo De Madera Tramontina 77144/544-77142/544","family":"Herramientas","category":"Herramientas Manuales","subCategory":"Horquillas","discount":0,"currency":"","price":0,"tax":22,"unitsPerItem":"PIEZA","unitMult":1,"relatedItems":["3452","4270","22009"],"shops":[{"cardCode":"401005","cardName":"Guglialmelli Oscar S.A.","cardFName":"Armeria Jabali","address2":"Paraguay 1109 y Rodo"}],"listOrder":"01200-000030","id":3367,"slug":"3367","code":"3367","subcategory":"Horquillas","images":["https://goldfarb.blob.core.windows.net/goldfarb/imagenes/3367.jpg"],"documents":[],"description":""},"3371":{"itemCode":"3371","brand":{"name":"Eclipse","slug":"eclipse"},"invoices":501,"finalPrice":0,"hasStock":true,"title":"Hoja Sierra P/Metal Acero Carbono 18 Dientes AM45W Eclipse","family":"Herramientas","category":"Accesorios","subCategory":"Hojas","discount":0,"currency":"","price":0,"tax":22,"unitsPerItem":"PIEZA","unitMult":10,"relatedItems":["3452","4270","22009"],"shops":[{"cardCode":"401005","cardName":"Guglialmelli Oscar S.A.","cardFName":"Armeria Jabali","address2":"Paraguay 1109 y Rodo"}],"listOrder":"01150-000050","id":3371,"slug":"3371","code":"3371","subcategory":"Hojas","images":["https://goldfarb.blob.core.windows.net/goldfarb/imagenes/3371.jpg"],"documents":[],"description":""},"3372":{"itemCode":"3372","brand":{"name":"Eclipse","slug":"eclipse"},"invoices":253,"finalPrice":0,"hasStock":true,"title":"Hoja Sierra P/Metal Acero Carbono 24 Dientes AM46B Eclipse","family":"Herramientas","category":"Accesorios","subCategory":"Hojas","discount":0,"currency":"","price":0,"tax":22,"unitsPerItem":"PIEZA","unitMult":10,"relatedItems":["3452","4270","22009"],"shops":[{"cardCode":"401005","cardName":"Guglialmelli Oscar S.A.","cardFName":"Armeria Jabali","address2":"Paraguay 1109 y Rodo"}],"listOrder":"01150-000060","id":3372,"slug":"3372","code":"3372","subcategory":"Hojas","images":["https://goldfarb.blob.core.windows.net/goldfarb/imagenes/3372.jpg"],"documents":[],"description":""},"3373":{"itemCode":"3373","brand":{"name":"Eclipse","slug":"eclipse"},"invoices":3329,"finalPrice":0,"hasStock":true,"title":"Hoja Sierra P/Metal Acero Rápido 18 Dientes AE45B Eclipse","family":"Herramientas","category":"Accesorios","subCategory":"Hojas","discount":0,"currency":"","price":0,"tax":22,"unitsPerItem":"PIEZA","unitMult":10,"relatedItems":["3452","4270","22009"],"shops":[{"cardCode":"401005","cardName":"Guglialmelli Oscar S.A.","cardFName":"Armeria Jabali","address2":"Paraguay 1109 y Rodo"}],"listOrder":"01150-000070","id":3373,"slug":"3373","code":"3373","subcategory":"Hojas","images":["https://goldfarb.blob.core.windows.net/goldfarb/imagenes/3373.jpg"],"documents":[],"description":""},"3374":{"itemCode":"3374","brand":{"name":"Eclipse","slug":"eclipse"},"invoices":1812,"finalPrice":0,"hasStock":true,"title":"Hoja Sierra P/Metal Acero Rápido 24 Dientes AE46X Eclipse","family":"Herramientas","category":"Accesorios","subCategory":"Hojas","discount":0,"currency":"","price":0,"tax":22,"unitsPerItem":"PIEZA","unitMult":10,"relatedItems":["3452","4270","22009"],"shops":[{"cardCode":"401005","cardName":"Guglialmelli Oscar S.A.","cardFName":"Armeria Jabali","address2":"Paraguay 1109 y Rodo"}],"listOrder":"01150-000080","id":3374,"slug":"3374","code":"3374","subcategory":"Hojas","images":["https://goldfarb.blob.core.windows.net/goldfarb/imagenes/3374.jpg"],"documents":[],"description":""},"3376":{"itemCode":"3376","brand":{"name":"Eclipse","slug":"eclipse"},"invoices":3648,"finalPrice":0,"hasStock":true,"title":"Hoja Sierra P/Metal Junior 71-132R Eclipse","family":"Herramientas","category":"Accesorios","subCategory":"Hojas","discount":0,"currency":"","price":0,"tax":22,"unitsPerItem":"PIEZA","unitMult":10,"relatedItems":["3452","4270","22009"],"shops":[{"cardCode":"401005","cardName":"Guglialmelli Oscar S.A.","cardFName":"Armeria Jabali","address2":"Paraguay 1109 y Rodo"}],"listOrder":"01150-000090","id":3376,"slug":"3376","code":"3376","subcategory":"Hojas","images":["https://goldfarb.blob.core.windows.net/goldfarb/imagenes/3376.jpg"],"documents":[],"description":""},"3377":{"itemCode":"3377","brand":{"name":"Sandflex","slug":"sandflex"},"invoices":2502,"finalPrice":0,"hasStock":true,"title":"Hoja Sierra Bimetálica 18 Dientes Sandflex Bahco","family":"Herramientas","category":"Accesorios","subCategory":"Hojas","discount":0,"currency":"","price":0,"tax":22,"unitsPerItem":"PIEZA","unitMult":10,"relatedItems":["3452","4270","22009"],"shops":[{"cardCode":"401005","cardName":"Guglialmelli Oscar S.A.","cardFName":"Armeria Jabali","address2":"Paraguay 1109 y Rodo"}],"listOrder":"01160-000030","id":3377,"slug":"3377","code":"3377","subcategory":"Hojas","images":["https://goldfarb.blob.core.windows.net/goldfarb/imagenes/3377.jpg"],"documents":[],"description":"Hoja bimetálica con dientes de precisión para todo tipo de aserrado de metales\rLa hoja Sandflex® combina un rendimiento de corte extremo y resistencia al desgaste\rAlto grado de flexibilidad y es muy superior a todas las hojas duras de alta velocidad o hojas flexibles convencionales.\rCon una parte posterior de la hoja de acero para muelles resistente y flexible y una línea de dientes en super HSS de alta aleación\rPrácticamente irrompible e inastillable\rExcelentes propiedades de desgaste de la banda dentada de acero de súper alta velocidad en una parte posterior flexible\rEsta hoja está garantizada para mantener su nitidez durante mucho tiempo.\rMayor comodidad y corte más fácil\rRendimiento superior, corte rápido y mayor longevidad."},"3378":{"itemCode":"3378","brand":{"name":"Eclipse","slug":"eclipse"},"invoices":122,"finalPrice":0,"hasStock":true,"title":"Hoja P/Máquina Acero Rápido 12x1x10d Eclipse","family":"Herramientas","category":"Accesorios","subCategory":"Hojas","discount":0,"currency":"","price":0,"tax":22,"unitsPerItem":"PIEZA","unitMult":1,"relatedItems":["3452","4270","22009"],"shops":[{"cardCode":"401005","cardName":"Guglialmelli Oscar S.A.","cardFName":"Armeria Jabali","address2":"Paraguay 1109 y Rodo"}],"listOrder":"01170-000030","id":3378,"slug":"3378","code":"3378","subcategory":"Hojas","images":["https://goldfarb.blob.core.windows.net/goldfarb/imagenes/3378.jpg"],"documents":[],"description":""},"3379":{"itemCode":"3379","brand":{"name":"Eclipse","slug":"eclipse"},"invoices":204,"finalPrice":0,"hasStock":true,"title":"Hoja P/Máquina Acero Rápido 14x1x10d-AE223R Eclipse","family":"Herramientas","category":"Accesorios","subCategory":"Hojas","discount":0,"currency":"","price":0,"tax":22,"unitsPerItem":"PIEZA","unitMult":1,"relatedItems":["3452","4270","22009"],"shops":[{"cardCode":"401005","cardName":"Guglialmelli Oscar S.A.","cardFName":"Armeria Jabali","address2":"Paraguay 1109 y Rodo"}],"listOrder":"01170-000050","id":3379,"slug":"3379","code":"3379","subcategory":"Hojas","images":["https://goldfarb.blob.core.windows.net/goldfarb/imagenes/3379.jpg"],"documents":[],"description":""},"3380":{"itemCode":"3380","brand":{"name":"Eclipse","slug":"eclipse"},"invoices":54,"finalPrice":0,"hasStock":false,"title":"Hoja P/Maquina Acero Rápido 16x1.1/4x6d Eclipse","family":"Herramientas","category":"Accesorios","subCategory":"Hojas","discount":0,"currency":"","price":0,"tax":22,"unitsPerItem":"PIEZA","unitMult":1,"relatedItems":["3452","4270","22009"],"shops":[{"cardCode":"401005","cardName":"Guglialmelli Oscar S.A.","cardFName":"Armeria Jabali","address2":"Paraguay 1109 y Rodo"}],"listOrder":"01170-000070","id":3380,"slug":"3380","code":"3380","subcategory":"Hojas","images":["https://goldfarb.blob.core.windows.net/goldfarb/imagenes/3380.jpg"],"documents":[],"description":""},"3381":{"itemCode":"3381","brand":{"name":"Eclipse","slug":"eclipse"},"invoices":15,"finalPrice":0,"hasStock":true,"title":"Hoja P/Máquina Acero Rápido 18x1.1/4x6d Eclipse","family":"Herramientas","category":"Accesorios","subCategory":"Hojas","discount":0,"currency":"","price":0,"tax":22,"unitsPerItem":"PIEZA","unitMult":1,"relatedItems":["3452","4270","22009"],"shops":[{"cardCode":"401005","cardName":"Guglialmelli Oscar S.A.","cardFName":"Armeria Jabali","address2":"Paraguay 1109 y Rodo"}],"listOrder":"01170-000090","id":3381,"slug":"3381","code":"3381","subcategory":"Hojas","images":["https://goldfarb.blob.core.windows.net/goldfarb/imagenes/3381.jpg"],"documents":[],"description":""},"3382":{"itemCode":"3382","brand":{"name":"Eclipse","slug":"eclipse"},"invoices":7,"finalPrice":0,"hasStock":true,"title":"Hoja P/Máquina Acero Rápido 21x1.1/2x6d Eclipse","family":"Herramientas","category":"Accesorios","subCategory":"Hojas","discount":0,"currency":"","price":0,"tax":22,"unitsPerItem":"PIEZA","unitMult":1,"relatedItems":["3452","4270","22009"],"shops":[{"cardCode":"401005","cardName":"Guglialmelli Oscar S.A.","cardFName":"Armeria Jabali","address2":"Paraguay 1109 y Rodo"}],"listOrder":"01170-000110","id":3382,"slug":"3382","code":"3382","subcategory":"Hojas","images":["https://goldfarb.blob.core.windows.net/goldfarb/imagenes/3382.jpg"],"documents":[],"description":""},"3385":{"itemCode":"3385","brand":{"name":"Eclipse","slug":"eclipse"},"invoices":110,"finalPrice":0,"hasStock":true,"title":"Hoja Sierra Coping Eclipse","family":"Herramientas","category":"Accesorios","subCategory":"Hojas","discount":0,"currency":"","price":0,"tax":22,"unitsPerItem":"PIEZA","unitMult":10,"relatedItems":["3452","4270","22009"],"shops":[{"cardCode":"401005","cardName":"Guglialmelli Oscar S.A.","cardFName":"Armeria Jabali","address2":"Paraguay 1109 y Rodo"}],"listOrder":"01150-000100","id":3385,"slug":"3385","code":"3385","subcategory":"Hojas","images":["https://goldfarb.blob.core.windows.net/goldfarb/imagenes/3385.jpg"],"documents":[],"description":""},"3387":{"itemCode":"3387","brand":{"name":"Eclipse","slug":"eclipse"},"invoices":712,"finalPrice":0,"hasStock":true,"title":"Hoja Sierra Acero Rápido 18 Bimetálica AA45E Eclipse","family":"Herramientas","category":"Accesorios","subCategory":"Hojas","discount":0,"currency":"","price":0,"tax":22,"unitsPerItem":"PIEZA","unitMult":10,"relatedItems":["3452","4270","22009"],"shops":[{"cardCode":"401005","cardName":"Guglialmelli Oscar S.A.","cardFName":"Armeria Jabali","address2":"Paraguay 1109 y Rodo"}],"listOrder":"01160-000050","id":3387,"slug":"3387","code":"3387","subcategory":"Hojas","images":["https://goldfarb.blob.core.windows.net/goldfarb/imagenes/3387.jpg"],"documents":[],"description":""},"3388":{"itemCode":"3388","brand":{"name":"Eclipse","slug":"eclipse"},"invoices":362,"finalPrice":0,"hasStock":true,"title":"Hoja Sierra Acero Rápido 24 Bimetálica AA46V Eclipse","family":"Herramientas","category":"Accesorios","subCategory":"Hojas","discount":0,"currency":"","price":0,"tax":22,"unitsPerItem":"PIEZA","unitMult":10,"relatedItems":["3452","4270","22009"],"shops":[{"cardCode":"401005","cardName":"Guglialmelli Oscar S.A.","cardFName":"Armeria Jabali","address2":"Paraguay 1109 y Rodo"}],"listOrder":"01160-000060","id":3388,"slug":"3388","code":"3388","subcategory":"Hojas","images":["https://goldfarb.blob.core.windows.net/goldfarb/imagenes/3388.jpg"],"documents":[],"description":""},"3392":{"itemCode":"3392","brand":{"name":"Eclipse","slug":"eclipse"},"invoices":4,"finalPrice":0,"hasStock":true,"title":"Hoja Sierra Acero Rápido Plus30 24 Dientes Eclipse","family":"Herramientas","category":"Accesorios","subCategory":"Hojas","discount":0,"currency":"","price":0,"tax":22,"unitsPerItem":"HJ","unitMult":10,"relatedItems":["3452","4270","22009"],"shops":[{"cardCode":"401005","cardName":"Guglialmelli Oscar S.A.","cardFName":"Armeria Jabali","address2":"Paraguay 1109 y Rodo"}],"listOrder":"01160-000070","id":3392,"slug":"3392","code":"3392","subcategory":"Hojas","images":["https://goldfarb.blob.core.windows.net/goldfarb/imagenes/3392.jpg"],"documents":[],"description":""},"3439":{"itemCode":"3439","brand":{"name":"Goldex","slug":"goldex"},"invoices":3000,"finalPrice":0,"hasStock":true,"title":"Sierra Circular 7.1/4'' 1200W PCS185C-PCS180 Goldex","family":"Herramientas","category":"Herramientas Eléctricas","subCategory":"Sierras","discount":0,"currency":"","price":0,"tax":22,"unitsPerItem":"PIEZA","unitMult":1,"relatedItems":["3452","4270","22009"],"shops":[{"cardCode":"401005","cardName":"Guglialmelli Oscar S.A.","cardFName":"Armeria Jabali","address2":"Paraguay 1109 y Rodo"}],"listOrder":"04200-000670","id":3439,"slug":"3439","code":"3439","subcategory":"Sierras","images":["https://goldfarb.blob.core.windows.net/goldfarb/imagenes/3439.jpg","https://goldfarb.blob.core.windows.net/goldfarb/imagenes/3439-1.jpg","https://goldfarb.blob.core.windows.net/goldfarb/imagenes/3439-2.jpg","https://goldfarb.blob.core.windows.net/goldfarb/imagenes/3439-3.jpg"],"documents":["https://goldfarb.blob.core.windows.net/goldfarb/documentos/3439.pdf"],"description":"Alimentación eléctrica  220 V 50 Hz.                               \rPotencia de motor 1200 W.  \rVelocidad en vacio 4500 RPM.\rIncluye guia y protector de hoja.\rEspesor de corte maximo de 64 mm.\rIncluye disco de 7 1/4'' 24D.\rUso hobby. \rGarantia 1 año."},"3449":{"itemCode":"3449","brand":{"name":"Goldex","slug":"goldex"},"invoices":3852,"finalPrice":0,"hasStock":true,"title":"Taladro C/Percutor 10mm 500W Ergonomico ZIJ-10T Goldex","family":"Herramientas","category":"Herramientas Eléctricas","subCategory":"Taladros","discount":0,"currency":"","price":0,"tax":22,"unitsPerItem":"PIEZA","unitMult":1,"relatedItems":["3452","4270","22009"],"shops":[{"cardCode":"401005","cardName":"Guglialmelli Oscar S.A.","cardFName":"Armeria Jabali","address2":"Paraguay 1109 y Rodo"}],"listOrder":"04200-000740","id":3449,"slug":"3449","code":"3449","subcategory":"Taladros","images":["https://goldfarb.blob.core.windows.net/goldfarb/imagenes/3449.jpg","https://goldfarb.blob.core.windows.net/goldfarb/imagenes/3449-1.jpg","https://goldfarb.blob.core.windows.net/goldfarb/imagenes/3449-2.jpg","https://goldfarb.blob.core.windows.net/goldfarb/imagenes/3449-3.jpg"],"documents":[],"description":"Alimentación eléctrica  220 V 50 Hz.                               \rPotencia de motor 500 W.  \rVelocidad variable y reversa 0 - 2500 RPM.\rCapacidad de mandril 1.5 - 10 mm (3/8\").\rMontado sobre rulemanes.\rDoble aislación.\rUso hobby. \rGarantia 1 año."},"3451":{"itemCode":"3451","brand":{"name":"Goldex","slug":"goldex"},"invoices":5398,"finalPrice":0,"hasStock":true,"title":"Taladro C/Percutor 13mm 500W ZIJ-13T Goldex","family":"Herramientas","category":"Herramientas Eléctricas","subCategory":"Taladros","discount":0,"currency":"","price":0,"tax":22,"unitsPerItem":"PIEZA","unitMult":1,"relatedItems":["3452","4270","22009"],"shops":[{"cardCode":"401005","cardName":"Guglialmelli Oscar S.A.","cardFName":"Armeria Jabali","address2":"Paraguay 1109 y Rodo"}],"listOrder":"04200-000750","id":3451,"slug":"3451","code":"3451","subcategory":"Taladros","images":["https://goldfarb.blob.core.windows.net/goldfarb/imagenes/3451.jpg","https://goldfarb.blob.core.windows.net/goldfarb/imagenes/3451-1.jpg","https://goldfarb.blob.core.windows.net/goldfarb/imagenes/3451-2.jpg","https://goldfarb.blob.core.windows.net/goldfarb/imagenes/3451-3.jpg"],"documents":[],"description":"Alimentación eléctrica  220 V 50 Hz.                               \rPotencia de motor 500 W.  \rVelocidad variable y reversa 0 - 2800 RPM.\rCapacidad de mandril 1.5 - 13 mm (1/2\").\rMontado sobre rulemanes.\rDoble aislación.\rUso hobby. \rGarantia 1 año."},"3452":{"itemCode":"3452","brand":{"name":"Goldex","slug":"goldex"},"invoices":11754,"finalPrice":0,"hasStock":true,"title":"Amoladora Angular 4.1/2'' 550W HW-AG2139/P04-AG115K Goldex","family":"Herramientas","category":"Herramientas Eléctricas","subCategory":"Amoladoras","discount":0,"currency":"","price":0,"tax":22,"unitsPerItem":"PIEZA","unitMult":1,"relatedItems":["3452","4270","22009"],"shops":[{"cardCode":"401005","cardName":"Guglialmelli Oscar S.A.","cardFName":"Armeria Jabali","address2":"Paraguay 1109 y Rodo"}],"listOrder":"04200-000110","id":3452,"slug":"3452","code":"3452","subcategory":"Amoladoras","images":["https://goldfarb.blob.core.windows.net/goldfarb/imagenes/3452.jpg","https://goldfarb.blob.core.windows.net/goldfarb/imagenes/3452-1.jpg","https://goldfarb.blob.core.windows.net/goldfarb/imagenes/3452-2.jpg","https://goldfarb.blob.core.windows.net/goldfarb/imagenes/3452-3.jpg"],"documents":["https://goldfarb.blob.core.windows.net/goldfarb/documentos/3452.pdf"],"description":"Alimentación eléctrica  220 V 50 Hz.                               \rPotencia de motor 550 W.  \rVelocidad en vacio 10000 RPM.\rPara disco de 115 mm con buje M14.\rUso hobby. \rGarantia 1 año."},"3461":{"itemCode":"3461","brand":{"name":"Goldex","slug":"goldex"},"invoices":408,"finalPrice":0,"hasStock":true,"title":"Lijadora Orbital 240W 110x100mmm HW-PS1801 Goldex","family":"Herramientas","category":"Herramientas Eléctricas","subCategory":"Lijadoras","discount":0,"currency":"","price":0,"tax":22,"unitsPerItem":"PIEZA","unitMult":1,"relatedItems":["3452","4270","22009"],"shops":[{"cardCode":"401005","cardName":"Guglialmelli Oscar S.A.","cardFName":"Armeria Jabali","address2":"Paraguay 1109 y Rodo"}],"listOrder":"04200-000530","id":3461,"slug":"3461","code":"3461","subcategory":"Lijadoras","images":["https://goldfarb.blob.core.windows.net/goldfarb/imagenes/3461.jpg","https://goldfarb.blob.core.windows.net/goldfarb/imagenes/3461-1.jpg","https://goldfarb.blob.core.windows.net/goldfarb/imagenes/3461-2.jpg","https://goldfarb.blob.core.windows.net/goldfarb/imagenes/3461-3.jpg"],"documents":[],"description":"Alimentación eléctrica  220 V 50 Hz.                               \rPotencia de motor 240 W.  \rVelocidad en vacio 12000 RPM.\rPlaca de base 110 x 100mm\rCon salida para aspiración de polvo y bolsa.\rUso hobby. \rGarantia 1 año."},"3462":{"itemCode":"3462","brand":{"name":"Goldex","slug":"goldex"},"invoices":398,"finalPrice":0,"hasStock":true,"title":"Sierra Sensitiva 14'' 2000W J1G350 Goldex","family":"Herramientas","category":"Herramientas Eléctricas","subCategory":"Sierras","discount":0,"currency":"","price":0,"tax":22,"unitsPerItem":"PIEZA","unitMult":1,"relatedItems":["3452","4270","22009"],"shops":[{"cardCode":"401005","cardName":"Guglialmelli Oscar S.A.","cardFName":"Armeria Jabali","address2":"Paraguay 1109 y Rodo"}],"listOrder":"04200-000710","id":3462,"slug":"3462","code":"3462","subcategory":"Sierras","images":["https://goldfarb.blob.core.windows.net/goldfarb/imagenes/3462.jpg"],"documents":[],"description":"Alimentación eléctrica  220 V 50 Hz.                               \rPotencia de motor 2000 W.  \rVelocidad en vacio 4500 RPM.\rMorza de ajuste y guia para cortes.\rCorte de hasta 75mm. en macizo y 120mm. en perfiles.\rIncluye disco de carburo de 350 mm. ( 14'' ).\rGarantia 1 año."},"3463":{"itemCode":"3463","brand":{"name":"Goldex","slug":"goldex"},"invoices":1927,"finalPrice":0,"hasStock":true,"title":"Sierra Caladora 350W M1q-50 (6)t Goldex","family":"Herramientas","category":"Herramientas Eléctricas","subCategory":"Caladoras","discount":0,"currency":"","price":0,"tax":22,"unitsPerItem":"PIEZA","unitMult":1,"relatedItems":["3452","4270","22009"],"shops":[{"cardCode":"401005","cardName":"Guglialmelli Oscar S.A.","cardFName":"Armeria Jabali","address2":"Paraguay 1109 y Rodo"}],"listOrder":"04200-000330","id":3463,"slug":"3463","code":"3463","subcategory":"Caladoras","images":["https://goldfarb.blob.core.windows.net/goldfarb/imagenes/3463.jpg","https://goldfarb.blob.core.windows.net/goldfarb/imagenes/3463-1.jpg","https://goldfarb.blob.core.windows.net/goldfarb/imagenes/3463-2.jpg","https://goldfarb.blob.core.windows.net/goldfarb/imagenes/3463-3.jpg"],"documents":[],"description":"Alimentación eléctrica  220 V 50 Hz.                               \rPotencia de motor 350 W.  \rVelocidad en vacio 3000 RPM.\rBase regulable hasta 45º.\rEspesor maximo de corte de madera 40mm. \rEspesor de corte maximo de metal 3mm. \rDoble aislacion. \rUso hobby.\rGarantia 1 año."},"3464":{"itemCode":"3464","brand":{"name":"Goldex","slug":"goldex"},"invoices":842,"finalPrice":0,"hasStock":true,"title":"Cepillo 710W M1B-AKJ8-82X2/M1b.82x1-15000Rpm Goldex","family":"Herramientas","category":"Herramientas Eléctricas","subCategory":"Cepillos","discount":0,"currency":"","price":0,"tax":22,"unitsPerItem":"PIEZA","unitMult":1,"relatedItems":["3452","4270","22009"],"shops":[{"cardCode":"401005","cardName":"Guglialmelli Oscar S.A.","cardFName":"Armeria Jabali","address2":"Paraguay 1109 y Rodo"}],"listOrder":"04200-000880","id":3464,"slug":"3464","code":"3464","subcategory":"Cepillos","images":["https://goldfarb.blob.core.windows.net/goldfarb/imagenes/3464.jpg","https://goldfarb.blob.core.windows.net/goldfarb/imagenes/3464-1.jpg","https://goldfarb.blob.core.windows.net/goldfarb/imagenes/3464-2.jpg","https://goldfarb.blob.core.windows.net/goldfarb/imagenes/3464-3.jpg"],"documents":["https://goldfarb.blob.core.windows.net/goldfarb/documentos/3464.pdf"],"description":"Alimentación eléctrica  220 V 50 Hz.                               \rPotencia de motor 710 W.  \rVelocidad en vacío 15000 RPM.\rProfundidad de rebaje 2 mm.\rAncho de cepillador 82 mm.\rGuía lateral y calibrador.\rSalida para polvo y bolsa.\rPeso 2.7 kg.\rGarantia 1 año."},"3471":{"itemCode":"3471","brand":{"name":"Tramontina","slug":"tramontina"},"invoices":1578,"finalPrice":0,"hasStock":false,"title":"Pala 4 Dientes Soldados C/Mango De Madera 74cm Tramontina 77119/344-77118/344","family":"Herramientas","category":"Herramientas Manuales","subCategory":"Palas","discount":0,"currency":"","price":0,"tax":22,"unitsPerItem":"PIEZA","unitMult":1,"relatedItems":["3452","4270","22009"],"shops":[{"cardCode":"401005","cardName":"Guglialmelli Oscar S.A.","cardFName":"Armeria Jabali","address2":"Paraguay 1109 y Rodo"}],"listOrder":"01660-000210","id":3471,"slug":"3471","code":"3471","subcategory":"Palas","images":["https://goldfarb.blob.core.windows.net/goldfarb/imagenes/3471.jpg"],"documents":[],"description":""},"3479":{"itemCode":"3479","brand":{"name":"Goldex","slug":"goldex"},"invoices":1171,"finalPrice":0,"hasStock":true,"title":"Sierra Caladora 450W P04-js60 (6)c Goldex","family":"Herramientas","category":"Herramientas Eléctricas","subCategory":"Caladoras","discount":0,"currency":"","price":0,"tax":22,"unitsPerItem":"PIEZA","unitMult":1,"relatedItems":["3452","4270","22009"],"shops":[{"cardCode":"401005","cardName":"Guglialmelli Oscar S.A.","cardFName":"Armeria Jabali","address2":"Paraguay 1109 y Rodo"}],"listOrder":"04200-000340","id":3479,"slug":"3479","code":"3479","subcategory":"Caladoras","images":["https://goldfarb.blob.core.windows.net/goldfarb/imagenes/3479.jpg","https://goldfarb.blob.core.windows.net/goldfarb/imagenes/3479-1.jpg","https://goldfarb.blob.core.windows.net/goldfarb/imagenes/3479-2.jpg","https://goldfarb.blob.core.windows.net/goldfarb/imagenes/3479-3.jpg"],"documents":[],"description":"Alimentación eléctrica  220 V 50 Hz.                               \rPotencia de motor 450 W.  \rVelocidad variable 500 - 3000 RPM.\rBase regulable hasta 45º.\rEspesor maximo de corte de madera 60mm. \rEspesor de corte maximo de metal 6mm. \rDoble aislacion. \rUso hobby.\rGarantia 1 año."},"3495":{"itemCode":"3495","brand":{"name":"Eclipse","slug":"eclipse"},"invoices":51,"finalPrice":0,"hasStock":true,"title":"Hoja P/Máquina Acero Rápido 12x1x14d Eclipse","family":"Herramientas","category":"Accesorios","subCategory":"Hojas","discount":0,"currency":"","price":0,"tax":22,"unitsPerItem":"PIEZA","unitMult":1,"relatedItems":["3452","4270","22009"],"shops":[{"cardCode":"401005","cardName":"Guglialmelli Oscar S.A.","cardFName":"Armeria Jabali","address2":"Paraguay 1109 y Rodo"}],"listOrder":"01170-000040","id":3495,"slug":"3495","code":"3495","subcategory":"Hojas","images":["https://goldfarb.blob.core.windows.net/goldfarb/imagenes/3495.jpg"],"documents":[],"description":""},"3496":{"itemCode":"3496","brand":{"name":"Eclipse","slug":"eclipse"},"invoices":156,"finalPrice":0,"hasStock":true,"title":"Hoja P/Máquina Acero Rápido 14x1x14d Eclipse","family":"Herramientas","category":"Accesorios","subCategory":"Hojas","discount":0,"currency":"","price":0,"tax":22,"unitsPerItem":"PIEZA","unitMult":1,"relatedItems":["3452","4270","22009"],"shops":[{"cardCode":"401005","cardName":"Guglialmelli Oscar S.A.","cardFName":"Armeria Jabali","address2":"Paraguay 1109 y Rodo"}],"listOrder":"01170-000060","id":3496,"slug":"3496","code":"3496","subcategory":"Hojas","images":["https://goldfarb.blob.core.windows.net/goldfarb/imagenes/3496.jpg"],"documents":[],"description":""},"3497":{"itemCode":"3497","brand":{"name":"Eclipse","slug":"eclipse"},"invoices":153,"finalPrice":0,"hasStock":true,"title":"Hoja P/Máquina Acero Rápido 16x1.1/4x10 Eclipse","family":"Herramientas","category":"Accesorios","subCategory":"Hojas","discount":0,"currency":"","price":0,"tax":22,"unitsPerItem":"PIEZA","unitMult":1,"relatedItems":["3452","4270","22009"],"shops":[{"cardCode":"401005","cardName":"Guglialmelli Oscar S.A.","cardFName":"Armeria Jabali","address2":"Paraguay 1109 y Rodo"}],"listOrder":"01170-000080","id":3497,"slug":"3497","code":"3497","subcategory":"Hojas","images":["https://goldfarb.blob.core.windows.net/goldfarb/imagenes/3497.jpg"],"documents":[],"description":""},"3498":{"itemCode":"3498","brand":{"name":"Eclipse","slug":"eclipse"},"invoices":51,"finalPrice":0,"hasStock":true,"title":"Hoja P/Máquina Acero Rápido 18x1.1/4x10d Eclipse","family":"Herramientas","category":"Accesorios","subCategory":"Hojas","discount":0,"currency":"","price":0,"tax":22,"unitsPerItem":"PIEZA","unitMult":1,"relatedItems":["3452","4270","22009"],"shops":[{"cardCode":"401005","cardName":"Guglialmelli Oscar S.A.","cardFName":"Armeria Jabali","address2":"Paraguay 1109 y Rodo"}],"listOrder":"01170-000100","id":3498,"slug":"3498","code":"3498","subcategory":"Hojas","images":["https://goldfarb.blob.core.windows.net/goldfarb/imagenes/3498.jpg"],"documents":[],"description":""},"3499":{"itemCode":"3499","brand":{"name":"Eclipse","slug":"eclipse"},"invoices":8,"finalPrice":0,"hasStock":true,"title":"Hoja P/Máquina Acero Rápido 21x1.1/2x10 Eclipse","family":"Herramientas","category":"Accesorios","subCategory":"Hojas","discount":0,"currency":"","price":0,"tax":22,"unitsPerItem":"PIEZA","unitMult":1,"relatedItems":["3452","4270","22009"],"shops":[{"cardCode":"401005","cardName":"Guglialmelli Oscar S.A.","cardFName":"Armeria Jabali","address2":"Paraguay 1109 y Rodo"}],"listOrder":"01170-000120","id":3499,"slug":"3499","code":"3499","subcategory":"Hojas","images":["https://goldfarb.blob.core.windows.net/goldfarb/imagenes/3499.jpg"],"documents":[],"description":""},"3503":{"itemCode":"3503","brand":{"name":"Goldex","slug":"goldex"},"invoices":45,"finalPrice":0,"hasStock":true,"title":"Micrometro 0-25mm Chino","family":"Herramientas","category":"Herramientas Manuales","subCategory":"Micrometros","discount":0,"currency":"","price":0,"tax":22,"unitsPerItem":"PIEZA","unitMult":1,"relatedItems":["3452","4270","22009"],"shops":[{"cardCode":"401005","cardName":"Guglialmelli Oscar S.A.","cardFName":"Armeria Jabali","address2":"Paraguay 1109 y Rodo"}],"listOrder":"01580-000040","id":3503,"slug":"3503","code":"3503","subcategory":"Micrometros","images":["https://goldfarb.blob.core.windows.net/goldfarb/imagenes/3503.jpg"],"documents":[],"description":""},"3511":{"itemCode":"3511","brand":{"name":"Goldex","slug":"goldex"},"invoices":461,"finalPrice":0,"hasStock":false,"title":"Lijadora De Banda 800W 76x533mm HW-PS1120 Goldex","family":"Herramientas","category":"Herramientas Eléctricas","subCategory":"Lijadoras","discount":0,"currency":"","price":0,"tax":22,"unitsPerItem":"PIEZA","unitMult":1,"relatedItems":["3452","4270","22009"],"shops":[{"cardCode":"401005","cardName":"Guglialmelli Oscar S.A.","cardFName":"Armeria Jabali","address2":"Paraguay 1109 y Rodo"}],"listOrder":"04200-000500","id":3511,"slug":"3511","code":"3511","subcategory":"Lijadoras","images":["https://goldfarb.blob.core.windows.net/goldfarb/imagenes/3511.jpg"],"documents":["https://goldfarb.blob.core.windows.net/goldfarb/documentos/3511.pdf"],"description":"Alimentación eléctrica  220 V 50 Hz.                               \rPotencia de motor 800 W.  \rVelocidad en vacio 2000 RPM.\rMedida de lija 533 x 75mm.\rSalida para aspiración de polvo y bolsa.\rUso hobby.\rGarantia 1 año"},"3522":{"itemCode":"3522","brand":{"name":"Goldex","slug":"goldex"},"invoices":429,"finalPrice":0,"hasStock":true,"title":"Lustra Lijadora 1200W 7'' 2 Velocidades P04-PBO180 Goldex","family":"Herramientas","category":"Herramientas Eléctricas","subCategory":"Lustralijadoras","discount":0,"currency":"","price":0,"tax":22,"unitsPerItem":"PIEZA","unitMult":1,"relatedItems":["3452","4270","22009"],"shops":[{"cardCode":"401005","cardName":"Guglialmelli Oscar S.A.","cardFName":"Armeria Jabali","address2":"Paraguay 1109 y Rodo"}],"listOrder":"04200-000550","id":3522,"slug":"3522","code":"3522","subcategory":"Lustralijadoras","images":["https://goldfarb.blob.core.windows.net/goldfarb/imagenes/3522.jpg"],"documents":[],"description":"Alimentación eléctrica  220 V 50 Hz.                               \rPotencia de motor 1200 W.  \rVelocidad variable 600 - 3000 RPM.\rDisco de 180mm.\rIncluye plato de apoyo y bonete de corderito.\rUso hobby.\rGarantia 1 año"},"3525":{"itemCode":"3525","brand":{"name":"Tramontina","slug":"tramontina"},"invoices":1595,"finalPrice":0,"hasStock":true,"title":"Kit P/Jardín 3Pz. Tramontina 78102/801-J729-78102/701","family":"Herramientas","category":"Herramientas Jardín","subCategory":"Juegos de Jardín","discount":0,"currency":"","price":0,"tax":22,"unitsPerItem":"JUEGO","unitMult":1,"relatedItems":["3452","4270","22009"],"shops":[{"cardCode":"401005","cardName":"Guglialmelli Oscar S.A.","cardFName":"Armeria Jabali","address2":"Paraguay 1109 y Rodo"}],"listOrder":"01230-000110","id":3525,"slug":"3525","code":"3525","subcategory":"Juegos de Jardín","images":["https://goldfarb.blob.core.windows.net/goldfarb/imagenes/3525.jpg"],"documents":[],"description":""},"3528":{"itemCode":"3528","brand":{"name":"Aleman","slug":"aleman"},"invoices":23,"finalPrice":0,"hasStock":true,"title":"Marcar Letras Golpe 5mm","family":"Herramientas","category":"Herramientas Manuales","subCategory":"Marcadores","discount":0,"currency":"","price":0,"tax":22,"unitsPerItem":"JUEGO","unitMult":1,"relatedItems":["3452","4270","22009"],"shops":[{"cardCode":"401005","cardName":"Guglialmelli Oscar S.A.","cardFName":"Armeria Jabali","address2":"Paraguay 1109 y Rodo"}],"listOrder":"01240-000050","id":3528,"slug":"3528","code":"3528","subcategory":"Marcadores","images":["https://goldfarb.blob.core.windows.net/goldfarb/imagenes/3528.jpg"],"documents":[],"description":""},"3529":{"itemCode":"3529","brand":{"name":"Aleman","slug":"aleman"},"invoices":28,"finalPrice":0,"hasStock":true,"title":"Marcar Letras Golpe 6mm","family":"Herramientas","category":"Herramientas Manuales","subCategory":"Marcadores","discount":0,"currency":"","price":0,"tax":22,"unitsPerItem":"JUEGO","unitMult":1,"relatedItems":["3452","4270","22009"],"shops":[{"cardCode":"401005","cardName":"Guglialmelli Oscar S.A.","cardFName":"Armeria Jabali","address2":"Paraguay 1109 y Rodo"}],"listOrder":"01240-000060","id":3529,"slug":"3529","code":"3529","subcategory":"Marcadores","images":["https://goldfarb.blob.core.windows.net/goldfarb/imagenes/3529.jpg"],"documents":[],"description":""},"3531":{"itemCode":"3531","brand":{"name":"Aleman","slug":"aleman"},"invoices":13,"finalPrice":0,"hasStock":true,"title":"Marcar Letras Golpe 10mm","family":"Herramientas","category":"Herramientas Manuales","subCategory":"Marcadores","discount":0,"currency":"","price":0,"tax":22,"unitsPerItem":"JUEGO","unitMult":1,"relatedItems":["3452","4270","22009"],"shops":[{"cardCode":"401005","cardName":"Guglialmelli Oscar S.A.","cardFName":"Armeria Jabali","address2":"Paraguay 1109 y Rodo"}],"listOrder":"01240-000080","id":3531,"slug":"3531","code":"3531","subcategory":"Marcadores","images":["https://goldfarb.blob.core.windows.net/goldfarb/imagenes/3531.jpg"],"documents":[],"description":""},"3532":{"itemCode":"3532","brand":{"name":"Aleman","slug":"aleman"},"invoices":16,"finalPrice":0,"hasStock":true,"title":"Marcar Letras Golpe 12mm","family":"Herramientas","category":"Herramientas Manuales","subCategory":"Marcadores","discount":0,"currency":"","price":0,"tax":22,"unitsPerItem":"JUEGO","unitMult":1,"relatedItems":["3452","4270","22009"],"shops":[{"cardCode":"401005","cardName":"Guglialmelli Oscar S.A.","cardFName":"Armeria Jabali","address2":"Paraguay 1109 y Rodo"}],"listOrder":"01240-000090","id":3532,"slug":"3532","code":"3532","subcategory":"Marcadores","images":["https://goldfarb.blob.core.windows.net/goldfarb/imagenes/3532.jpg"],"documents":[],"description":""},"3556":{"itemCode":"3556","brand":{"name":"Goldex","slug":"goldex"},"invoices":2859,"finalPrice":0,"hasStock":true,"title":"Amoladora Angular 4.1/2'' 650W Reforzada P04-AG115T2 Goldex","family":"Herramientas","category":"Herramientas Eléctricas","subCategory":"Amoladoras","discount":0,"currency":"","price":0,"tax":22,"unitsPerItem":"PIEZA","unitMult":1,"relatedItems":["3452","4270","22009"],"shops":[{"cardCode":"401005","cardName":"Guglialmelli Oscar S.A.","cardFName":"Armeria Jabali","address2":"Paraguay 1109 y Rodo"}],"listOrder":"04200-000130","id":3556,"slug":"3556","code":"3556","subcategory":"Amoladoras","images":["https://goldfarb.blob.core.windows.net/goldfarb/imagenes/3556.jpg","https://goldfarb.blob.core.windows.net/goldfarb/imagenes/3556-1.jpg","https://goldfarb.blob.core.windows.net/goldfarb/imagenes/3556-2.jpg","https://goldfarb.blob.core.windows.net/goldfarb/imagenes/3556-3.jpg"],"documents":[],"description":"Alimentación eléctrica  220 V 50 Hz.                               \rPotencia de motor 650 W.  \rVelocidad en vacio 11000 RPM.\rPara disco de 115 mm con buje M14.\rModelo reforzado, mayor vida útil.\rUso hobby. \rGarantia 1 año."},"3557":{"itemCode":"3557","brand":{"name":"Goldex","slug":"goldex"},"invoices":1434,"finalPrice":0,"hasStock":true,"title":"Taladro C/Percutor 13mm 500W C/Herramientas HW-IDK01/02 Goldex","family":"Herramientas","category":"Herramientas Eléctricas","subCategory":"Kits","discount":0,"currency":"","price":0,"tax":22,"unitsPerItem":"PIEZA","unitMult":1,"relatedItems":["3452","4270","22009"],"shops":[{"cardCode":"401005","cardName":"Guglialmelli Oscar S.A.","cardFName":"Armeria Jabali","address2":"Paraguay 1109 y Rodo"}],"listOrder":"04200-000770","id":3557,"slug":"3557","code":"3557","subcategory":"Kits","images":["https://goldfarb.blob.core.windows.net/goldfarb/imagenes/3557.jpg","https://goldfarb.blob.core.windows.net/goldfarb/imagenes/3557-1.jpg","https://goldfarb.blob.core.windows.net/goldfarb/imagenes/3557-2.jpg","https://goldfarb.blob.core.windows.net/goldfarb/imagenes/3557-3.jpg","https://goldfarb.blob.core.windows.net/goldfarb/imagenes/3557-4.jpg"],"documents":[],"description":"Alimentación eléctrica  220 V 50 Hz.                               \rPotencia de motor 500 W.  \rVelocidad variable y reversa 0 - 2800 RPM.\rCapacidad de mandril 1.5 - 13 mm (1/2\").\rIncluye: mechas metal; madera y mamposteria; trincheta; martillo; destornilladores; alicates; llave ajustable;bocallaves; piedras montadas; etc.\rMontado sobre rulemanes.\rDoble aislación.\rUso hobby. \rGarantia 1 año."},"3558":{"itemCode":"3558","brand":{"name":"Goldex","slug":"goldex"},"invoices":1491,"finalPrice":0,"hasStock":false,"title":"Taladro C/Percutor 13mm 500W C/Accesorios En Blister Goldex","family":"Herramientas","category":"Herramientas Eléctricas","subCategory":"Kits","discount":0,"currency":"","price":0,"tax":22,"unitsPerItem":"PIEZA","unitMult":1,"relatedItems":["3452","4270","22009"],"shops":[{"cardCode":"401005","cardName":"Guglialmelli Oscar S.A.","cardFName":"Armeria Jabali","address2":"Paraguay 1109 y Rodo"}],"listOrder":"04200-000780","id":3558,"slug":"3558","code":"3558","subcategory":"Kits","images":["https://goldfarb.blob.core.windows.net/goldfarb/imagenes/3558.jpg"],"documents":[],"description":"MANDRIL : 13MM \rPOTENCIA : 500W \rVELOCIDAD : 0 A 2800 RPM \rACCESORIOS QUE LO COMPONEN : \rTACOS DE FIJACION : 5MM - 6MM - 8MM - 10MM .\rMECHAS MAMPOSTERIA : 3MM-4MM-5MM-6MM-8MM MECHAS ALTA VELOCIDAD : 3MM-4MM-5MM-6MM-8MM MECHAS PARA MADERA:1.5MM-2MM-3MM-4MM-5MM-6MM-8MM \rPUNTAS PARA ATORNILLAR :\rPLANO 4MM - 5MM - 6MM                          \rPHILLIPS : PH 1 - PH 2\rPOZIDRIV : 1 Y 2"},"3559":{"itemCode":"3559","brand":{"name":"Goldex","slug":"goldex"},"invoices":1367,"finalPrice":0,"hasStock":true,"title":"Amoladora Angular 4.1/2'' 500W En Blister PAG115A Goldex","family":"Herramientas","category":"Herramientas Eléctricas","subCategory":"Amoladoras","discount":0,"currency":"","price":0,"tax":22,"unitsPerItem":"KIT","unitMult":1,"relatedItems":["3452","4270","22009"],"shops":[{"cardCode":"401005","cardName":"Guglialmelli Oscar S.A.","cardFName":"Armeria Jabali","address2":"Paraguay 1109 y Rodo"}],"listOrder":"04200-000120","id":3559,"slug":"3559","code":"3559","subcategory":"Amoladoras","images":["https://goldfarb.blob.core.windows.net/goldfarb/imagenes/3559.jpg","https://goldfarb.blob.core.windows.net/goldfarb/imagenes/3559-1.jpg"],"documents":[],"description":"Alimentación eléctrica  220 V 50 Hz.                               \rPotencia de motor 550 W.  \rVelocidad en vacio 10000 RPM.\rPara disco de 115 mm con buje M14.\rAccesorios:\r- Disco de apoyo de goma para lijas circulares.\r- Cepillo circular plano bronceado.\r- 3 discos de lijar, gr. 60 , 80 y 100.\r- 1 disco corte metal.\r- 1 disco desbaste metal.\r\rUso hobby. \rGarantia 1 año.\r\r\r* 1 DISCO DE LIJA GR. 60 ; 1 GR. 80 Y 1 GR. 100\r* 1 DISCO CORTE METAL 4½''\r* 1 DISCO DESBASTE METAL 4½''"},"3563":{"itemCode":"3563","brand":{"name":"Goldex","slug":"goldex"},"invoices":97,"finalPrice":0,"hasStock":true,"title":"Cargador De Batería 12V (Base+Transformador) P/Taladro Atorn. HW-CDL1101 Goldex","family":"Herramientas","category":"Herramientas Eléctricas","subCategory":"Cargadores","discount":0,"currency":"","price":0,"tax":22,"unitsPerItem":"PIEZA","unitMult":1,"relatedItems":["3452","4270","22009"],"shops":[{"cardCode":"401005","cardName":"Guglialmelli Oscar S.A.","cardFName":"Armeria Jabali","address2":"Paraguay 1109 y Rodo"}],"listOrder":"04215-000180","id":3563,"slug":"3563","code":"3563","subcategory":"Cargadores","images":["https://goldfarb.blob.core.windows.net/goldfarb/imagenes/3563.jpg"],"documents":[],"description":"Para carga de baterías cod. 3494"},"3564":{"itemCode":"3564","brand":{"name":"Goldex","slug":"goldex"},"invoices":2811,"finalPrice":0,"hasStock":true,"title":"Taladro C/Percutor 13mm 710W Ergonómico P01-ID13E Goldex","family":"Herramientas","category":"Herramientas Eléctricas","subCategory":"Taladros","discount":0,"currency":"","price":0,"tax":22,"unitsPerItem":"PIEZA","unitMult":1,"relatedItems":["3452","4270","22009"],"shops":[{"cardCode":"401005","cardName":"Guglialmelli Oscar S.A.","cardFName":"Armeria Jabali","address2":"Paraguay 1109 y Rodo"}],"listOrder":"04200-000790","id":3564,"slug":"3564","code":"3564","subcategory":"Taladros","images":["https://goldfarb.blob.core.windows.net/goldfarb/imagenes/3564.jpg","https://goldfarb.blob.core.windows.net/goldfarb/imagenes/3564-1.jpg","https://goldfarb.blob.core.windows.net/goldfarb/imagenes/3564-2.jpg","https://goldfarb.blob.core.windows.net/goldfarb/imagenes/3564-3.jpg"],"documents":[],"description":"Alimentación eléctrica  220 V 50 Hz.                               \rPotencia de motor 710 W.  \rVelocidad variable y reversa 0 - 2800 RPM.\rCapacidad de mandril 1.5 - 13 mm (1/2\").\rEmpuñadura con regla para profundidad de perforación.\rMontado sobre rulemanes.\rDoble aislación.\rUso hobby. \rGarantia 1 año."},"3571":{"itemCode":"3571","brand":{"name":"Goldex","slug":"goldex"},"invoices":1711,"finalPrice":0,"hasStock":true,"title":"Bomba Sumergible De Plástico QSBJH400 1/2Hp Goldex","family":"Herramientas","category":"Herramientas Eléctricas","subCategory":"Bombas","discount":0,"currency":"","price":0,"tax":22,"unitsPerItem":"PIEZA","unitMult":1,"relatedItems":["3452","4270","22009"],"shops":[{"cardCode":"401005","cardName":"Guglialmelli Oscar S.A.","cardFName":"Armeria Jabali","address2":"Paraguay 1109 y Rodo"}],"listOrder":"04200-000310","id":3571,"slug":"3571","code":"3571","subcategory":"Bombas","images":["https://goldfarb.blob.core.windows.net/goldfarb/imagenes/3571.jpg"],"documents":[],"description":"Potencia 375W (1/2HP)\rMotor monofásico - 220v/50Hz.\rPara agua limpia y fabricada en plástico.\rElevacion máxima 5Mts.\rCaudal máximo 7.000 LTS./H. \rIncluye automático de nivel"},"3572":{"itemCode":"3572","brand":{"name":"Goldex","slug":"goldex"},"invoices":640,"finalPrice":0,"hasStock":true,"title":"Bomba Sumergible De Acero Inoxidable  QSBJH750 1Hp Goldex","family":"Herramientas","category":"Herramientas Eléctricas","subCategory":"Bombas","discount":0,"currency":"","price":0,"tax":22,"unitsPerItem":"PIEZA","unitMult":1,"relatedItems":["3452","4270","22009"],"shops":[{"cardCode":"401005","cardName":"Guglialmelli Oscar S.A.","cardFName":"Armeria Jabali","address2":"Paraguay 1109 y Rodo"}],"listOrder":"04200-000300","id":3572,"slug":"3572","code":"3572","subcategory":"Bombas","images":["https://goldfarb.blob.core.windows.net/goldfarb/imagenes/3572.jpg"],"documents":[],"description":"Potencia 750W (1HP)\rMotor monofásico - 220v/50Hz.\rPara agua limpia y fabricada en acero inoxidable.\rElevacion máxima 8Mts.\rCaudal máximo  10.500 LTS./H. \rIncluye automático de nivel"},"3578":{"itemCode":"3578","brand":{"name":"Goldex","slug":"goldex"},"invoices":1797,"finalPrice":0,"hasStock":false,"title":"Bomba Periférica LDB35/PPV-Q60 1/2Hp Goldex","family":"Herramientas","category":"Herramientas Eléctricas","subCategory":"Bombas","discount":0,"currency":"","price":0,"tax":22,"unitsPerItem":"PIEZA","unitMult":1,"relatedItems":["3452","4270","22009"],"shops":[{"cardCode":"401005","cardName":"Guglialmelli Oscar S.A.","cardFName":"Armeria Jabali","address2":"Paraguay 1109 y Rodo"}],"listOrder":"04200-000290","id":3578,"slug":"3578","code":"3578","subcategory":"Bombas","images":["https://goldfarb.blob.core.windows.net/goldfarb/imagenes/3578.jpg"],"documents":[],"description":"Potencia 375W (1/2HP)\rMotor monofásico - 220v/50Hz.\rPERIFERICA y  PARA AGUA LIMPIA \rSUCCION 7 MTS. \rCAUDAL 2400 LTS./HORA \rPRESION 3.5 BAR"},"3579":{"itemCode":"3579","brand":{"name":"Goldex","slug":"goldex"},"invoices":885,"finalPrice":0,"hasStock":false,"title":"Bomba Centrífuga SCM42 3/4Hp Goldex","family":"Herramientas","category":"Herramientas Eléctricas","subCategory":"Bombas","discount":0,"currency":"","price":0,"tax":22,"unitsPerItem":"PIEZA","unitMult":1,"relatedItems":["3452","4270","22009"],"shops":[{"cardCode":"401005","cardName":"Guglialmelli Oscar S.A.","cardFName":"Armeria Jabali","address2":"Paraguay 1109 y Rodo"}],"listOrder":"04200-000270","id":3579,"slug":"3579","code":"3579","subcategory":"Bombas","images":["https://goldfarb.blob.core.windows.net/goldfarb/imagenes/3579.jpg"],"documents":[],"description":"Potencia 550W (3/4HP)\rMotor monofásico - 220v/50Hz.\rCENTRIFUGA y PARA AGUA LIMPIA\rSUCCION HASTA 7 MTS \rCAUDAL 4200 LTS./H \rPRESION 3.5 BAR"},"3580":{"itemCode":"3580","brand":{"name":"Goldex","slug":"goldex"},"invoices":832,"finalPrice":0,"hasStock":true,"title":"Bomba Centrífuga SCM50 1.1/4 Hp Goldex","family":"Herramientas","category":"Herramientas Eléctricas","subCategory":"Bombas","discount":0,"currency":"","price":0,"tax":22,"unitsPerItem":"PIEZA","unitMult":1,"relatedItems":["3452","4270","22009"],"shops":[{"cardCode":"401005","cardName":"Guglialmelli Oscar S.A.","cardFName":"Armeria Jabali","address2":"Paraguay 1109 y Rodo"}],"listOrder":"04200-000280","id":3580,"slug":"3580","code":"3580","subcategory":"Bombas","images":["https://goldfarb.blob.core.windows.net/goldfarb/imagenes/3580.jpg"],"documents":[],"description":"Potencia 940W (1.1/4 HP)\rMotor monofásico - 220v/50Hz.\rCENTRIFUGA y PARA AGUA LIMPIA \rSUCCION 7 MTS. \rCAUDAL 4980 LTS./H \rPRESION 4.0 BAR"},"3582":{"itemCode":"3582","brand":{"name":"Goldex","slug":"goldex"},"invoices":181,"finalPrice":0,"hasStock":false,"title":"Mandril 1/2'' C/Llave y Adaptador SDS Plus P/Rotomartillo 26mm Goldex","family":"Herramientas","category":"Accesorios","subCategory":"Mandriles","discount":0,"currency":"","price":0,"tax":22,"unitsPerItem":"PIEZA","unitMult":1,"relatedItems":["3452","4270","22009"],"shops":[{"cardCode":"401005","cardName":"Guglialmelli Oscar S.A.","cardFName":"Armeria Jabali","address2":"Paraguay 1109 y Rodo"}],"listOrder":"04205-000790","id":3582,"slug":"3582","code":"3582","subcategory":"Mandriles","images":["https://goldfarb.blob.core.windows.net/goldfarb/imagenes/3582.jpg"],"documents":[],"description":""},"3584":{"itemCode":"3584","brand":{"name":"Goldex","slug":"goldex"},"invoices":2104,"finalPrice":0,"hasStock":true,"title":"Amoladora Angular 4.1/2'' 860W P02-AG115E  Blindada Goldex","family":"Herramientas","category":"Herramientas Eléctricas","subCategory":"Amoladoras","discount":0,"currency":"","price":0,"tax":22,"unitsPerItem":"PIEZA","unitMult":1,"relatedItems":["3452","4270","22009"],"shops":[{"cardCode":"401005","cardName":"Guglialmelli Oscar S.A.","cardFName":"Armeria Jabali","address2":"Paraguay 1109 y Rodo"}],"listOrder":"04200-000140","id":3584,"slug":"3584","code":"3584","subcategory":"Amoladoras","images":["https://goldfarb.blob.core.windows.net/goldfarb/imagenes/3584.jpg","https://goldfarb.blob.core.windows.net/goldfarb/imagenes/3584-1.jpg","https://goldfarb.blob.core.windows.net/goldfarb/imagenes/3584-2.jpg","https://goldfarb.blob.core.windows.net/goldfarb/imagenes/3584-3.jpg"],"documents":[],"description":"Alimentación eléctrica  220 V 50 Hz.                               \rPotencia de motor 860 W.  \rVelocidad en vacio 11000 RPM.\rPara disco de 115 mm con buje M14.\rInterruptor blindado, mayor vida útil.\rUso hobby. \rGarantia 1 año."},"3593":{"itemCode":"3593","brand":{"name":"Sonca","slug":"sonca"},"invoices":5,"finalPrice":0,"hasStock":true,"title":"Lamparita Hpr53 P/Lint.H500 Sonca 3 Elem","family":"Herramientas","category":"Iluminación","subCategory":"Lamparitas","discount":0,"currency":"","price":0,"tax":22,"unitsPerItem":"PIEZA","unitMult":1,"relatedItems":["3452","4270","22009"],"shops":[{"cardCode":"401005","cardName":"Guglialmelli Oscar S.A.","cardFName":"Armeria Jabali","address2":"Paraguay 1109 y Rodo"}],"listOrder":"01270-000120","id":3593,"slug":"3593","code":"3593","subcategory":"Lamparitas","images":["https://goldfarb.blob.core.windows.net/goldfarb/imagenes/3593.jpg"],"documents":[],"description":""},"3600":{"itemCode":"3600","brand":{"name":"Goldex","slug":"goldex"},"invoices":1890,"finalPrice":0,"hasStock":true,"title":"Pistola De Calor 2000W HAG2000C Goldex","family":"Herramientas","category":"Herramientas Eléctricas","subCategory":"Pistolas","discount":0,"currency":"","price":0,"tax":22,"unitsPerItem":"PIEZA","unitMult":1,"relatedItems":["3452","4270","22009"],"shops":[{"cardCode":"401005","cardName":"Guglialmelli Oscar S.A.","cardFName":"Armeria Jabali","address2":"Paraguay 1109 y Rodo"}],"listOrder":"04200-000920","id":3600,"slug":"3600","code":"3600","subcategory":"Pistolas","images":["https://goldfarb.blob.core.windows.net/goldfarb/imagenes/3600.jpg","https://goldfarb.blob.core.windows.net/goldfarb/imagenes/3600-1.jpg","https://goldfarb.blob.core.windows.net/goldfarb/imagenes/3600-2.jpg","https://goldfarb.blob.core.windows.net/goldfarb/imagenes/3600-3.jpg"],"documents":[],"description":"Alimentación eléctrica  220 V 50 Hz.                               \rPotencia de motor 2000 W.  \rDos posiciones de temperatura 350 C y 600º C.\rGarantia  1 año."},"3719":{"itemCode":"3719","brand":{"name":"Mustad","slug":"mustad"},"invoices":27,"finalPrice":0,"hasStock":true,"title":"Herraduras 4Pz. P/Mano Maroñas Nº4 Aluminio Mustad","family":"Herramientas","category":"Prevención y Seguridad","subCategory":"Herraduras","discount":0,"currency":"","price":0,"tax":22,"unitsPerItem":"CAJA","unitMult":1,"relatedItems":["3452","4270","22009"],"shops":[{"cardCode":"401005","cardName":"Guglialmelli Oscar S.A.","cardFName":"Armeria Jabali","address2":"Paraguay 1109 y Rodo"}],"listOrder":"01050-000620","id":3719,"slug":"3719","code":"3719","subcategory":"Herraduras","images":["https://goldfarb.blob.core.windows.net/goldfarb/imagenes/3719.jpg"],"documents":[],"description":""},"3720":{"itemCode":"3720","brand":{"name":"Mustad","slug":"mustad"},"invoices":24,"finalPrice":0,"hasStock":true,"title":"Herraduras 4Pz. P/Pata Maroñas Nº4 Aluminio Mustad","family":"Herramientas","category":"Prevención y Seguridad","subCategory":"Herraduras","discount":0,"currency":"","price":0,"tax":22,"unitsPerItem":"CAJA","unitMult":1,"relatedItems":["3452","4270","22009"],"shops":[{"cardCode":"401005","cardName":"Guglialmelli Oscar S.A.","cardFName":"Armeria Jabali","address2":"Paraguay 1109 y Rodo"}],"listOrder":"01050-000630","id":3720,"slug":"3720","code":"3720","subcategory":"Herraduras","images":["https://goldfarb.blob.core.windows.net/goldfarb/imagenes/3720.jpg"],"documents":[],"description":""},"3721":{"itemCode":"3721","brand":{"name":"Goldex","slug":"goldex"},"invoices":65,"finalPrice":0,"hasStock":true,"title":"Carbones P/Taladro 16mm Goldex","family":"Herramientas","category":"Repuestos","subCategory":"Taladros","discount":0,"currency":"","price":0,"tax":22,"unitsPerItem":"JUEGO","unitMult":1,"relatedItems":["3452","4270","22009"],"shops":[{"cardCode":"401005","cardName":"Guglialmelli Oscar S.A.","cardFName":"Armeria Jabali","address2":"Paraguay 1109 y Rodo"}],"listOrder":"04220-000260","id":3721,"slug":"3721","code":"3721","subcategory":"Taladros","images":["https://goldfarb.blob.core.windows.net/goldfarb/imagenes/3721.jpg"],"documents":[],"description":""},"3895":{"itemCode":"3895","brand":{"name":"Eclipse","slug":"eclipse"},"invoices":65,"finalPrice":0,"hasStock":true,"title":"Arco Sierra 18tnd Eclipse","family":"Herramientas","category":"Herramientas Manuales","subCategory":"Arcos","discount":0,"currency":"","price":0,"tax":22,"unitsPerItem":"PIEZA","unitMult":1,"relatedItems":["3452","4270","22009"],"shops":[{"cardCode":"401005","cardName":"Guglialmelli Oscar S.A.","cardFName":"Armeria Jabali","address2":"Paraguay 1109 y Rodo"}],"listOrder":"00140-000130","id":3895,"slug":"3895","code":"3895","subcategory":"Arcos","images":["https://goldfarb.blob.core.windows.net/goldfarb/imagenes/3895.jpg"],"documents":[],"description":""},"3912":{"itemCode":"3912","brand":{"name":"Bahco","slug":"bahco"},"invoices":1533,"finalPrice":0,"hasStock":true,"title":"Lima Motosierra X 3 Unid. 8''x 3/16'' Bahco","family":"Herramientas","category":"Accesorios","subCategory":"Limas","discount":0,"currency":"","price":0,"tax":22,"unitsPerItem":"BLIST","unitMult":1,"relatedItems":["3452","4270","22009"],"shops":[{"cardCode":"401005","cardName":"Guglialmelli Oscar S.A.","cardFName":"Armeria Jabali","address2":"Paraguay 1109 y Rodo"}],"listOrder":"04435-000260","id":3912,"slug":"3912","code":"3912","subcategory":"Limas","images":["https://goldfarb.blob.core.windows.net/goldfarb/imagenes/3912.jpg"],"documents":[],"description":"Lima redonda para afilar el dentado de las cadenas de motosierra; sin cabo.\rLas limas vienen presentadas en un blister especial de tres en tres, con perforaciones para una fácil separación individual."},"3913":{"itemCode":"3913","brand":{"name":"Bahco","slug":"bahco"},"invoices":906,"finalPrice":0,"hasStock":true,"title":"Lima Motosierra X 3 Unid. 8''x 7/32'' Bahco","family":"Herramientas","category":"Accesorios","subCategory":"Limas","discount":0,"currency":"","price":0,"tax":22,"unitsPerItem":"BLIST","unitMult":1,"relatedItems":["3452","4270","22009"],"shops":[{"cardCode":"401005","cardName":"Guglialmelli Oscar S.A.","cardFName":"Armeria Jabali","address2":"Paraguay 1109 y Rodo"}],"listOrder":"04435-000250","id":3913,"slug":"3913","code":"3913","subcategory":"Limas","images":["https://goldfarb.blob.core.windows.net/goldfarb/imagenes/3913.jpg"],"documents":[],"description":"Lima redonda para afilar el dentado de las cadenas de motosierra; sin cabo.\rLas limas vienen presentadas en un blister especial de tres en tres, con perforaciones para una fácil separación individual."},"3914":{"itemCode":"3914","brand":{"name":"Bahco","slug":"bahco"},"invoices":1599,"finalPrice":0,"hasStock":true,"title":"Lima Motosierra X 3 Unid. 8''x 5/32'' Bahco","family":"Herramientas","category":"Accesorios","subCategory":"Limas","discount":0,"currency":"","price":0,"tax":22,"unitsPerItem":"BLIST","unitMult":1,"relatedItems":["3452","4270","22009"],"shops":[{"cardCode":"401005","cardName":"Guglialmelli Oscar S.A.","cardFName":"Armeria Jabali","address2":"Paraguay 1109 y Rodo"}],"listOrder":"04435-000240","id":3914,"slug":"3914","code":"3914","subcategory":"Limas","images":["https://goldfarb.blob.core.windows.net/goldfarb/imagenes/3914.jpg"],"documents":[],"description":"Lima redonda para afilar el dentado de las cadenas de motosierra; sin cabo.\rLas limas vienen presentadas en un blister especial de tres en tres, con perforaciones para una fácil separación individual."},"3926":{"itemCode":"3926","brand":{"name":"Tramontina","slug":"tramontina"},"invoices":464,"finalPrice":0,"hasStock":true,"title":"Llana Plástica C/Esponja 25x15cm 77385/118 Tramontina","family":"Herramientas","category":"Herramientas Manuales","subCategory":"Llanas","discount":0,"currency":"","price":0,"tax":22,"unitsPerItem":"PIEZA","unitMult":1,"relatedItems":["3452","4270","22009"],"shops":[{"cardCode":"401005","cardName":"Guglialmelli Oscar S.A.","cardFName":"Armeria Jabali","address2":"Paraguay 1109 y Rodo"}],"listOrder":"01340-000240","id":3926,"slug":"3926","code":"3926","subcategory":"Llanas","images":["https://goldfarb.blob.core.windows.net/goldfarb/imagenes/3926.jpg"],"documents":[],"description":""},"3927":{"itemCode":"3927","brand":{"name":"Tramontina","slug":"tramontina"},"invoices":349,"finalPrice":0,"hasStock":true,"title":"Llana Metálica Lisa 28x12 77370/115 Tramontina","family":"Herramientas","category":"Herramientas Manuales","subCategory":"Llanas","discount":0,"currency":"","price":0,"tax":22,"unitsPerItem":"PIEZA","unitMult":1,"relatedItems":["3452","4270","22009"],"shops":[{"cardCode":"401005","cardName":"Guglialmelli Oscar S.A.","cardFName":"Armeria Jabali","address2":"Paraguay 1109 y Rodo"}],"listOrder":"01340-000230","id":3927,"slug":"3927","code":"3927","subcategory":"Llanas","images":["https://goldfarb.blob.core.windows.net/goldfarb/imagenes/3927.jpg"],"documents":[],"description":""},"3928":{"itemCode":"3928","brand":{"name":"Tramontina","slug":"tramontina"},"invoices":627,"finalPrice":0,"hasStock":true,"title":"Llana Metálica Dentada 27x12cm 77375/115 Tramontina","family":"Herramientas","category":"Herramientas Manuales","subCategory":"Llanas","discount":0,"currency":"","price":0,"tax":22,"unitsPerItem":"PIEZA","unitMult":1,"relatedItems":["3452","4270","22009"],"shops":[{"cardCode":"401005","cardName":"Guglialmelli Oscar S.A.","cardFName":"Armeria Jabali","address2":"Paraguay 1109 y Rodo"}],"listOrder":"01340-000220","id":3928,"slug":"3928","code":"3928","subcategory":"Llanas","images":["https://goldfarb.blob.core.windows.net/goldfarb/imagenes/3928.jpg"],"documents":[],"description":""},"3941":{"itemCode":"3941","brand":{"name":"Pacetta","slug":"pacetta"},"invoices":39,"finalPrice":0,"hasStock":true,"title":"Llana Metálica Lisa Cabo Abierto 120x255mm 2075 Pacetta","family":"Herramientas","category":"Herramientas Manuales","subCategory":"Llanas","discount":0,"currency":"","price":0,"tax":22,"unitsPerItem":"PIEZA","unitMult":1,"relatedItems":["3452","4270","22009"],"shops":[{"cardCode":"401005","cardName":"Guglialmelli Oscar S.A.","cardFName":"Armeria Jabali","address2":"Paraguay 1109 y Rodo"}],"listOrder":"01340-000260","id":3941,"slug":"3941","code":"3941","subcategory":"Llanas","images":["https://goldfarb.blob.core.windows.net/goldfarb/imagenes/3941.jpg"],"documents":[],"description":""},"3945":{"itemCode":"3945","brand":{"name":"Eclipse","slug":"eclipse"},"invoices":12,"finalPrice":0,"hasStock":true,"title":"Arco Sierra 70-22Tr Empuñadura Goma Eclipse","family":"Herramientas","category":"Herramientas Manuales","subCategory":"Arcos","discount":0,"currency":"","price":0,"tax":22,"unitsPerItem":"PIEZA","unitMult":1,"relatedItems":["3452","4270","22009"],"shops":[{"cardCode":"401005","cardName":"Guglialmelli Oscar S.A.","cardFName":"Armeria Jabali","address2":"Paraguay 1109 y Rodo"}],"listOrder":"00140-000140","id":3945,"slug":"3945","code":"3945","subcategory":"Arcos","images":["https://goldfarb.blob.core.windows.net/goldfarb/imagenes/3945.jpg"],"documents":[],"description":""}}